Workbook

Sheet Инструкция
A1: РАСЧЁТ ЗАРПЛАТЫ · Alisher Karimov · Constantia Intensivpflege GmbH
B3: Источники: Arbeitsvertrag от 01.08.2026 (§§ 1–19), EzB от 13.07.2026, ArbZG, EStG (§ 3b, § 32a, § 39b), SvEV, BUrlG, EFZG, PflegeArbbV
A5: ЛИСТЫ ФАЙЛА
B6: Настройки | C6: Все параметры: ставка, надбавки, время смен, лимит переработки, налоговый класс. Жёлтое — можно менять.
B7: Dienstplan | C7: График месяца: ND / TD / FREI, статус (Arbeit / Urlaub / Krank), «x» = Eingesprungen. Сейчас заполнен СЕНТЯБРЬ 2026: 15 TD + 3 ND = 18 смен = 216 ч.
B8: Расчёт | C8: Брутто, надбавки, счёт часов, соцвзносы, налоги, нетто.
B9: Lohnsteuer | C9: Подоходный налог по методу официального Programmablaufplan.
B10: Контроль ArbZG | C10: Проверка по закону о рабочем времени.
B11: Права и риски | C11: Что в договоре есть, чего нет, и что из этого следует.
B12: Feiertage | C12: Праздники Нижней Саксонии 2026/2027.
B13: Мои данные | C13: Пустые поля для SV-Nummer, Steuer-ID и т.д. Заполни у себя — файл лежит в ПУБЛИЧНОМ репозитории GitHub.
B14: Год | C14: Сводка по 12 месяцам и счёт переносимых часов.
B15: Сверка с расчёткой | C15: Реальные Lohnabrechnung 07/2026 и 08/2026, разобранные построчно, и проверка каждой суммы. Август зафиксирован числами и не меняется при смене месяца.
A17: ВАЖНО ПРО ФОРМАТ
B18: Время смен — это ЧИСЛА | C18: 20 = 20:00, 8 = 08:00, 6,5 = 06:30. Так сделано специально: Numbers на iPhone/Mac ломает формулы с настоящими значениями времени.
B19: Numbers убирает подсветку | C19: Цветные предупреждения Numbers удаляет. Поэтому все предупреждения продублированы ТЕКСТОМ в последней колонке Dienstplan и на листе «Контроль ArbZG».
B20: Если что-то показывает ошибку | C20: Открой в Excel, Google Sheets или LibreOffice — там работает всё. В Numbers формулы тоже работают, но подсветка и выпадающие списки пропадают.
A22: ЧТО ГОВОРИТ ДОГОВОР (§ 3 Vergütung)
B23: Часовая ставка | C23: 27,00 € брутто (§ 3 Abs. 1)
B24: Оклад в месяц | C24: 4.676,40 € брутто → норма 4.676,40 / 27,00 = 173,20 ч/мес
B25: Рабочее время | C25: 40 ч в неделю, пятидневка, БЕЗ учёта перерывов (§ 2 Abs. 1)
B26: Ночь 20:00–06:00 | C26: +25 % (§ 3 Abs. 2 a)
B27: Воскресенье 00:00–24:00 | C27: +50 % (§ 3 Abs. 2 b)
B28: Праздник с отгулом (mit FZA) | C28: +35 % (§ 3 Abs. 2 c)
B29: Праздник без отгула (ohne FZA) | C29: +135 % (§ 3 Abs. 2 d)
B30: Совпадение надбавок | C30: Платится ТОЛЬКО САМАЯ ВЫСОКАЯ. Ночь в воскресенье = 50 %, не 75 %.
B31: Твои смены | C31: ND 20:00–08:00 = 12 ч, из них 10 ч ночных (20:00–06:00) и 2 ч обычных (06:00–08:00). TD 08:00–20:00 = 12 ч, ночных 0.
B32: Переработка | C32: § 2 Abs. 3: первые 8 ч/мес включены в оклад. Работодатель на практике оплачивает максимум 60 ч/мес, остальное переносит в следующий месяц отгулами — в договоре этого правила НЕТ, см. лист «Права и риски».
B33: Выплата | C33: 15-го числа следующего месяца (§ 3 Abs. 3)
B34: Срок претензий | C34: 3 месяца — § 14 Ausschlussfrist. Пропустил — право пропало.
A36: НАЛОГИ И ВЗНОСЫ
B37: § 3b EStG | C37: Надбавки за ночь/воскресенье/праздник свободны от подоходного налога: ночь до 25 %, воскресенье до 50 %, праздник до 125 % (01.05, 25./26.12 и 24.12 с 14:00 — до 150 %). База — максимум 50 €/ч.
B38: § 1 Abs. 1 SvEV | C38: От соцвзносов надбавки свободны только с базы 25,00 €/ч. Ставка 27,00 € → часть надбавки, посчитанная с 2,00 €/ч, взносами облагается. Файл делит автоматически.
B39: Отпуск и больничный | C39: Надбавки, выплаченные за дни отпуска/болезни, налогом ОБЛАГАЮТСЯ — § 3b требует фактической работы. Ставь статус Urlaub/Krank.
B40: Налоговый класс 3, 1 ребёнок | C40: Считается по Splittingtarif. Ребёнок с 2025 г. → доплата бездетных в Pflegeversicherung (0,6 %) больше НЕ удерживается — проверь это в Lohnabrechnung.
A42: ТОЧНОСТЬ
B43: Часы, надбавки, брутто | C43: Точно — по формулам договора.
B44: Соцвзносы | C44: Точно — ставки и предельные базы 2026.
B45: Подоходный налог | C45: Оценка ±несколько евро. Классы 5 и 6 не поддерживаются.
B46: Нетто | C46: Оценка. Официальный документ — Lohnabrechnung. Этот файл нужен, чтобы её проверить.
B48: Файл — вспомогательный инструмент, не юридическая консультация. При споре: профсоюз ver.di или Fachanwalt für Arbeitsrecht.

Sheet Настройки
A1: НАСТРОЙКИ / EINSTELLUNGEN — жёлтые поля можно менять
B3: 1. РАСЧЁТНЫЙ МЕСЯЦ
B4: Год | C4: Jahr | D4: 2026
B5: Месяц (1–12) | C5: Monat | D5: 9
B6: Дней в месяце | C6: Tage im Monat | D6: =DAY(EOMONTH(DATE(Настройки!$D$4,Настройки!$D$5,1),0))
B7: Федеральная земля | C7: Bundesland | D7: Niedersachsen | E7: Праздники — с листа «Feiertage»
B9: 2. ОПЛАТА — § 3 Arbeitsvertrag
B10: Часовая ставка | C10: Stundenlohn (Grundlohn) | D10: 27 | E10: § 3 Abs. 1
B11: Оклад брутто в месяц | C11: Monatsvergütung brutto | D11: 4676.4 | E11: § 3 Abs. 1
B12: Плановые часы в месяц | C12: Sollstunden / Monat | D12: =Настройки!$D$11/Настройки!$D$10 | E12: оклад / ставка = 173,20 ч
B13: Часов в неделю | C13: Wochenarbeitszeit | D13: 40 | E13: § 2 Abs. 1
B14: Переработка включена в оклад (ч) | C14: pauschal abgegoltene Überstunden | D14: 0 | E14: § 2 Abs. 3 договора разрешает не платить первые 8 ч/мес. Но в расчётке 08/2026 оплачены ВСЕ 216 ч — поэтому здесь 0. Поставь 8, если хочешь увидеть минимум по договору
B15: Максимум оплачиваемой переработки (ч) | C15: max. auszahlbare Überstunden | D15: 60 | E15: Практика работодателя: не более 60 ч/мес. В ДОГОВОРЕ такого правила нет — см. лист «Права и риски»
B16: Оплачивать переработку? | C16: Überstunden auszahlen (ja/nein) | D16: ja | E16: «nein» = всё идёт в счёт часов отгулами
B17: Надбавка за переработку | C17: Überstundenzuschlag | D17: 0 | E17: Договором не предусмотрена
B18: Перенос часов из прошлого месяца | C18: Übertrag aus Vormonat | D18: 0 | E18: Остаток счёта часов (Arbeitszeitkonto) на начало месяца
B19: Премия за Eingesprungen (за смену) | C19: Einspringprämie je Dienst | D19: 0 | E19: В договоре НЕТ. Впиши сумму, о которой договорились. Требуй подтверждение по e-mail — см. «Права и риски»
B20: Фактор неполного месяца | C20: Faktor (Ein-/Austritt) | D20: 1 | E20: 1,00 = полный месяц
B22: 3. НАДБАВКИ — § 3 Abs. 2 Arbeitsvertrag
B23: Ночная надбавка | C23: Nachtzuschlag | D23: 0.25 | E23: § 3 Abs. 2 a)
B24: Ночь: с (час) | C24: Nachtarbeit von | D24: 20 | E24: 20 = 20:00. Подтверждено работодателем (Chris, WhatsApp 09/2026): «20:00 – 06:00 morgens Nacht»
B25: Ночь: до (час) | C25: Nachtarbeit bis | D25: 6 | E25: 6 = 06:00
B26: Воскресная надбавка | C26: Sonntagszuschlag | D26: 0.5 | E26: § 3 Abs. 2 b). Подтверждено (Chris): «Sonntags Zuschlag ab 00:00» и «Sonntag > als Nacht, dann zählt Sonntag» — надбавки НЕ складываются
B27: Праздник С отгулом | C27: Feiertag mit FZA | D27: 0.35 | E27: § 3 Abs. 2 c)
B28: Праздник БЕЗ отгула | C28: Feiertag ohne FZA | D28: 1.35 | E28: § 3 Abs. 2 d)
B29: Праздники по умолчанию | C29: Feiertagsmodus | D29: ohne FZA | E29: «mit FZA» / «ohne FZA»; в графике можно задать по дню (колонка FZA: j / n)
B31: 4. ЛЬГОТЫ ПО НАДБАВКАМ — § 3b EStG / § 1 SvEV
B32: Макс. необлагаемая ночная | C32: Höchstsatz Nacht steuerfrei | D32: 0.25 | E32: § 3b Abs. 1 Nr. 1 EStG
B33: Макс. необлагаемая воскресная | C33: Höchstsatz Sonntag steuerfrei | D33: 0.5 | E33: § 3b Abs. 1 Nr. 2 EStG
B34: Макс. необлагаемая праздничная | C34: Höchstsatz Feiertag steuerfrei | D34: 1.25 | E34: § 3b Abs. 1 Nr. 3 EStG; для 01.05 и 25./26.12 — 150 % (в колонке D листа «Feiertage»)
B35: Предел базы: налог | C35: Grundlohngrenze steuerfrei | D35: 50 | E35: § 3b Abs. 2 EStG
B36: Предел базы: соцвзносы | C36: Grundlohngrenze SV-frei | D36: 25 | E36: § 1 Abs. 1 Nr. 1 SvEV — твои 27 € выше, часть надбавок облагается взносами
B38: 5. ВРЕМЯ СМЕН — ЧИСЛА-ЧАСЫ (20 = 20:00, 8 = 08:00, 6,5 = 06:30)
B39: TD (Tagdienst) начало | C39: TD Beginn | D39: 8 | E39: 08:00
B40: TD (Tagdienst) конец | C40: TD Ende | D40: 20 | E40: 20:00 → 12 часов
B41: TD перерыв (часы) | C41: TD Pause | D41: 0 | E41: § 4 ArbZG при смене >9 ч требует 45 мин. Впиши 0,75 если работодатель вычитает перерыв
B42: ND (Nachtdienst) начало | C42: ND Beginn | D42: 20 | E42: 20:00
B43: ND (Nachtdienst) конец | C43: ND Ende | D43: 8 | E43: 08:00 следующего дня → 12 часов, из них 10 ночных
B44: ND перерыв (часы) | C44: ND Pause | D44: 0 | E44: § 4 ArbZG при смене >9 ч требует 45 мин
B46: 6. НАЛОГИ И СОЦВЗНОСЫ 2026
B47: Налоговый класс | C47: Steuerklasse | D47: 3 | E47: Класс 3 → Splittingtarif. Классы 5 и 6 не поддерживаются
B48: Церковный налог? | C48: Kirchensteuerpflicht (ja/nein) | D48: nein
B49: Ставка церковного налога | C49: Kirchensteuersatz | D49: 0.09 | E49: Нижняя Саксония 9 %
B50: Детские вычеты (Zähler) | C50: Kinderfreibeträge | D50: 1 | E50: Класс 3 → 1,0 на ребёнка. Влияет только на Soli и церковный налог
B51: Бездетный (доплата в PV)? | C51: kinderlos ab 23 (ja/nein) | D51: nein | E51: У тебя ребёнок 2025 г. → «nein». Доплата 0,6 % удерживаться НЕ должна — проверь в Lohnabrechnung
B52: Взнос KV общий | C52: KV allgemeiner Beitragssatz | D52: 0.146 | E52: делится пополам
B53: Доп. взнос кассы | C53: kassenindiv. Zusatzbeitrag | D53: 0.0299 | E53: AOK Baden-Württemberg 2026 = 2,99 % (проверено по Lohnabrechnung 08/2026: 511,21 € / 5.812,50 € = 8,795 % = (14,6 % + 2,99 %) / 2)
B54: Взнос PV | C54: Pflegeversicherung | D54: 0.036 | E54: делится пополам
B55: Доплата бездетным PV | C55: Zuschlag Kinderlose | D55: 0.006 | E55: применяется только если поле выше = «ja»
B56: Взнос RV | C56: Rentenversicherung | D56: 0.186 | E56: → 9,3 % с работника
B57: Взнос AV | C57: Arbeitslosenversicherung | D57: 0.026 | E57: → 1,3 % с работника
B58: Предел базы KV/PV в месяц | C58: BBG KV/PV monatlich | D58: 5812.5 | E58: 2026: 69.750 €/год
B59: Предел базы RV/AV в месяц | C59: BBG RV/AV monatlich | D59: 8450 | E59: 2026: 101.400 €/год
B61: 7. ПАРАМЕТРЫ ПОДОХОДНОГО НАЛОГА 2026
B62: Вычет на работника | C62: Arbeitnehmer-Pauschbetrag | D62: 1230 | E62: § 9a EStG, в год
B63: Вычет особых расходов | C63: Sonderausgaben-Pauschbetrag | D63: 36 | E63: § 10c EStG, в год
B64: Вычет одинокому родителю | C64: Entlastungsbetrag Alleinerziehende | D64: 4260 | E64: только класс 2
B65: Учитывать AV в Vorsorgepauschale? | C65: AV-Teilbetrag ansetzen (ja/nein) | D65: nein | E65: Новое с 2026 (§ 39b Abs. 2 S. 5 Nr. 3 Bst. e EStG), но только в пределах 1.900 € вместе с KV/PV — у тебя они уже выше
B66: Порог Soli (налог за год) | C66: Soli-Freigrenze | D66: 20350 | E66: одинокий; для класса 3 порог удваивается — при твоём доходе Soli всё равно 0
B67: Базовый вычет | C67: Grundfreibetrag 2026 | D67: 12348 | E67: § 32a EStG
B68: Граница 1-й зоны | C68: Ende Zone 1 | D68: 17799 | E68: § 32a EStG 2026
B69: Граница 2-й зоны | C69: Ende Zone 2 | D69: 69878 | E69: § 32a EStG 2026
B70: Граница 3-й зоны | C70: Ende Zone 3 | D70: 277825 | E70: § 32a EStG 2026

Sheet Feiertage
A1: ПРАЗДНИКИ / GESETZLICHE FEIERTAGE — Niedersachsen
A2: Дописывать можно до строки 43. Колонка D — максимальная НЕОБЛАГАЕМАЯ надбавка по § 3b EStG.
A3: Дата | B3: Название (Feiertag) | C3: Земля | D3: §3b Höchstsatz | E3: Примечание
A4: 46023 | B4: Neujahr | C4: bundesweit | D4: 1.25
A5: 46115 | B5: Karfreitag | C5: bundesweit | D5: 1.25
A6: 46118 | B6: Ostermontag | C6: bundesweit | D6: 1.25
A7: 46143 | B7: Tag der Arbeit | C7: bundesweit | D7: 1.5 | E7: § 3b Abs. 3 Nr. 3 — до 150 %
A8: 46156 | B8: Christi Himmelfahrt | C8: bundesweit | D8: 1.25
A9: 46167 | B9: Pfingstmontag | C9: bundesweit | D9: 1.25
A10: 46298 | B10: Tag der Deutschen Einheit | C10: bundesweit | D10: 1.25
A11: 46326 | B11: Reformationstag | C11: Niedersachsen | D11: 1.25
A12: 46381 | B12: 1. Weihnachtstag | C12: bundesweit | D12: 1.5 | E12: § 3b Abs. 3 Nr. 3 — до 150 %
A13: 46382 | B13: 2. Weihnachtstag | C13: bundesweit | D13: 1.5 | E13: § 3b Abs. 3 Nr. 3 — до 150 %
A14: 46388 | B14: Neujahr | C14: bundesweit | D14: 1.25
A15: 46472 | B15: Karfreitag | C15: bundesweit | D15: 1.25
A16: 46475 | B16: Ostermontag | C16: bundesweit | D16: 1.25
A17: 46508 | B17: Tag der Arbeit | C17: bundesweit | D17: 1.5 | E17: суббота
A18: 46513 | B18: Christi Himmelfahrt | C18: bundesweit | D18: 1.25
A19: 46524 | B19: Pfingstmontag | C19: bundesweit | D19: 1.25
A20: 46663 | B20: Tag der Deutschen Einheit | C20: bundesweit | D20: 1.25 | E20: воскресенье
A21: 46691 | B21: Reformationstag | C21: Niedersachsen | D21: 1.25 | E21: воскресенье
A22: 46746 | B22: 1. Weihnachtstag | C22: bundesweit | D22: 1.5 | E22: суббота
A23: 46747 | B23: 2. Weihnachtstag | C23: bundesweit | D23: 1.5 | E23: воскресенье
A46: НЕ праздники, но льгота по § 3b EStG:
A47: · 24.12 с 14:00 — до 150 % необлагаемо
A48: · 31.12 с 14:00 — до 125 % необлагаемо
A49: · ночь 00:00–04:00, если смена начата до полуночи — до 40 % необлагаемо (§ 3b Abs. 3 Nr. 1)
A50: · договор Constantia платит за эти часы обычные ставки — льгота касается только налога, не суммы выплаты

Sheet Dienstplan
A1: ГРАФИК И РАСЧЁТ ЧАСОВ / DIENSTPLAN
A2: ND = Nachtdienst 20:00–08:00 · TD = Tagdienst 08:00–20:00 · FREI = выходной · «x» = eingesprungen · статус: Arbeit / Urlaub / Krank / Fortbildung · FZA: j = праздник с отгулом, n = без отгула. Время — числа-часы (20 = 20:00). Смена относится к дню, в который НАЧАЛАСЬ.
A4: Дата Datum | B4: День | C4: Праздник Feiertag | D4: Смена ND/TD/FREI | E4: Статус Status | F4: Sprn | G4: FZA | H4: Начало час | I4: Конец час | J4: Пауза ч | K4: Длит. ч | L4: Часы оплач. | M4: Ночь ч | N4: Воскр. ч | O4: Праздн. ч | P4: Обычн. ч | Q4: Надбавка € | R4: из них без налога | S4: из них без взносов | T4: Отдых до смены ч | U4: Предупреждение (ArbZG)
A5: =IF(1>Настройки!$D$6,"",DATE(Настройки!$D$4,Настройки!$D$5,1)) | B5: =IF($A5="","",CHOOSE(WEEKDAY($A5,2),"Пн","Вт","Ср","Чт","Пт","Сб","Вс")) | C5: =IF($A5="","",IFERROR(INDEX(Feiertage!$B$4:$B$43,MATCH($A5,Feiertage!$A$4:$A$43,0)),"")) | D5: TD | E5: Arbeit | H5: =IF($D5="ND",Настройки!$D$42,IF($D5="TD",Настройки!$D$39,"")) | I5: =IF($D5="ND",Настройки!$D$43,IF($D5="TD",Настройки!$D$40,"")) | J5: =IF($D5="ND",Настройки!$D$44,IF($D5="TD",Настройки!$D$41,"")) | K5: =IF($H5="","",$I5-$H5+IF($I5<=$H5,24,0)) | L5: =IF($K5="","",MAX(0,$K5-$J5)) | M5: =($AF5+$AG5)*$Y5 | N5: =($Z5*$AH5+$AA5*$AI5)*$Y5 | O5: =($AB5*$AH5+$AC5*$AI5)*$Y5 | P5: =IF($L5="","",MAX(0,$L5-$O5-$AL5-$AM5)) | Q5: =ROUND(Настройки!$D$10*($AK5*$AN5+$AJ5*MAX($AN5,Настройки!$D$26)+$AL5*Настройки!$D$26+$AM5*Настройки!$D$23),2) | R5: =IF($E5<>"Arbeit",0,ROUND(MIN(Настройки!$D$10,Настройки!$D$35)*($AK5*MIN($AN5,$AO5)+$AJ5*MIN(MAX($AN5,Настройки!$D$26),$AO5)+$AL5*MIN(Настройки!$D$26,Настройки!$D$33)+$AM5*MIN(Настройки!$D$23,Настройки!$D$32)),2)) | S5: =IF($E5<>"Arbeit",0,ROUND(MIN(Настройки!$D$10,Настройки!$D$36)*($AK5*MIN($AN5,$AO5)+$AJ5*MIN(MAX($AN5,Настройки!$D$26),$AO5)+$AL5*MIN(Настройки!$D$26,Настройки!$D$33)+$AM5*MIN(Настройки!$D$23,Настройки!$D$32)),2)) | U5: =IF($L5="","",TRIM(IF($L5>10,"смена >10 ч (§ 3 / § 6 ArbZG) ","")&IF(AND($T5<>"",$T5<11),"отдых <11 ч (§ 5 ArbZG) ","")&IF(AND($L5>9,$J5<0.75),"перерыв <45 мин (§ 4 ArbZG) ","")&IF(AND($L5>6,$L5<=9,$J5<0.5),"перерыв <30 мин (§ 4 ArbZG)",""))) | W5: =IF($H5="","",$H5) | X5: =IF($H5="","",$I5+IF($I5<=$H5,24,0)) | Y5: =IF(OR($K5="",$K5=0),0,$L5/$K5) | Z5: =IF($A5="",0,IF(WEEKDAY($A5,2)=7,1,0)) | AA5: =IF($A5="",0,IF(WEEKDAY($A5+1,2)=7,1,0)) | AB5: =IF($A5="",0,MIN(1,COUNTIF(Feiertage!$A$4:$A$43,$A5))) | AC5: =IF($A5="",0,MIN(1,COUNTIF(Feiertage!$A$4:$A$43,$A5+1))) | AD5: =IFERROR(INDEX(Feiertage!$D$4:$D$43,MATCH($A5,Feiertage!$A$4:$A$43,0)),Настройки!$D$34) | AE5: =IFERROR(INDEX(Feiertage!$D$4:$D$43,MATCH($A5+1,Feiertage!$A$4:$A$43,0)),Настройки!$D$34) | AF5: =IF($W5="",0,MAX(0,MIN($X5,Настройки!$D$25)-MAX($W5,0))+MAX(0,MIN($X5,24)-MAX($W5,Настройки!$D$24))) | AG5: =IF($W5="",0,MAX(0,MIN($X5,24+Настройки!$D$25)-MAX($W5,24))) | AH5: =IF($W5="",0,MAX(0,MIN($X5,24)-MAX($W5,0))) | AI5: =IF($W5="",0,MAX(0,MIN($X5,48)-MAX($W5,24))) | AJ5: =($Z5*$AB5*$AH5+$AA5*$AC5*$AI5)*$Y5 | AK5: =$O5-$AJ5 | AL5: =$N5-$AJ5 | AM5: =$M5-(MAX($Z5,$AB5)*$AF5+MAX($AA5,$AC5)*$AG5)*$Y5 | AN5: =IF($G5="j",Настройки!$D$27,IF($G5="n",Настройки!$D$28,IF(Настройки!$D$29="mit FZA",Настройки!$D$27,Настройки!$D$28))) | AO5: =IF($O5=0,Настройки!$D$34,($AB5*$AH5*$AD5+$AC5*$AI5*$AE5)*$Y5/$O5)
A6: =IF(2>Настройки!$D$6,"",DATE(Настройки!$D$4,Настройки!$D$5,2)) | B6: =IF($A6="","",CHOOSE(WEEKDAY($A6,2),"Пн","Вт","Ср","Чт","Пт","Сб","Вс")) | C6: =IF($A6="","",IFERROR(INDEX(Feiertage!$B$4:$B$43,MATCH($A6,Feiertage!$A$4:$A$43,0)),"")) | D6: TD | E6: Arbeit | H6: =IF($D6="ND",Настройки!$D$42,IF($D6="TD",Настройки!$D$39,"")) | I6: =IF($D6="ND",Настройки!$D$43,IF($D6="TD",Настройки!$D$40,"")) | J6: =IF($D6="ND",Настройки!$D$44,IF($D6="TD",Настройки!$D$41,"")) | K6: =IF($H6="","",$I6-$H6+IF($I6<=$H6,24,0)) | L6: =IF($K6="","",MAX(0,$K6-$J6)) | M6: =($AF6+$AG6)*$Y6 | N6: =($Z6*$AH6+$AA6*$AI6)*$Y6 | O6: =($AB6*$AH6+$AC6*$AI6)*$Y6 | P6: =IF($L6="","",MAX(0,$L6-$O6-$AL6-$AM6)) | Q6: =ROUND(Настройки!$D$10*($AK6*$AN6+$AJ6*MAX($AN6,Настройки!$D$26)+$AL6*Настройки!$D$26+$AM6*Настройки!$D$23),2) | R6: =IF($E6<>"Arbeit",0,ROUND(MIN(Настройки!$D$10,Настройки!$D$35)*($AK6*MIN($AN6,$AO6)+$AJ6*MIN(MAX($AN6,Настройки!$D$26),$AO6)+$AL6*MIN(Настройки!$D$26,Настройки!$D$33)+$AM6*MIN(Настройки!$D$23,Настройки!$D$32)),2)) | S6: =IF($E6<>"Arbeit",0,ROUND(MIN(Настройки!$D$10,Настройки!$D$36)*($AK6*MIN($AN6,$AO6)+$AJ6*MIN(MAX($AN6,Настройки!$D$26),$AO6)+$AL6*MIN(Настройки!$D$26,Настройки!$D$33)+$AM6*MIN(Настройки!$D$23,Настройки!$D$32)),2)) | T6: =IF(OR($W6="",$W5=""),"",24+$W6-$X5) | U6: =IF($L6="","",TRIM(IF($L6>10,"смена >10 ч (§ 3 / § 6 ArbZG) ","")&IF(AND($T6<>"",$T6<11),"отдых <11 ч (§ 5 ArbZG) ","")&IF(AND($L6>9,$J6<0.75),"перерыв <45 мин (§ 4 ArbZG) ","")&IF(AND($L6>6,$L6<=9,$J6<0.5),"перерыв <30 мин (§ 4 ArbZG)",""))) | W6: =IF($H6="","",$H6) | X6: =IF($H6="","",$I6+IF($I6<=$H6,24,0)) | Y6: =IF(OR($K6="",$K6=0),0,$L6/$K6) | Z6: =IF($A6="",0,IF(WEEKDAY($A6,2)=7,1,0)) | AA6: =IF($A6="",0,IF(WEEKDAY($A6+1,2)=7,1,0)) | AB6: =IF($A6="",0,MIN(1,COUNTIF(Feiertage!$A$4:$A$43,$A6))) | AC6: =IF($A6="",0,MIN(1,COUNTIF(Feiertage!$A$4:$A$43,$A6+1))) | AD6: =IFERROR(INDEX(Feiertage!$D$4:$D$43,MATCH($A6,Feiertage!$A$4:$A$43,0)),Настройки!$D$34) | AE6: =IFERROR(INDEX(Feiertage!$D$4:$D$43,MATCH($A6+1,Feiertage!$A$4:$A$43,0)),Настройки!$D$34) | AF6: =IF($W6="",0,MAX(0,MIN($X6,Настройки!$D$25)-MAX($W6,0))+MAX(0,MIN($X6,24)-MAX($W6,Настройки!$D$24))) | AG6: =IF($W6="",0,MAX(0,MIN($X6,24+Настройки!$D$25)-MAX($W6,24))) | AH6: =IF($W6="",0,MAX(0,MIN($X6,24)-MAX($W6,0))) | AI6: =IF($W6="",0,MAX(0,MIN($X6,48)-MAX($W6,24))) | AJ6: =($Z6*$AB6*$AH6+$AA6*$AC6*$AI6)*$Y6 | AK6: =$O6-$AJ6 | AL6: =$N6-$AJ6 | AM6: =$M6-(MAX($Z6,$AB6)*$AF6+MAX($AA6,$AC6)*$AG6)*$Y6 | AN6: =IF($G6="j",Настройки!$D$27,IF($G6="n",Настройки!$D$28,IF(Настройки!$D$29="mit FZA",Настройки!$D$27,Настройки!$D$28))) | AO6: =IF($O6=0,Настройки!$D$34,($AB6*$AH6*$AD6+$AC6*$AI6*$AE6)*$Y6/$O6)
A7: =IF(3>Настройки!$D$6,"",DATE(Настройки!$D$4,Настройки!$D$5,3)) | B7: =IF($A7="","",CHOOSE(WEEKDAY($A7,2),"Пн","Вт","Ср","Чт","Пт","Сб","Вс")) | C7: =IF($A7="","",IFERROR(INDEX(Feiertage!$B$4:$B$43,MATCH($A7,Feiertage!$A$4:$A$43,0)),"")) | D7: FREI | H7: =IF($D7="ND",Настройки!$D$42,IF($D7="TD",Настройки!$D$39,"")) | I7: =IF($D7="ND",Настройки!$D$43,IF($D7="TD",Настройки!$D$40,"")) | J7: =IF($D7="ND",Настройки!$D$44,IF($D7="TD",Настройки!$D$41,"")) | K7: =IF($H7="","",$I7-$H7+IF($I7<=$H7,24,0)) | L7: =IF($K7="","",MAX(0,$K7-$J7)) | M7: =($AF7+$AG7)*$Y7 | N7: =($Z7*$AH7+$AA7*$AI7)*$Y7 | O7: =($AB7*$AH7+$AC7*$AI7)*$Y7 | P7: =IF($L7="","",MAX(0,$L7-$O7-$AL7-$AM7)) | Q7: =ROUND(Настройки!$D$10*($AK7*$AN7+$AJ7*MAX($AN7,Настройки!$D$26)+$AL7*Настройки!$D$26+$AM7*Настройки!$D$23),2) | R7: =IF($E7<>"Arbeit",0,ROUND(MIN(Настройки!$D$10,Настройки!$D$35)*($AK7*MIN($AN7,$AO7)+$AJ7*MIN(MAX($AN7,Настройки!$D$26),$AO7)+$AL7*MIN(Настройки!$D$26,Настройки!$D$33)+$AM7*MIN(Настройки!$D$23,Настройки!$D$32)),2)) | S7: =IF($E7<>"Arbeit",0,ROUND(MIN(Настройки!$D$10,Настройки!$D$36)*($AK7*MIN($AN7,$AO7)+$AJ7*MIN(MAX($AN7,Настройки!$D$26),$AO7)+$AL7*MIN(Настройки!$D$26,Настройки!$D$33)+$AM7*MIN(Настройки!$D$23,Настройки!$D$32)),2)) | T7: =IF(OR($W7="",$W6=""),"",24+$W7-$X6) | U7: =IF($L7="","",TRIM(IF($L7>10,"смена >10 ч (§ 3 / § 6 ArbZG) ","")&IF(AND($T7<>"",$T7<11),"отдых <11 ч (§ 5 ArbZG) ","")&IF(AND($L7>9,$J7<0.75),"перерыв <45 мин (§ 4 ArbZG) ","")&IF(AND($L7>6,$L7<=9,$J7<0.5),"перерыв <30 мин (§ 4 ArbZG)",""))) | W7: =IF($H7="","",$H7) | X7: =IF($H7="","",$I7+IF($I7<=$H7,24,0)) | Y7: =IF(OR($K7="",$K7=0),0,$L7/$K7) | Z7: =IF($A7="",0,IF(WEEKDAY($A7,2)=7,1,0)) | AA7: =IF($A7="",0,IF(WEEKDAY($A7+1,2)=7,1,0)) | AB7: =IF($A7="",0,MIN(1,COUNTIF(Feiertage!$A$4:$A$43,$A7))) | AC7: =IF($A7="",0,MIN(1,COUNTIF(Feiertage!$A$4:$A$43,$A7+1))) | AD7: =IFERROR(INDEX(Feiertage!$D$4:$D$43,MATCH($A7,Feiertage!$A$4:$A$43,0)),Настройки!$D$34) | AE7: =IFERROR(INDEX(Feiertage!$D$4:$D$43,MATCH($A7+1,Feiertage!$A$4:$A$43,0)),Настройки!$D$34) | AF7: =IF($W7="",0,MAX(0,MIN($X7,Настройки!$D$25)-MAX($W7,0))+MAX(0,MIN($X7,24)-MAX($W7,Настройки!$D$24))) | AG7: =IF($W7="",0,MAX(0,MIN($X7,24+Настройки!$D$25)-MAX($W7,24))) | AH7: =IF($W7="",0,MAX(0,MIN($X7,24)-MAX($W7,0))) | AI7: =IF($W7="",0,MAX(0,MIN($X7,48)-MAX($W7,24))) | AJ7: =($Z7*$AB7*$AH7+$AA7*$AC7*$AI7)*$Y7 | AK7: =$O7-$AJ7 | AL7: =$N7-$AJ7 | AM7: =$M7-(MAX($Z7,$AB7)*$AF7+MAX($AA7,$AC7)*$AG7)*$Y7 | AN7: =IF($G7="j",Настройки!$D$27,IF($G7="n",Настройки!$D$28,IF(Настройки!$D$29="mit FZA",Настройки!$D$27,Настройки!$D$28))) | AO7: =IF($O7=0,Настройки!$D$34,($AB7*$AH7*$AD7+$AC7*$AI7*$AE7)*$Y7/$O7)
A8: =IF(4>Настройки!$D$6,"",DATE(Настройки!$D$4,Настройки!$D$5,4)) | B8: =IF($A8="","",CHOOSE(WEEKDAY($A8,2),"Пн","Вт","Ср","Чт","Пт","Сб","Вс")) | C8: =IF($A8="","",IFERROR(INDEX(Feiertage!$B$4:$B$43,MATCH($A8,Feiertage!$A$4:$A$43,0)),"")) | D8: ND | E8: Arbeit | H8: =IF($D8="ND",Настройки!$D$42,IF($D8="TD",Настройки!$D$39,"")) | I8: =IF($D8="ND",Настройки!$D$43,IF($D8="TD",Настройки!$D$40,"")) | J8: =IF($D8="ND",Настройки!$D$44,IF($D8="TD",Настройки!$D$41,"")) | K8: =IF($H8="","",$I8-$H8+IF($I8<=$H8,24,0)) | L8: =IF($K8="","",MAX(0,$K8-$J8)) | M8: =($AF8+$AG8)*$Y8 | N8: =($Z8*$AH8+$AA8*$AI8)*$Y8 | O8: =($AB8*$AH8+$AC8*$AI8)*$Y8 | P8: =IF($L8="","",MAX(0,$L8-$O8-$AL8-$AM8)) | Q8: =ROUND(Настройки!$D$10*($AK8*$AN8+$AJ8*MAX($AN8,Настройки!$D$26)+$AL8*Настройки!$D$26+$AM8*Настройки!$D$23),2) | R8: =IF($E8<>"Arbeit",0,ROUND(MIN(Настройки!$D$10,Настройки!$D$35)*($AK8*MIN($AN8,$AO8)+$AJ8*MIN(MAX($AN8,Настройки!$D$26),$AO8)+$AL8*MIN(Настройки!$D$26,Настройки!$D$33)+$AM8*MIN(Настройки!$D$23,Настройки!$D$32)),2)) | S8: =IF($E8<>"Arbeit",0,ROUND(MIN(Настройки!$D$10,Настройки!$D$36)*($AK8*MIN($AN8,$AO8)+$AJ8*MIN(MAX($AN8,Настройки!$D$26),$AO8)+$AL8*MIN(Настройки!$D$26,Настройки!$D$33)+$AM8*MIN(Настройки!$D$23,Настройки!$D$32)),2)) | T8: =IF(OR($W8="",$W7=""),"",24+$W8-$X7) | U8: =IF($L8="","",TRIM(IF($L8>10,"смена >10 ч (§ 3 / § 6 ArbZG) ","")&IF(AND($T8<>"",$T8<11),"отдых <11 ч (§ 5 ArbZG) ","")&IF(AND($L8>9,$J8<0.75),"перерыв <45 мин (§ 4 ArbZG) ","")&IF(AND($L8>6,$L8<=9,$J8<0.5),"перерыв <30 мин (§ 4 ArbZG)",""))) | W8: =IF($H8="","",$H8) | X8: =IF($H8="","",$I8+IF($I8<=$H8,24,0)) | Y8: =IF(OR($K8="",$K8=0),0,$L8/$K8) | Z8: =IF($A8="",0,IF(WEEKDAY($A8,2)=7,1,0)) | AA8: =IF($A8="",0,IF(WEEKDAY($A8+1,2)=7,1,0)) | AB8: =IF($A8="",0,MIN(1,COUNTIF(Feiertage!$A$4:$A$43,$A8))) | AC8: =IF($A8="",0,MIN(1,COUNTIF(Feiertage!$A$4:$A$43,$A8+1))) | AD8: =IFERROR(INDEX(Feiertage!$D$4:$D$43,MATCH($A8,Feiertage!$A$4:$A$43,0)),Настройки!$D$34) | AE8: =IFERROR(INDEX(Feiertage!$D$4:$D$43,MATCH($A8+1,Feiertage!$A$4:$A$43,0)),Настройки!$D$34) | AF8: =IF($W8="",0,MAX(0,MIN($X8,Настройки!$D$25)-MAX($W8,0))+MAX(0,MIN($X8,24)-MAX($W8,Настройки!$D$24))) | AG8: =IF($W8="",0,MAX(0,MIN($X8,24+Настройки!$D$25)-MAX($W8,24))) | AH8: =IF($W8="",0,MAX(0,MIN($X8,24)-MAX($W8,0))) | AI8: =IF($W8="",0,MAX(0,MIN($X8,48)-MAX($W8,24))) | AJ8: =($Z8*$AB8*$AH8+$AA8*$AC8*$AI8)*$Y8 | AK8: =$O8-$AJ8 | AL8: =$N8-$AJ8 | AM8: =$M8-(MAX($Z8,$AB8)*$AF8+MAX($AA8,$AC8)*$AG8)*$Y8 | AN8: =IF($G8="j",Настройки!$D$27,IF($G8="n",Настройки!$D$28,IF(Настройки!$D$29="mit FZA",Настройки!$D$27,Настройки!$D$28))) | AO8: =IF($O8=0,Настройки!$D$34,($AB8*$AH8*$AD8+$AC8*$AI8*$AE8)*$Y8/$O8)
A9: =IF(5>Настройки!$D$6,"",DATE(Настройки!$D$4,Настройки!$D$5,5)) | B9: =IF($A9="","",CHOOSE(WEEKDAY($A9,2),"Пн","Вт","Ср","Чт","Пт","Сб","Вс")) | C9: =IF($A9="","",IFERROR(INDEX(Feiertage!$B$4:$B$43,MATCH($A9,Feiertage!$A$4:$A$43,0)),"")) | D9: ND | E9: Arbeit | H9: =IF($D9="ND",Настройки!$D$42,IF($D9="TD",Настройки!$D$39,"")) | I9: =IF($D9="ND",Настройки!$D$43,IF($D9="TD",Настройки!$D$40,"")) | J9: =IF($D9="ND",Настройки!$D$44,IF($D9="TD",Настройки!$D$41,"")) | K9: =IF($H9="","",$I9-$H9+IF($I9<=$H9,24,0)) | L9: =IF($K9="","",MAX(0,$K9-$J9)) | M9: =($AF9+$AG9)*$Y9 | N9: =($Z9*$AH9+$AA9*$AI9)*$Y9 | O9: =($AB9*$AH9+$AC9*$AI9)*$Y9 | P9: =IF($L9="","",MAX(0,$L9-$O9-$AL9-$AM9)) | Q9: =ROUND(Настройки!$D$10*($AK9*$AN9+$AJ9*MAX($AN9,Настройки!$D$26)+$AL9*Настройки!$D$26+$AM9*Настройки!$D$23),2) | R9: =IF($E9<>"Arbeit",0,ROUND(MIN(Настройки!$D$10,Настройки!$D$35)*($AK9*MIN($AN9,$AO9)+$AJ9*MIN(MAX($AN9,Настройки!$D$26),$AO9)+$AL9*MIN(Настройки!$D$26,Настройки!$D$33)+$AM9*MIN(Настройки!$D$23,Настройки!$D$32)),2)) | S9: =IF($E9<>"Arbeit",0,ROUND(MIN(Настройки!$D$10,Настройки!$D$36)*($AK9*MIN($AN9,$AO9)+$AJ9*MIN(MAX($AN9,Настройки!$D$26),$AO9)+$AL9*MIN(Настройки!$D$26,Настройки!$D$33)+$AM9*MIN(Настройки!$D$23,Настройки!$D$32)),2)) | T9: =IF(OR($W9="",$W8=""),"",24+$W9-$X8) | U9: =IF($L9="","",TRIM(IF($L9>10,"смена >10 ч (§ 3 / § 6 ArbZG) ","")&IF(AND($T9<>"",$T9<11),"отдых <11 ч (§ 5 ArbZG) ","")&IF(AND($L9>9,$J9<0.75),"перерыв <45 мин (§ 4 ArbZG) ","")&IF(AND($L9>6,$L9<=9,$J9<0.5),"перерыв <30 мин (§ 4 ArbZG)",""))) | W9: =IF($H9="","",$H9) | X9: =IF($H9="","",$I9+IF($I9<=$H9,24,0)) | Y9: =IF(OR($K9="",$K9=0),0,$L9/$K9) | Z9: =IF($A9="",0,IF(WEEKDAY($A9,2)=7,1,0)) | AA9: =IF($A9="",0,IF(WEEKDAY($A9+1,2)=7,1,0)) | AB9: =IF($A9="",0,MIN(1,COUNTIF(Feiertage!$A$4:$A$43,$A9))) | AC9: =IF($A9="",0,MIN(1,COUNTIF(Feiertage!$A$4:$A$43,$A9+1))) | AD9: =IFERROR(INDEX(Feiertage!$D$4:$D$43,MATCH($A9,Feiertage!$A$4:$A$43,0)),Настройки!$D$34) | AE9: =IFERROR(INDEX(Feiertage!$D$4:$D$43,MATCH($A9+1,Feiertage!$A$4:$A$43,0)),Настройки!$D$34) | AF9: =IF($W9="",0,MAX(0,MIN($X9,Настройки!$D$25)-MAX($W9,0))+MAX(0,MIN($X9,24)-MAX($W9,Настройки!$D$24))) | AG9: =IF($W9="",0,MAX(0,MIN($X9,24+Настройки!$D$25)-MAX($W9,24))) | AH9: =IF($W9="",0,MAX(0,MIN($X9,24)-MAX($W9,0))) | AI9: =IF($W9="",0,MAX(0,MIN($X9,48)-MAX($W9,24))) | AJ9: =($Z9*$AB9*$AH9+$AA9*$AC9*$AI9)*$Y9 | AK9: =$O9-$AJ9 | AL9: =$N9-$AJ9 | AM9: =$M9-(MAX($Z9,$AB9)*$AF9+MAX($AA9,$AC9)*$AG9)*$Y9 | AN9: =IF($G9="j",Настройки!$D$27,IF($G9="n",Настройки!$D$28,IF(Настройки!$D$29="mit FZA",Настройки!$D$27,Настройки!$D$28))) | AO9: =IF($O9=0,Настройки!$D$34,($AB9*$AH9*$AD9+$AC9*$AI9*$AE9)*$Y9/$O9)
A10: =IF(6>Настройки!$D$6,"",DATE(Настройки!$D$4,Настройки!$D$5,6)) | B10: =IF($A10="","",CHOOSE(WEEKDAY($A10,2),"Пн","Вт","Ср","Чт","Пт","Сб","Вс")) | C10: =IF($A10="","",IFERROR(INDEX(Feiertage!$B$4:$B$43,MATCH($A10,Feiertage!$A$4:$A$43,0)),"")) | D10: ND | E10: Arbeit | H10: =IF($D10="ND",Настройки!$D$42,IF($D10="TD",Настройки!$D$39,"")) | I10: =IF($D10="ND",Настройки!$D$43,IF($D10="TD",Настройки!$D$40,"")) | J10: =IF($D10="ND",Настройки!$D$44,IF($D10="TD",Настройки!$D$41,"")) | K10: =IF($H10="","",$I10-$H10+IF($I10<=$H10,24,0)) | L10: =IF($K10="","",MAX(0,$K10-$J10)) | M10: =($AF10+$AG10)*$Y10 | N10: =($Z10*$AH10+$AA10*$AI10)*$Y10 | O10: =($AB10*$AH10+$AC10*$AI10)*$Y10 | P10: =IF($L10="","",MAX(0,$L10-$O10-$AL10-$AM10)) | Q10: =ROUND(Настройки!$D$10*($AK10*$AN10+$AJ10*MAX($AN10,Настройки!$D$26)+$AL10*Настройки!$D$26+$AM10*Настройки!$D$23),2) | R10: =IF($E10<>"Arbeit",0,ROUND(MIN(Настройки!$D$10,Настройки!$D$35)*($AK10*MIN($AN10,$AO10)+$AJ10*MIN(MAX($AN10,Настройки!$D$26),$AO10)+$AL10*MIN(Настройки!$D$26,Настройки!$D$33)+$AM10*MIN(Настройки!$D$23,Настройки!$D$32)),2)) | S10: =IF($E10<>"Arbeit",0,ROUND(MIN(Настройки!$D$10,Настройки!$D$36)*($AK10*MIN($AN10,$AO10)+$AJ10*MIN(MAX($AN10,Настройки!$D$26),$AO10)+$AL10*MIN(Настройки!$D$26,Настройки!$D$33)+$AM10*MIN(Настройки!$D$23,Настройки!$D$32)),2)) | T10: =IF(OR($W10="",$W9=""),"",24+$W10-$X9) | U10: =IF($L10="","",TRIM(IF($L10>10,"смена >10 ч (§ 3 / § 6 ArbZG) ","")&IF(AND($T10<>"",$T10<11),"отдых <11 ч (§ 5 ArbZG) ","")&IF(AND($L10>9,$J10<0.75),"перерыв <45 мин (§ 4 ArbZG) ","")&IF(AND($L10>6,$L10<=9,$J10<0.5),"перерыв <30 мин (§ 4 ArbZG)",""))) | W10: =IF($H10="","",$H10) | X10: =IF($H10="","",$I10+IF($I10<=$H10,24,0)) | Y10: =IF(OR($K10="",$K10=0),0,$L10/$K10) | Z10: =IF($A10="",0,IF(WEEKDAY($A10,2)=7,1,0)) | AA10: =IF($A10="",0,IF(WEEKDAY($A10+1,2)=7,1,0)) | AB10: =IF($A10="",0,MIN(1,COUNTIF(Feiertage!$A$4:$A$43,$A10))) | AC10: =IF($A10="",0,MIN(1,COUNTIF(Feiertage!$A$4:$A$43,$A10+1))) | AD10: =IFERROR(INDEX(Feiertage!$D$4:$D$43,MATCH($A10,Feiertage!$A$4:$A$43,0)),Настройки!$D$34) | AE10: =IFERROR(INDEX(Feiertage!$D$4:$D$43,MATCH($A10+1,Feiertage!$A$4:$A$43,0)),Настройки!$D$34) | AF10: =IF($W10="",0,MAX(0,MIN($X10,Настройки!$D$25)-MAX($W10,0))+MAX(0,MIN($X10,24)-MAX($W10,Настройки!$D$24))) | AG10: =IF($W10="",0,MAX(0,MIN($X10,24+Настройки!$D$25)-MAX($W10,24))) | AH10: =IF($W10="",0,MAX(0,MIN($X10,24)-MAX($W10,0))) | AI10: =IF($W10="",0,MAX(0,MIN($X10,48)-MAX($W10,24))) | AJ10: =($Z10*$AB10*$AH10+$AA10*$AC10*$AI10)*$Y10 | AK10: =$O10-$AJ10 | AL10: =$N10-$AJ10 | AM10: =$M10-(MAX($Z10,$AB10)*$AF10+MAX($AA10,$AC10)*$AG10)*$Y10 | AN10: =IF($G10="j",Настройки!$D$27,IF($G10="n",Настройки!$D$28,IF(Настройки!$D$29="mit FZA",Настройки!$D$27,Настройки!$D$28))) | AO10: =IF($O10=0,Настройки!$D$34,($AB10*$AH10*$AD10+$AC10*$AI10*$AE10)*$Y10/$O10)
A11: =IF(7>Настройки!$D$6,"",DATE(Настройки!$D$4,Настройки!$D$5,7)) | B11: =IF($A11="","",CHOOSE(WEEKDAY($A11,2),"Пн","Вт","Ср","Чт","Пт","Сб","Вс")) | C11: =IF($A11="","",IFERROR(INDEX(Feiertage!$B$4:$B$43,MATCH($A11,Feiertage!$A$4:$A$43,0)),"")) | D11: FREI | H11: =IF($D11="ND",Настройки!$D$42,IF($D11="TD",Настройки!$D$39,"")) | I11: =IF($D11="ND",Настройки!$D$43,IF($D11="TD",Настройки!$D$40,"")) | J11: =IF($D11="ND",Настройки!$D$44,IF($D11="TD",Настройки!$D$41,"")) | K11: =IF($H11="","",$I11-$H11+IF($I11<=$H11,24,0)) | L11: =IF($K11="","",MAX(0,$K11-$J11)) | M11: =($AF11+$AG11)*$Y11 | N11: =($Z11*$AH11+$AA11*$AI11)*$Y11 | O11: =($AB11*$AH11+$AC11*$AI11)*$Y11 | P11: =IF($L11="","",MAX(0,$L11-$O11-$AL11-$AM11)) | Q11: =ROUND(Настройки!$D$10*($AK11*$AN11+$AJ11*MAX($AN11,Настройки!$D$26)+$AL11*Настройки!$D$26+$AM11*Настройки!$D$23),2) | R11: =IF($E11<>"Arbeit",0,ROUND(MIN(Настройки!$D$10,Настройки!$D$35)*($AK11*MIN($AN11,$AO11)+$AJ11*MIN(MAX($AN11,Настройки!$D$26),$AO11)+$AL11*MIN(Настройки!$D$26,Настройки!$D$33)+$AM11*MIN(Настройки!$D$23,Настройки!$D$32)),2)) | S11: =IF($E11<>"Arbeit",0,ROUND(MIN(Настройки!$D$10,Настройки!$D$36)*($AK11*MIN($AN11,$AO11)+$AJ11*MIN(MAX($AN11,Настройки!$D$26),$AO11)+$AL11*MIN(Настройки!$D$26,Настройки!$D$33)+$AM11*MIN(Настройки!$D$23,Настройки!$D$32)),2)) | T11: =IF(OR($W11="",$W10=""),"",24+$W11-$X10) | U11: =IF($L11="","",TRIM(IF($L11>10,"смена >10 ч (§ 3 / § 6 ArbZG) ","")&IF(AND($T11<>"",$T11<11),"отдых <11 ч (§ 5 ArbZG) ","")&IF(AND($L11>9,$J11<0.75),"перерыв <45 мин (§ 4 ArbZG) ","")&IF(AND($L11>6,$L11<=9,$J11<0.5),"перерыв <30 мин (§ 4 ArbZG)",""))) | W11: =IF($H11="","",$H11) | X11: =IF($H11="","",$I11+IF($I11<=$H11,24,0)) | Y11: =IF(OR($K11="",$K11=0),0,$L11/$K11) | Z11: =IF($A11="",0,IF(WEEKDAY($A11,2)=7,1,0)) | AA11: =IF($A11="",0,IF(WEEKDAY($A11+1,2)=7,1,0)) | AB11: =IF($A11="",0,MIN(1,COUNTIF(Feiertage!$A$4:$A$43,$A11))) | AC11: =IF($A11="",0,MIN(1,COUNTIF(Feiertage!$A$4:$A$43,$A11+1))) | AD11: =IFERROR(INDEX(Feiertage!$D$4:$D$43,MATCH($A11,Feiertage!$A$4:$A$43,0)),Настройки!$D$34) | AE11: =IFERROR(INDEX(Feiertage!$D$4:$D$43,MATCH($A11+1,Feiertage!$A$4:$A$43,0)),Настройки!$D$34) | AF11: =IF($W11="",0,MAX(0,MIN($X11,Настройки!$D$25)-MAX($W11,0))+MAX(0,MIN($X11,24)-MAX($W11,Настройки!$D$24))) | AG11: =IF($W11="",0,MAX(0,MIN($X11,24+Настройки!$D$25)-MAX($W11,24))) | AH11: =IF($W11="",0,MAX(0,MIN($X11,24)-MAX($W11,0))) | AI11: =IF($W11="",0,MAX(0,MIN($X11,48)-MAX($W11,24))) | AJ11: =($Z11*$AB11*$AH11+$AA11*$AC11*$AI11)*$Y11 | AK11: =$O11-$AJ11 | AL11: =$N11-$AJ11 | AM11: =$M11-(MAX($Z11,$AB11)*$AF11+MAX($AA11,$AC11)*$AG11)*$Y11 | AN11: =IF($G11="j",Настройки!$D$27,IF($G11="n",Настройки!$D$28,IF(Настройки!$D$29="mit FZA",Настройки!$D$27,Настройки!$D$28))) | AO11: =IF($O11=0,Настройки!$D$34,($AB11*$AH11*$AD11+$AC11*$AI11*$AE11)*$Y11/$O11)
A12: =IF(8>Настройки!$D$6,"",DATE(Настройки!$D$4,Настройки!$D$5,8)) | B12: =IF($A12="","",CHOOSE(WEEKDAY($A12,2),"Пн","Вт","Ср","Чт","Пт","Сб","Вс")) | C12: =IF($A12="","",IFERROR(INDEX(Feiertage!$B$4:$B$43,MATCH($A12,Feiertage!$A$4:$A$43,0)),"")) | D12: FREI | H12: =IF($D12="ND",Настройки!$D$42,IF($D12="TD",Настройки!$D$39,"")) | I12: =IF($D12="ND",Настройки!$D$43,IF($D12="TD",Настройки!$D$40,"")) | J12: =IF($D12="ND",Настройки!$D$44,IF($D12="TD",Настройки!$D$41,"")) | K12: =IF($H12="","",$I12-$H12+IF($I12<=$H12,24,0)) | L12: =IF($K12="","",MAX(0,$K12-$J12)) | M12: =($AF12+$AG12)*$Y12 | N12: =($Z12*$AH12+$AA12*$AI12)*$Y12 | O12: =($AB12*$AH12+$AC12*$AI12)*$Y12 | P12: =IF($L12="","",MAX(0,$L12-$O12-$AL12-$AM12)) | Q12: =ROUND(Настройки!$D$10*($AK12*$AN12+$AJ12*MAX($AN12,Настройки!$D$26)+$AL12*Настройки!$D$26+$AM12*Настройки!$D$23),2) | R12: =IF($E12<>"Arbeit",0,ROUND(MIN(Настройки!$D$10,Настройки!$D$35)*($AK12*MIN($AN12,$AO12)+$AJ12*MIN(MAX($AN12,Настройки!$D$26),$AO12)+$AL12*MIN(Настройки!$D$26,Настройки!$D$33)+$AM12*MIN(Настройки!$D$23,Настройки!$D$32)),2)) | S12: =IF($E12<>"Arbeit",0,ROUND(MIN(Настройки!$D$10,Настройки!$D$36)*($AK12*MIN($AN12,$AO12)+$AJ12*MIN(MAX($AN12,Настройки!$D$26),$AO12)+$AL12*MIN(Настройки!$D$26,Настройки!$D$33)+$AM12*MIN(Настройки!$D$23,Настройки!$D$32)),2)) | T12: =IF(OR($W12="",$W11=""),"",24+$W12-$X11) | U12: =IF($L12="","",TRIM(IF($L12>10,"смена >10 ч (§ 3 / § 6 ArbZG) ","")&IF(AND($T12<>"",$T12<11),"отдых <11 ч (§ 5 ArbZG) ","")&IF(AND($L12>9,$J12<0.75),"перерыв <45 мин (§ 4 ArbZG) ","")&IF(AND($L12>6,$L12<=9,$J12<0.5),"перерыв <30 мин (§ 4 ArbZG)",""))) | W12: =IF($H12="","",$H12) | X12: =IF($H12="","",$I12+IF($I12<=$H12,24,0)) | Y12: =IF(OR($K12="",$K12=0),0,$L12/$K12) | Z12: =IF($A12="",0,IF(WEEKDAY($A12,2)=7,1,0)) | AA12: =IF($A12="",0,IF(WEEKDAY($A12+1,2)=7,1,0)) | AB12: =IF($A12="",0,MIN(1,COUNTIF(Feiertage!$A$4:$A$43,$A12))) | AC12: =IF($A12="",0,MIN(1,COUNTIF(Feiertage!$A$4:$A$43,$A12+1))) | AD12: =IFERROR(INDEX(Feiertage!$D$4:$D$43,MATCH($A12,Feiertage!$A$4:$A$43,0)),Настройки!$D$34) | AE12: =IFERROR(INDEX(Feiertage!$D$4:$D$43,MATCH($A12+1,Feiertage!$A$4:$A$43,0)),Настройки!$D$34) | AF12: =IF($W12="",0,MAX(0,MIN($X12,Настройки!$D$25)-MAX($W12,0))+MAX(0,MIN($X12,24)-MAX($W12,Настройки!$D$24))) | AG12: =IF($W12="",0,MAX(0,MIN($X12,24+Настройки!$D$25)-MAX($W12,24))) | AH12: =IF($W12="",0,MAX(0,MIN($X12,24)-MAX($W12,0))) | AI12: =IF($W12="",0,MAX(0,MIN($X12,48)-MAX($W12,24))) | AJ12: =($Z12*$AB12*$AH12+$AA12*$AC12*$AI12)*$Y12 | AK12: =$O12-$AJ12 | AL12: =$N12-$AJ12 | AM12: =$M12-(MAX($Z12,$AB12)*$AF12+MAX($AA12,$AC12)*$AG12)*$Y12 | AN12: =IF($G12="j",Настройки!$D$27,IF($G12="n",Настройки!$D$28,IF(Настройки!$D$29="mit FZA",Настройки!$D$27,Настройки!$D$28))) | AO12: =IF($O12=0,Настройки!$D$34,($AB12*$AH12*$AD12+$AC12*$AI12*$AE12)*$Y12/$O12)
A13: =IF(9>Настройки!$D$6,"",DATE(Настройки!$D$4,Настройки!$D$5,9)) | B13: =IF($A13="","",CHOOSE(WEEKDAY($A13,2),"Пн","Вт","Ср","Чт","Пт","Сб","Вс")) | C13: =IF($A13="","",IFERROR(INDEX(Feiertage!$B$4:$B$43,MATCH($A13,Feiertage!$A$4:$A$43,0)),"")) | D13: TD | E13: Arbeit | H13: =IF($D13="ND",Настройки!$D$42,IF($D13="TD",Настройки!$D$39,"")) | I13: =IF($D13="ND",Настройки!$D$43,IF($D13="TD",Настройки!$D$40,"")) | J13: =IF($D13="ND",Настройки!$D$44,IF($D13="TD",Настройки!$D$41,"")) | K13: =IF($H13="","",$I13-$H13+IF($I13<=$H13,24,0)) | L13: =IF($K13="","",MAX(0,$K13-$J13)) | M13: =($AF13+$AG13)*$Y13 | N13: =($Z13*$AH13+$AA13*$AI13)*$Y13 | O13: =($AB13*$AH13+$AC13*$AI13)*$Y13 | P13: =IF($L13="","",MAX(0,$L13-$O13-$AL13-$AM13)) | Q13: =ROUND(Настройки!$D$10*($AK13*$AN13+$AJ13*MAX($AN13,Настройки!$D$26)+$AL13*Настройки!$D$26+$AM13*Настройки!$D$23),2) | R13: =IF($E13<>"Arbeit",0,ROUND(MIN(Настройки!$D$10,Настройки!$D$35)*($AK13*MIN($AN13,$AO13)+$AJ13*MIN(MAX($AN13,Настройки!$D$26),$AO13)+$AL13*MIN(Настройки!$D$26,Настройки!$D$33)+$AM13*MIN(Настройки!$D$23,Настройки!$D$32)),2)) | S13: =IF($E13<>"Arbeit",0,ROUND(MIN(Настройки!$D$10,Настройки!$D$36)*($AK13*MIN($AN13,$AO13)+$AJ13*MIN(MAX($AN13,Настройки!$D$26),$AO13)+$AL13*MIN(Настройки!$D$26,Настройки!$D$33)+$AM13*MIN(Настройки!$D$23,Настройки!$D$32)),2)) | T13: =IF(OR($W13="",$W12=""),"",24+$W13-$X12) | U13: =IF($L13="","",TRIM(IF($L13>10,"смена >10 ч (§ 3 / § 6 ArbZG) ","")&IF(AND($T13<>"",$T13<11),"отдых <11 ч (§ 5 ArbZG) ","")&IF(AND($L13>9,$J13<0.75),"перерыв <45 мин (§ 4 ArbZG) ","")&IF(AND($L13>6,$L13<=9,$J13<0.5),"перерыв <30 мин (§ 4 ArbZG)",""))) | W13: =IF($H13="","",$H13) | X13: =IF($H13="","",$I13+IF($I13<=$H13,24,0)) | Y13: =IF(OR($K13="",$K13=0),0,$L13/$K13) | Z13: =IF($A13="",0,IF(WEEKDAY($A13,2)=7,1,0)) | AA13: =IF($A13="",0,IF(WEEKDAY($A13+1,2)=7,1,0)) | AB13: =IF($A13="",0,MIN(1,COUNTIF(Feiertage!$A$4:$A$43,$A13))) | AC13: =IF($A13="",0,MIN(1,COUNTIF(Feiertage!$A$4:$A$43,$A13+1))) | AD13: =IFERROR(INDEX(Feiertage!$D$4:$D$43,MATCH($A13,Feiertage!$A$4:$A$43,0)),Настройки!$D$34) | AE13: =IFERROR(INDEX(Feiertage!$D$4:$D$43,MATCH($A13+1,Feiertage!$A$4:$A$43,0)),Настройки!$D$34) | AF13: =IF($W13="",0,MAX(0,MIN($X13,Настройки!$D$25)-MAX($W13,0))+MAX(0,MIN($X13,24)-MAX($W13,Настройки!$D$24))) | AG13: =IF($W13="",0,MAX(0,MIN($X13,24+Настройки!$D$25)-MAX($W13,24))) | AH13: =IF($W13="",0,MAX(0,MIN($X13,24)-MAX($W13,0))) | AI13: =IF($W13="",0,MAX(0,MIN($X13,48)-MAX($W13,24))) | AJ13: =($Z13*$AB13*$AH13+$AA13*$AC13*$AI13)*$Y13 | AK13: =$O13-$AJ13 | AL13: =$N13-$AJ13 | AM13: =$M13-(MAX($Z13,$AB13)*$AF13+MAX($AA13,$AC13)*$AG13)*$Y13 | AN13: =IF($G13="j",Настройки!$D$27,IF($G13="n",Настройки!$D$28,IF(Настройки!$D$29="mit FZA",Настройки!$D$27,Настройки!$D$28))) | AO13: =IF($O13=0,Настройки!$D$34,($AB13*$AH13*$AD13+$AC13*$AI13*$AE13)*$Y13/$O13)
A14: =IF(10>Настройки!$D$6,"",DATE(Настройки!$D$4,Настройки!$D$5,10)) | B14: =IF($A14="","",CHOOSE(WEEKDAY($A14,2),"Пн","Вт","Ср","Чт","Пт","Сб","Вс")) | C14: =IF($A14="","",IFERROR(INDEX(Feiertage!$B$4:$B$43,MATCH($A14,Feiertage!$A$4:$A$43,0)),"")) | D14: TD | E14: Arbeit | H14: =IF($D14="ND",Настройки!$D$42,IF($D14="TD",Настройки!$D$39,"")) | I14: =IF($D14="ND",Настройки!$D$43,IF($D14="TD",Настройки!$D$40,"")) | J14: =IF($D14="ND",Настройки!$D$44,IF($D14="TD",Настройки!$D$41,"")) | K14: =IF($H14="","",$I14-$H14+IF($I14<=$H14,24,0)) | L14: =IF($K14="","",MAX(0,$K14-$J14)) | M14: =($AF14+$AG14)*$Y14 | N14: =($Z14*$AH14+$AA14*$AI14)*$Y14 | O14: =($AB14*$AH14+$AC14*$AI14)*$Y14 | P14: =IF($L14="","",MAX(0,$L14-$O14-$AL14-$AM14)) | Q14: =ROUND(Настройки!$D$10*($AK14*$AN14+$AJ14*MAX($AN14,Настройки!$D$26)+$AL14*Настройки!$D$26+$AM14*Настройки!$D$23),2) | R14: =IF($E14<>"Arbeit",0,ROUND(MIN(Настройки!$D$10,Настройки!$D$35)*($AK14*MIN($AN14,$AO14)+$AJ14*MIN(MAX($AN14,Настройки!$D$26),$AO14)+$AL14*MIN(Настройки!$D$26,Настройки!$D$33)+$AM14*MIN(Настройки!$D$23,Настройки!$D$32)),2)) | S14: =IF($E14<>"Arbeit",0,ROUND(MIN(Настройки!$D$10,Настройки!$D$36)*($AK14*MIN($AN14,$AO14)+$AJ14*MIN(MAX($AN14,Настройки!$D$26),$AO14)+$AL14*MIN(Настройки!$D$26,Настройки!$D$33)+$AM14*MIN(Настройки!$D$23,Настройки!$D$32)),2)) | T14: =IF(OR($W14="",$W13=""),"",24+$W14-$X13) | U14: =IF($L14="","",TRIM(IF($L14>10,"смена >10 ч (§ 3 / § 6 ArbZG) ","")&IF(AND($T14<>"",$T14<11),"отдых <11 ч (§ 5 ArbZG) ","")&IF(AND($L14>9,$J14<0.75),"перерыв <45 мин (§ 4 ArbZG) ","")&IF(AND($L14>6,$L14<=9,$J14<0.5),"перерыв <30 мин (§ 4 ArbZG)",""))) | W14: =IF($H14="","",$H14) | X14: =IF($H14="","",$I14+IF($I14<=$H14,24,0)) | Y14: =IF(OR($K14="",$K14=0),0,$L14/$K14) | Z14: =IF($A14="",0,IF(WEEKDAY($A14,2)=7,1,0)) | AA14: =IF($A14="",0,IF(WEEKDAY($A14+1,2)=7,1,0)) | AB14: =IF($A14="",0,MIN(1,COUNTIF(Feiertage!$A$4:$A$43,$A14))) | AC14: =IF($A14="",0,MIN(1,COUNTIF(Feiertage!$A$4:$A$43,$A14+1))) | AD14: =IFERROR(INDEX(Feiertage!$D$4:$D$43,MATCH($A14,Feiertage!$A$4:$A$43,0)),Настройки!$D$34) | AE14: =IFERROR(INDEX(Feiertage!$D$4:$D$43,MATCH($A14+1,Feiertage!$A$4:$A$43,0)),Настройки!$D$34) | AF14: =IF($W14="",0,MAX(0,MIN($X14,Настройки!$D$25)-MAX($W14,0))+MAX(0,MIN($X14,24)-MAX($W14,Настройки!$D$24))) | AG14: =IF($W14="",0,MAX(0,MIN($X14,24+Настройки!$D$25)-MAX($W14,24))) | AH14: =IF($W14="",0,MAX(0,MIN($X14,24)-MAX($W14,0))) | AI14: =IF($W14="",0,MAX(0,MIN($X14,48)-MAX($W14,24))) | AJ14: =($Z14*$AB14*$AH14+$AA14*$AC14*$AI14)*$Y14 | AK14: =$O14-$AJ14 | AL14: =$N14-$AJ14 | AM14: =$M14-(MAX($Z14,$AB14)*$AF14+MAX($AA14,$AC14)*$AG14)*$Y14 | AN14: =IF($G14="j",Настройки!$D$27,IF($G14="n",Настройки!$D$28,IF(Настройки!$D$29="mit FZA",Настройки!$D$27,Настройки!$D$28))) | AO14: =IF($O14=0,Настройки!$D$34,($AB14*$AH14*$AD14+$AC14*$AI14*$AE14)*$Y14/$O14)
A15: =IF(11>Настройки!$D$6,"",DATE(Настройки!$D$4,Настройки!$D$5,11)) | B15: =IF($A15="","",CHOOSE(WEEKDAY($A15,2),"Пн","Вт","Ср","Чт","Пт","Сб","Вс")) | C15: =IF($A15="","",IFERROR(INDEX(Feiertage!$B$4:$B$43,MATCH($A15,Feiertage!$A$4:$A$43,0)),"")) | D15: TD | E15: Arbeit | H15: =IF($D15="ND",Настройки!$D$42,IF($D15="TD",Настройки!$D$39,"")) | I15: =IF($D15="ND",Настройки!$D$43,IF($D15="TD",Настройки!$D$40,"")) | J15: =IF($D15="ND",Настройки!$D$44,IF($D15="TD",Настройки!$D$41,"")) | K15: =IF($H15="","",$I15-$H15+IF($I15<=$H15,24,0)) | L15: =IF($K15="","",MAX(0,$K15-$J15)) | M15: =($AF15+$AG15)*$Y15 | N15: =($Z15*$AH15+$AA15*$AI15)*$Y15 | O15: =($AB15*$AH15+$AC15*$AI15)*$Y15 | P15: =IF($L15="","",MAX(0,$L15-$O15-$AL15-$AM15)) | Q15: =ROUND(Настройки!$D$10*($AK15*$AN15+$AJ15*MAX($AN15,Настройки!$D$26)+$AL15*Настройки!$D$26+$AM15*Настройки!$D$23),2) | R15: =IF($E15<>"Arbeit",0,ROUND(MIN(Настройки!$D$10,Настройки!$D$35)*($AK15*MIN($AN15,$AO15)+$AJ15*MIN(MAX($AN15,Настройки!$D$26),$AO15)+$AL15*MIN(Настройки!$D$26,Настройки!$D$33)+$AM15*MIN(Настройки!$D$23,Настройки!$D$32)),2)) | S15: =IF($E15<>"Arbeit",0,ROUND(MIN(Настройки!$D$10,Настройки!$D$36)*($AK15*MIN($AN15,$AO15)+$AJ15*MIN(MAX($AN15,Настройки!$D$26),$AO15)+$AL15*MIN(Настройки!$D$26,Настройки!$D$33)+$AM15*MIN(Настройки!$D$23,Настройки!$D$32)),2)) | T15: =IF(OR($W15="",$W14=""),"",24+$W15-$X14) | U15: =IF($L15="","",TRIM(IF($L15>10,"смена >10 ч (§ 3 / § 6 ArbZG) ","")&IF(AND($T15<>"",$T15<11),"отдых <11 ч (§ 5 ArbZG) ","")&IF(AND($L15>9,$J15<0.75),"перерыв <45 мин (§ 4 ArbZG) ","")&IF(AND($L15>6,$L15<=9,$J15<0.5),"перерыв <30 мин (§ 4 ArbZG)",""))) | W15: =IF($H15="","",$H15) | X15: =IF($H15="","",$I15+IF($I15<=$H15,24,0)) | Y15: =IF(OR($K15="",$K15=0),0,$L15/$K15) | Z15: =IF($A15="",0,IF(WEEKDAY($A15,2)=7,1,0)) | AA15: =IF($A15="",0,IF(WEEKDAY($A15+1,2)=7,1,0)) | AB15: =IF($A15="",0,MIN(1,COUNTIF(Feiertage!$A$4:$A$43,$A15))) | AC15: =IF($A15="",0,MIN(1,COUNTIF(Feiertage!$A$4:$A$43,$A15+1))) | AD15: =IFERROR(INDEX(Feiertage!$D$4:$D$43,MATCH($A15,Feiertage!$A$4:$A$43,0)),Настройки!$D$34) | AE15: =IFERROR(INDEX(Feiertage!$D$4:$D$43,MATCH($A15+1,Feiertage!$A$4:$A$43,0)),Настройки!$D$34) | AF15: =IF($W15="",0,MAX(0,MIN($X15,Настройки!$D$25)-MAX($W15,0))+MAX(0,MIN($X15,24)-MAX($W15,Настройки!$D$24))) | AG15: =IF($W15="",0,MAX(0,MIN($X15,24+Настройки!$D$25)-MAX($W15,24))) | AH15: =IF($W15="",0,MAX(0,MIN($X15,24)-MAX($W15,0))) | AI15: =IF($W15="",0,MAX(0,MIN($X15,48)-MAX($W15,24))) | AJ15: =($Z15*$AB15*$AH15+$AA15*$AC15*$AI15)*$Y15 | AK15: =$O15-$AJ15 | AL15: =$N15-$AJ15 | AM15: =$M15-(MAX($Z15,$AB15)*$AF15+MAX($AA15,$AC15)*$AG15)*$Y15 | AN15: =IF($G15="j",Настройки!$D$27,IF($G15="n",Настройки!$D$28,IF(Настройки!$D$29="mit FZA",Настройки!$D$27,Настройки!$D$28))) | AO15: =IF($O15=0,Настройки!$D$34,($AB15*$AH15*$AD15+$AC15*$AI15*$AE15)*$Y15/$O15)
A16: =IF(12>Настройки!$D$6,"",DATE(Настройки!$D$4,Настройки!$D$5,12)) | B16: =IF($A16="","",CHOOSE(WEEKDAY($A16,2),"Пн","Вт","Ср","Чт","Пт","Сб","Вс")) | C16: =IF($A16="","",IFERROR(INDEX(Feiertage!$B$4:$B$43,MATCH($A16,Feiertage!$A$4:$A$43,0)),"")) | D16: TD | E16: Arbeit | H16: =IF($D16="ND",Настройки!$D$42,IF($D16="TD",Настройки!$D$39,"")) | I16: =IF($D16="ND",Настройки!$D$43,IF($D16="TD",Настройки!$D$40,"")) | J16: =IF($D16="ND",Настройки!$D$44,IF($D16="TD",Настройки!$D$41,"")) | K16: =IF($H16="","",$I16-$H16+IF($I16<=$H16,24,0)) | L16: =IF($K16="","",MAX(0,$K16-$J16)) | M16: =($AF16+$AG16)*$Y16 | N16: =($Z16*$AH16+$AA16*$AI16)*$Y16 | O16: =($AB16*$AH16+$AC16*$AI16)*$Y16 | P16: =IF($L16="","",MAX(0,$L16-$O16-$AL16-$AM16)) | Q16: =ROUND(Настройки!$D$10*($AK16*$AN16+$AJ16*MAX($AN16,Настройки!$D$26)+$AL16*Настройки!$D$26+$AM16*Настройки!$D$23),2) | R16: =IF($E16<>"Arbeit",0,ROUND(MIN(Настройки!$D$10,Настройки!$D$35)*($AK16*MIN($AN16,$AO16)+$AJ16*MIN(MAX($AN16,Настройки!$D$26),$AO16)+$AL16*MIN(Настройки!$D$26,Настройки!$D$33)+$AM16*MIN(Настройки!$D$23,Настройки!$D$32)),2)) | S16: =IF($E16<>"Arbeit",0,ROUND(MIN(Настройки!$D$10,Настройки!$D$36)*($AK16*MIN($AN16,$AO16)+$AJ16*MIN(MAX($AN16,Настройки!$D$26),$AO16)+$AL16*MIN(Настройки!$D$26,Настройки!$D$33)+$AM16*MIN(Настройки!$D$23,Настройки!$D$32)),2)) | T16: =IF(OR($W16="",$W15=""),"",24+$W16-$X15) | U16: =IF($L16="","",TRIM(IF($L16>10,"смена >10 ч (§ 3 / § 6 ArbZG) ","")&IF(AND($T16<>"",$T16<11),"отдых <11 ч (§ 5 ArbZG) ","")&IF(AND($L16>9,$J16<0.75),"перерыв <45 мин (§ 4 ArbZG) ","")&IF(AND($L16>6,$L16<=9,$J16<0.5),"перерыв <30 мин (§ 4 ArbZG)",""))) | W16: =IF($H16="","",$H16) | X16: =IF($H16="","",$I16+IF($I16<=$H16,24,0)) | Y16: =IF(OR($K16="",$K16=0),0,$L16/$K16) | Z16: =IF($A16="",0,IF(WEEKDAY($A16,2)=7,1,0)) | AA16: =IF($A16="",0,IF(WEEKDAY($A16+1,2)=7,1,0)) | AB16: =IF($A16="",0,MIN(1,COUNTIF(Feiertage!$A$4:$A$43,$A16))) | AC16: =IF($A16="",0,MIN(1,COUNTIF(Feiertage!$A$4:$A$43,$A16+1))) | AD16: =IFERROR(INDEX(Feiertage!$D$4:$D$43,MATCH($A16,Feiertage!$A$4:$A$43,0)),Настройки!$D$34) | AE16: =IFERROR(INDEX(Feiertage!$D$4:$D$43,MATCH($A16+1,Feiertage!$A$4:$A$43,0)),Настройки!$D$34) | AF16: =IF($W16="",0,MAX(0,MIN($X16,Настройки!$D$25)-MAX($W16,0))+MAX(0,MIN($X16,24)-MAX($W16,Настройки!$D$24))) | AG16: =IF($W16="",0,MAX(0,MIN($X16,24+Настройки!$D$25)-MAX($W16,24))) | AH16: =IF($W16="",0,MAX(0,MIN($X16,24)-MAX($W16,0))) | AI16: =IF($W16="",0,MAX(0,MIN($X16,48)-MAX($W16,24))) | AJ16: =($Z16*$AB16*$AH16+$AA16*$AC16*$AI16)*$Y16 | AK16: =$O16-$AJ16 | AL16: =$N16-$AJ16 | AM16: =$M16-(MAX($Z16,$AB16)*$AF16+MAX($AA16,$AC16)*$AG16)*$Y16 | AN16: =IF($G16="j",Настройки!$D$27,IF($G16="n",Настройки!$D$28,IF(Настройки!$D$29="mit FZA",Настройки!$D$27,Настройки!$D$28))) | AO16: =IF($O16=0,Настройки!$D$34,($AB16*$AH16*$AD16+$AC16*$AI16*$AE16)*$Y16/$O16)
A17: =IF(13>Настройки!$D$6,"",DATE(Настройки!$D$4,Настройки!$D$5,13)) | B17: =IF($A17="","",CHOOSE(WEEKDAY($A17,2),"Пн","Вт","Ср","Чт","Пт","Сб","Вс")) | C17: =IF($A17="","",IFERROR(INDEX(Feiertage!$B$4:$B$43,MATCH($A17,Feiertage!$A$4:$A$43,0)),"")) | D17: TD | E17: Arbeit | H17: =IF($D17="ND",Настройки!$D$42,IF($D17="TD",Настройки!$D$39,"")) | I17: =IF($D17="ND",Настройки!$D$43,IF($D17="TD",Настройки!$D$40,"")) | J17: =IF($D17="ND",Настройки!$D$44,IF($D17="TD",Настройки!$D$41,"")) | K17: =IF($H17="","",$I17-$H17+IF($I17<=$H17,24,0)) | L17: =IF($K17="","",MAX(0,$K17-$J17)) | M17: =($AF17+$AG17)*$Y17 | N17: =($Z17*$AH17+$AA17*$AI17)*$Y17 | O17: =($AB17*$AH17+$AC17*$AI17)*$Y17 | P17: =IF($L17="","",MAX(0,$L17-$O17-$AL17-$AM17)) | Q17: =ROUND(Настройки!$D$10*($AK17*$AN17+$AJ17*MAX($AN17,Настройки!$D$26)+$AL17*Настройки!$D$26+$AM17*Настройки!$D$23),2) | R17: =IF($E17<>"Arbeit",0,ROUND(MIN(Настройки!$D$10,Настройки!$D$35)*($AK17*MIN($AN17,$AO17)+$AJ17*MIN(MAX($AN17,Настройки!$D$26),$AO17)+$AL17*MIN(Настройки!$D$26,Настройки!$D$33)+$AM17*MIN(Настройки!$D$23,Настройки!$D$32)),2)) | S17: =IF($E17<>"Arbeit",0,ROUND(MIN(Настройки!$D$10,Настройки!$D$36)*($AK17*MIN($AN17,$AO17)+$AJ17*MIN(MAX($AN17,Настройки!$D$26),$AO17)+$AL17*MIN(Настройки!$D$26,Настройки!$D$33)+$AM17*MIN(Настройки!$D$23,Настройки!$D$32)),2)) | T17: =IF(OR($W17="",$W16=""),"",24+$W17-$X16) | U17: =IF($L17="","",TRIM(IF($L17>10,"смена >10 ч (§ 3 / § 6 ArbZG) ","")&IF(AND($T17<>"",$T17<11),"отдых <11 ч (§ 5 ArbZG) ","")&IF(AND($L17>9,$J17<0.75),"перерыв <45 мин (§ 4 ArbZG) ","")&IF(AND($L17>6,$L17<=9,$J17<0.5),"перерыв <30 мин (§ 4 ArbZG)",""))) | W17: =IF($H17="","",$H17) | X17: =IF($H17="","",$I17+IF($I17<=$H17,24,0)) | Y17: =IF(OR($K17="",$K17=0),0,$L17/$K17) | Z17: =IF($A17="",0,IF(WEEKDAY($A17,2)=7,1,0)) | AA17: =IF($A17="",0,IF(WEEKDAY($A17+1,2)=7,1,0)) | AB17: =IF($A17="",0,MIN(1,COUNTIF(Feiertage!$A$4:$A$43,$A17))) | AC17: =IF($A17="",0,MIN(1,COUNTIF(Feiertage!$A$4:$A$43,$A17+1))) | AD17: =IFERROR(INDEX(Feiertage!$D$4:$D$43,MATCH($A17,Feiertage!$A$4:$A$43,0)),Настройки!$D$34) | AE17: =IFERROR(INDEX(Feiertage!$D$4:$D$43,MATCH($A17+1,Feiertage!$A$4:$A$43,0)),Настройки!$D$34) | AF17: =IF($W17="",0,MAX(0,MIN($X17,Настройки!$D$25)-MAX($W17,0))+MAX(0,MIN($X17,24)-MAX($W17,Настройки!$D$24))) | AG17: =IF($W17="",0,MAX(0,MIN($X17,24+Настройки!$D$25)-MAX($W17,24))) | AH17: =IF($W17="",0,MAX(0,MIN($X17,24)-MAX($W17,0))) | AI17: =IF($W17="",0,MAX(0,MIN($X17,48)-MAX($W17,24))) | AJ17: =($Z17*$AB17*$AH17+$AA17*$AC17*$AI17)*$Y17 | AK17: =$O17-$AJ17 | AL17: =$N17-$AJ17 | AM17: =$M17-(MAX($Z17,$AB17)*$AF17+MAX($AA17,$AC17)*$AG17)*$Y17 | AN17: =IF($G17="j",Настройки!$D$27,IF($G17="n",Настройки!$D$28,IF(Настройки!$D$29="mit FZA",Настройки!$D$27,Настройки!$D$28))) | AO17: =IF($O17=0,Настройки!$D$34,($AB17*$AH17*$AD17+$AC17*$AI17*$AE17)*$Y17/$O17)
A18: =IF(14>Настройки!$D$6,"",DATE(Настройки!$D$4,Настройки!$D$5,14)) | B18: =IF($A18="","",CHOOSE(WEEKDAY($A18,2),"Пн","Вт","Ср","Чт","Пт","Сб","Вс")) | C18: =IF($A18="","",IFERROR(INDEX(Feiertage!$B$4:$B$43,MATCH($A18,Feiertage!$A$4:$A$43,0)),"")) | D18: TD | E18: Arbeit | H18: =IF($D18="ND",Настройки!$D$42,IF($D18="TD",Настройки!$D$39,"")) | I18: =IF($D18="ND",Настройки!$D$43,IF($D18="TD",Настройки!$D$40,"")) | J18: =IF($D18="ND",Настройки!$D$44,IF($D18="TD",Настройки!$D$41,"")) | K18: =IF($H18="","",$I18-$H18+IF($I18<=$H18,24,0)) | L18: =IF($K18="","",MAX(0,$K18-$J18)) | M18: =($AF18+$AG18)*$Y18 | N18: =($Z18*$AH18+$AA18*$AI18)*$Y18 | O18: =($AB18*$AH18+$AC18*$AI18)*$Y18 | P18: =IF($L18="","",MAX(0,$L18-$O18-$AL18-$AM18)) | Q18: =ROUND(Настройки!$D$10*($AK18*$AN18+$AJ18*MAX($AN18,Настройки!$D$26)+$AL18*Настройки!$D$26+$AM18*Настройки!$D$23),2) | R18: =IF($E18<>"Arbeit",0,ROUND(MIN(Настройки!$D$10,Настройки!$D$35)*($AK18*MIN($AN18,$AO18)+$AJ18*MIN(MAX($AN18,Настройки!$D$26),$AO18)+$AL18*MIN(Настройки!$D$26,Настройки!$D$33)+$AM18*MIN(Настройки!$D$23,Настройки!$D$32)),2)) | S18: =IF($E18<>"Arbeit",0,ROUND(MIN(Настройки!$D$10,Настройки!$D$36)*($AK18*MIN($AN18,$AO18)+$AJ18*MIN(MAX($AN18,Настройки!$D$26),$AO18)+$AL18*MIN(Настройки!$D$26,Настройки!$D$33)+$AM18*MIN(Настройки!$D$23,Настройки!$D$32)),2)) | T18: =IF(OR($W18="",$W17=""),"",24+$W18-$X17) | U18: =IF($L18="","",TRIM(IF($L18>10,"смена >10 ч (§ 3 / § 6 ArbZG) ","")&IF(AND($T18<>"",$T18<11),"отдых <11 ч (§ 5 ArbZG) ","")&IF(AND($L18>9,$J18<0.75),"перерыв <45 мин (§ 4 ArbZG) ","")&IF(AND($L18>6,$L18<=9,$J18<0.5),"перерыв <30 мин (§ 4 ArbZG)",""))) | W18: =IF($H18="","",$H18) | X18: =IF($H18="","",$I18+IF($I18<=$H18,24,0)) | Y18: =IF(OR($K18="",$K18=0),0,$L18/$K18) | Z18: =IF($A18="",0,IF(WEEKDAY($A18,2)=7,1,0)) | AA18: =IF($A18="",0,IF(WEEKDAY($A18+1,2)=7,1,0)) | AB18: =IF($A18="",0,MIN(1,COUNTIF(Feiertage!$A$4:$A$43,$A18))) | AC18: =IF($A18="",0,MIN(1,COUNTIF(Feiertage!$A$4:$A$43,$A18+1))) | AD18: =IFERROR(INDEX(Feiertage!$D$4:$D$43,MATCH($A18,Feiertage!$A$4:$A$43,0)),Настройки!$D$34) | AE18: =IFERROR(INDEX(Feiertage!$D$4:$D$43,MATCH($A18+1,Feiertage!$A$4:$A$43,0)),Настройки!$D$34) | AF18: =IF($W18="",0,MAX(0,MIN($X18,Настройки!$D$25)-MAX($W18,0))+MAX(0,MIN($X18,24)-MAX($W18,Настройки!$D$24))) | AG18: =IF($W18="",0,MAX(0,MIN($X18,24+Настройки!$D$25)-MAX($W18,24))) | AH18: =IF($W18="",0,MAX(0,MIN($X18,24)-MAX($W18,0))) | AI18: =IF($W18="",0,MAX(0,MIN($X18,48)-MAX($W18,24))) | AJ18: =($Z18*$AB18*$AH18+$AA18*$AC18*$AI18)*$Y18 | AK18: =$O18-$AJ18 | AL18: =$N18-$AJ18 | AM18: =$M18-(MAX($Z18,$AB18)*$AF18+MAX($AA18,$AC18)*$AG18)*$Y18 | AN18: =IF($G18="j",Настройки!$D$27,IF($G18="n",Настройки!$D$28,IF(Настройки!$D$29="mit FZA",Настройки!$D$27,Настройки!$D$28))) | AO18: =IF($O18=0,Настройки!$D$34,($AB18*$AH18*$AD18+$AC18*$AI18*$AE18)*$Y18/$O18)
A19: =IF(15>Настройки!$D$6,"",DATE(Настройки!$D$4,Настройки!$D$5,15)) | B19: =IF($A19="","",CHOOSE(WEEKDAY($A19,2),"Пн","Вт","Ср","Чт","Пт","Сб","Вс")) | C19: =IF($A19="","",IFERROR(INDEX(Feiertage!$B$4:$B$43,MATCH($A19,Feiertage!$A$4:$A$43,0)),"")) | D19: FREI | H19: =IF($D19="ND",Настройки!$D$42,IF($D19="TD",Настройки!$D$39,"")) | I19: =IF($D19="ND",Настройки!$D$43,IF($D19="TD",Настройки!$D$40,"")) | J19: =IF($D19="ND",Настройки!$D$44,IF($D19="TD",Настройки!$D$41,"")) | K19: =IF($H19="","",$I19-$H19+IF($I19<=$H19,24,0)) | L19: =IF($K19="","",MAX(0,$K19-$J19)) | M19: =($AF19+$AG19)*$Y19 | N19: =($Z19*$AH19+$AA19*$AI19)*$Y19 | O19: =($AB19*$AH19+$AC19*$AI19)*$Y19 | P19: =IF($L19="","",MAX(0,$L19-$O19-$AL19-$AM19)) | Q19: =ROUND(Настройки!$D$10*($AK19*$AN19+$AJ19*MAX($AN19,Настройки!$D$26)+$AL19*Настройки!$D$26+$AM19*Настройки!$D$23),2) | R19: =IF($E19<>"Arbeit",0,ROUND(MIN(Настройки!$D$10,Настройки!$D$35)*($AK19*MIN($AN19,$AO19)+$AJ19*MIN(MAX($AN19,Настройки!$D$26),$AO19)+$AL19*MIN(Настройки!$D$26,Настройки!$D$33)+$AM19*MIN(Настройки!$D$23,Настройки!$D$32)),2)) | S19: =IF($E19<>"Arbeit",0,ROUND(MIN(Настройки!$D$10,Настройки!$D$36)*($AK19*MIN($AN19,$AO19)+$AJ19*MIN(MAX($AN19,Настройки!$D$26),$AO19)+$AL19*MIN(Настройки!$D$26,Настройки!$D$33)+$AM19*MIN(Настройки!$D$23,Настройки!$D$32)),2)) | T19: =IF(OR($W19="",$W18=""),"",24+$W19-$X18) | U19: =IF($L19="","",TRIM(IF($L19>10,"смена >10 ч (§ 3 / § 6 ArbZG) ","")&IF(AND($T19<>"",$T19<11),"отдых <11 ч (§ 5 ArbZG) ","")&IF(AND($L19>9,$J19<0.75),"перерыв <45 мин (§ 4 ArbZG) ","")&IF(AND($L19>6,$L19<=9,$J19<0.5),"перерыв <30 мин (§ 4 ArbZG)",""))) | W19: =IF($H19="","",$H19) | X19: =IF($H19="","",$I19+IF($I19<=$H19,24,0)) | Y19: =IF(OR($K19="",$K19=0),0,$L19/$K19) | Z19: =IF($A19="",0,IF(WEEKDAY($A19,2)=7,1,0)) | AA19: =IF($A19="",0,IF(WEEKDAY($A19+1,2)=7,1,0)) | AB19: =IF($A19="",0,MIN(1,COUNTIF(Feiertage!$A$4:$A$43,$A19))) | AC19: =IF($A19="",0,MIN(1,COUNTIF(Feiertage!$A$4:$A$43,$A19+1))) | AD19: =IFERROR(INDEX(Feiertage!$D$4:$D$43,MATCH($A19,Feiertage!$A$4:$A$43,0)),Настройки!$D$34) | AE19: =IFERROR(INDEX(Feiertage!$D$4:$D$43,MATCH($A19+1,Feiertage!$A$4:$A$43,0)),Настройки!$D$34) | AF19: =IF($W19="",0,MAX(0,MIN($X19,Настройки!$D$25)-MAX($W19,0))+MAX(0,MIN($X19,24)-MAX($W19,Настройки!$D$24))) | AG19: =IF($W19="",0,MAX(0,MIN($X19,24+Настройки!$D$25)-MAX($W19,24))) | AH19: =IF($W19="",0,MAX(0,MIN($X19,24)-MAX($W19,0))) | AI19: =IF($W19="",0,MAX(0,MIN($X19,48)-MAX($W19,24))) | AJ19: =($Z19*$AB19*$AH19+$AA19*$AC19*$AI19)*$Y19 | AK19: =$O19-$AJ19 | AL19: =$N19-$AJ19 | AM19: =$M19-(MAX($Z19,$AB19)*$AF19+MAX($AA19,$AC19)*$AG19)*$Y19 | AN19: =IF($G19="j",Настройки!$D$27,IF($G19="n",Настройки!$D$28,IF(Настройки!$D$29="mit FZA",Настройки!$D$27,Настройки!$D$28))) | AO19: =IF($O19=0,Настройки!$D$34,($AB19*$AH19*$AD19+$AC19*$AI19*$AE19)*$Y19/$O19)
A20: =IF(16>Настройки!$D$6,"",DATE(Настройки!$D$4,Настройки!$D$5,16)) | B20: =IF($A20="","",CHOOSE(WEEKDAY($A20,2),"Пн","Вт","Ср","Чт","Пт","Сб","Вс")) | C20: =IF($A20="","",IFERROR(INDEX(Feiertage!$B$4:$B$43,MATCH($A20,Feiertage!$A$4:$A$43,0)),"")) | D20: FREI | H20: =IF($D20="ND",Настройки!$D$42,IF($D20="TD",Настройки!$D$39,"")) | I20: =IF($D20="ND",Настройки!$D$43,IF($D20="TD",Настройки!$D$40,"")) | J20: =IF($D20="ND",Настройки!$D$44,IF($D20="TD",Настройки!$D$41,"")) | K20: =IF($H20="","",$I20-$H20+IF($I20<=$H20,24,0)) | L20: =IF($K20="","",MAX(0,$K20-$J20)) | M20: =($AF20+$AG20)*$Y20 | N20: =($Z20*$AH20+$AA20*$AI20)*$Y20 | O20: =($AB20*$AH20+$AC20*$AI20)*$Y20 | P20: =IF($L20="","",MAX(0,$L20-$O20-$AL20-$AM20)) | Q20: =ROUND(Настройки!$D$10*($AK20*$AN20+$AJ20*MAX($AN20,Настройки!$D$26)+$AL20*Настройки!$D$26+$AM20*Настройки!$D$23),2) | R20: =IF($E20<>"Arbeit",0,ROUND(MIN(Настройки!$D$10,Настройки!$D$35)*($AK20*MIN($AN20,$AO20)+$AJ20*MIN(MAX($AN20,Настройки!$D$26),$AO20)+$AL20*MIN(Настройки!$D$26,Настройки!$D$33)+$AM20*MIN(Настройки!$D$23,Настройки!$D$32)),2)) | S20: =IF($E20<>"Arbeit",0,ROUND(MIN(Настройки!$D$10,Настройки!$D$36)*($AK20*MIN($AN20,$AO20)+$AJ20*MIN(MAX($AN20,Настройки!$D$26),$AO20)+$AL20*MIN(Настройки!$D$26,Настройки!$D$33)+$AM20*MIN(Настройки!$D$23,Настройки!$D$32)),2)) | T20: =IF(OR($W20="",$W19=""),"",24+$W20-$X19) | U20: =IF($L20="","",TRIM(IF($L20>10,"смена >10 ч (§ 3 / § 6 ArbZG) ","")&IF(AND($T20<>"",$T20<11),"отдых <11 ч (§ 5 ArbZG) ","")&IF(AND($L20>9,$J20<0.75),"перерыв <45 мин (§ 4 ArbZG) ","")&IF(AND($L20>6,$L20<=9,$J20<0.5),"перерыв <30 мин (§ 4 ArbZG)",""))) | W20: =IF($H20="","",$H20) | X20: =IF($H20="","",$I20+IF($I20<=$H20,24,0)) | Y20: =IF(OR($K20="",$K20=0),0,$L20/$K20) | Z20: =IF($A20="",0,IF(WEEKDAY($A20,2)=7,1,0)) | AA20: =IF($A20="",0,IF(WEEKDAY($A20+1,2)=7,1,0)) | AB20: =IF($A20="",0,MIN(1,COUNTIF(Feiertage!$A$4:$A$43,$A20))) | AC20: =IF($A20="",0,MIN(1,COUNTIF(Feiertage!$A$4:$A$43,$A20+1))) | AD20: =IFERROR(INDEX(Feiertage!$D$4:$D$43,MATCH($A20,Feiertage!$A$4:$A$43,0)),Настройки!$D$34) | AE20: =IFERROR(INDEX(Feiertage!$D$4:$D$43,MATCH($A20+1,Feiertage!$A$4:$A$43,0)),Настройки!$D$34) | AF20: =IF($W20="",0,MAX(0,MIN($X20,Настройки!$D$25)-MAX($W20,0))+MAX(0,MIN($X20,24)-MAX($W20,Настройки!$D$24))) | AG20: =IF($W20="",0,MAX(0,MIN($X20,24+Настройки!$D$25)-MAX($W20,24))) | AH20: =IF($W20="",0,MAX(0,MIN($X20,24)-MAX($W20,0))) | AI20: =IF($W20="",0,MAX(0,MIN($X20,48)-MAX($W20,24))) | AJ20: =($Z20*$AB20*$AH20+$AA20*$AC20*$AI20)*$Y20 | AK20: =$O20-$AJ20 | AL20: =$N20-$AJ20 | AM20: =$M20-(MAX($Z20,$AB20)*$AF20+MAX($AA20,$AC20)*$AG20)*$Y20 | AN20: =IF($G20="j",Настройки!$D$27,IF($G20="n",Настройки!$D$28,IF(Настройки!$D$29="mit FZA",Настройки!$D$27,Настройки!$D$28))) | AO20: =IF($O20=0,Настройки!$D$34,($AB20*$AH20*$AD20+$AC20*$AI20*$AE20)*$Y20/$O20)
A21: =IF(17>Настройки!$D$6,"",DATE(Настройки!$D$4,Настройки!$D$5,17)) | B21: =IF($A21="","",CHOOSE(WEEKDAY($A21,2),"Пн","Вт","Ср","Чт","Пт","Сб","Вс")) | C21: =IF($A21="","",IFERROR(INDEX(Feiertage!$B$4:$B$43,MATCH($A21,Feiertage!$A$4:$A$43,0)),"")) | D21: FREI | H21: =IF($D21="ND",Настройки!$D$42,IF($D21="TD",Настройки!$D$39,"")) | I21: =IF($D21="ND",Настройки!$D$43,IF($D21="TD",Настройки!$D$40,"")) | J21: =IF($D21="ND",Настройки!$D$44,IF($D21="TD",Настройки!$D$41,"")) | K21: =IF($H21="","",$I21-$H21+IF($I21<=$H21,24,0)) | L21: =IF($K21="","",MAX(0,$K21-$J21)) | M21: =($AF21+$AG21)*$Y21 | N21: =($Z21*$AH21+$AA21*$AI21)*$Y21 | O21: =($AB21*$AH21+$AC21*$AI21)*$Y21 | P21: =IF($L21="","",MAX(0,$L21-$O21-$AL21-$AM21)) | Q21: =ROUND(Настройки!$D$10*($AK21*$AN21+$AJ21*MAX($AN21,Настройки!$D$26)+$AL21*Настройки!$D$26+$AM21*Настройки!$D$23),2) | R21: =IF($E21<>"Arbeit",0,ROUND(MIN(Настройки!$D$10,Настройки!$D$35)*($AK21*MIN($AN21,$AO21)+$AJ21*MIN(MAX($AN21,Настройки!$D$26),$AO21)+$AL21*MIN(Настройки!$D$26,Настройки!$D$33)+$AM21*MIN(Настройки!$D$23,Настройки!$D$32)),2)) | S21: =IF($E21<>"Arbeit",0,ROUND(MIN(Настройки!$D$10,Настройки!$D$36)*($AK21*MIN($AN21,$AO21)+$AJ21*MIN(MAX($AN21,Настройки!$D$26),$AO21)+$AL21*MIN(Настройки!$D$26,Настройки!$D$33)+$AM21*MIN(Настройки!$D$23,Настройки!$D$32)),2)) | T21: =IF(OR($W21="",$W20=""),"",24+$W21-$X20) | U21: =IF($L21="","",TRIM(IF($L21>10,"смена >10 ч (§ 3 / § 6 ArbZG) ","")&IF(AND($T21<>"",$T21<11),"отдых <11 ч (§ 5 ArbZG) ","")&IF(AND($L21>9,$J21<0.75),"перерыв <45 мин (§ 4 ArbZG) ","")&IF(AND($L21>6,$L21<=9,$J21<0.5),"перерыв <30 мин (§ 4 ArbZG)",""))) | W21: =IF($H21="","",$H21) | X21: =IF($H21="","",$I21+IF($I21<=$H21,24,0)) | Y21: =IF(OR($K21="",$K21=0),0,$L21/$K21) | Z21: =IF($A21="",0,IF(WEEKDAY($A21,2)=7,1,0)) | AA21: =IF($A21="",0,IF(WEEKDAY($A21+1,2)=7,1,0)) | AB21: =IF($A21="",0,MIN(1,COUNTIF(Feiertage!$A$4:$A$43,$A21))) | AC21: =IF($A21="",0,MIN(1,COUNTIF(Feiertage!$A$4:$A$43,$A21+1))) | AD21: =IFERROR(INDEX(Feiertage!$D$4:$D$43,MATCH($A21,Feiertage!$A$4:$A$43,0)),Настройки!$D$34) | AE21: =IFERROR(INDEX(Feiertage!$D$4:$D$43,MATCH($A21+1,Feiertage!$A$4:$A$43,0)),Настройки!$D$34) | AF21: =IF($W21="",0,MAX(0,MIN($X21,Настройки!$D$25)-MAX($W21,0))+MAX(0,MIN($X21,24)-MAX($W21,Настройки!$D$24))) | AG21: =IF($W21="",0,MAX(0,MIN($X21,24+Настройки!$D$25)-MAX($W21,24))) | AH21: =IF($W21="",0,MAX(0,MIN($X21,24)-MAX($W21,0))) | AI21: =IF($W21="",0,MAX(0,MIN($X21,48)-MAX($W21,24))) | AJ21: =($Z21*$AB21*$AH21+$AA21*$AC21*$AI21)*$Y21 | AK21: =$O21-$AJ21 | AL21: =$N21-$AJ21 | AM21: =$M21-(MAX($Z21,$AB21)*$AF21+MAX($AA21,$AC21)*$AG21)*$Y21 | AN21: =IF($G21="j",Настройки!$D$27,IF($G21="n",Настройки!$D$28,IF(Настройки!$D$29="mit FZA",Настройки!$D$27,Настройки!$D$28))) | AO21: =IF($O21=0,Настройки!$D$34,($AB21*$AH21*$AD21+$AC21*$AI21*$AE21)*$Y21/$O21)
A22: =IF(18>Настройки!$D$6,"",DATE(Настройки!$D$4,Настройки!$D$5,18)) | B22: =IF($A22="","",CHOOSE(WEEKDAY($A22,2),"Пн","Вт","Ср","Чт","Пт","Сб","Вс")) | C22: =IF($A22="","",IFERROR(INDEX(Feiertage!$B$4:$B$43,MATCH($A22,Feiertage!$A$4:$A$43,0)),"")) | D22: FREI | H22: =IF($D22="ND",Настройки!$D$42,IF($D22="TD",Настройки!$D$39,"")) | I22: =IF($D22="ND",Настройки!$D$43,IF($D22="TD",Настройки!$D$40,"")) | J22: =IF($D22="ND",Настройки!$D$44,IF($D22="TD",Настройки!$D$41,"")) | K22: =IF($H22="","",$I22-$H22+IF($I22<=$H22,24,0)) | L22: =IF($K22="","",MAX(0,$K22-$J22)) | M22: =($AF22+$AG22)*$Y22 | N22: =($Z22*$AH22+$AA22*$AI22)*$Y22 | O22: =($AB22*$AH22+$AC22*$AI22)*$Y22 | P22: =IF($L22="","",MAX(0,$L22-$O22-$AL22-$AM22)) | Q22: =ROUND(Настройки!$D$10*($AK22*$AN22+$AJ22*MAX($AN22,Настройки!$D$26)+$AL22*Настройки!$D$26+$AM22*Настройки!$D$23),2) | R22: =IF($E22<>"Arbeit",0,ROUND(MIN(Настройки!$D$10,Настройки!$D$35)*($AK22*MIN($AN22,$AO22)+$AJ22*MIN(MAX($AN22,Настройки!$D$26),$AO22)+$AL22*MIN(Настройки!$D$26,Настройки!$D$33)+$AM22*MIN(Настройки!$D$23,Настройки!$D$32)),2)) | S22: =IF($E22<>"Arbeit",0,ROUND(MIN(Настройки!$D$10,Настройки!$D$36)*($AK22*MIN($AN22,$AO22)+$AJ22*MIN(MAX($AN22,Настройки!$D$26),$AO22)+$AL22*MIN(Настройки!$D$26,Настройки!$D$33)+$AM22*MIN(Настройки!$D$23,Настройки!$D$32)),2)) | T22: =IF(OR($W22="",$W21=""),"",24+$W22-$X21) | U22: =IF($L22="","",TRIM(IF($L22>10,"смена >10 ч (§ 3 / § 6 ArbZG) ","")&IF(AND($T22<>"",$T22<11),"отдых <11 ч (§ 5 ArbZG) ","")&IF(AND($L22>9,$J22<0.75),"перерыв <45 мин (§ 4 ArbZG) ","")&IF(AND($L22>6,$L22<=9,$J22<0.5),"перерыв <30 мин (§ 4 ArbZG)",""))) | W22: =IF($H22="","",$H22) | X22: =IF($H22="","",$I22+IF($I22<=$H22,24,0)) | Y22: =IF(OR($K22="",$K22=0),0,$L22/$K22) | Z22: =IF($A22="",0,IF(WEEKDAY($A22,2)=7,1,0)) | AA22: =IF($A22="",0,IF(WEEKDAY($A22+1,2)=7,1,0)) | AB22: =IF($A22="",0,MIN(1,COUNTIF(Feiertage!$A$4:$A$43,$A22))) | AC22: =IF($A22="",0,MIN(1,COUNTIF(Feiertage!$A$4:$A$43,$A22+1))) | AD22: =IFERROR(INDEX(Feiertage!$D$4:$D$43,MATCH($A22,Feiertage!$A$4:$A$43,0)),Настройки!$D$34) | AE22: =IFERROR(INDEX(Feiertage!$D$4:$D$43,MATCH($A22+1,Feiertage!$A$4:$A$43,0)),Настройки!$D$34) | AF22: =IF($W22="",0,MAX(0,MIN($X22,Настройки!$D$25)-MAX($W22,0))+MAX(0,MIN($X22,24)-MAX($W22,Настройки!$D$24))) | AG22: =IF($W22="",0,MAX(0,MIN($X22,24+Настройки!$D$25)-MAX($W22,24))) | AH22: =IF($W22="",0,MAX(0,MIN($X22,24)-MAX($W22,0))) | AI22: =IF($W22="",0,MAX(0,MIN($X22,48)-MAX($W22,24))) | AJ22: =($Z22*$AB22*$AH22+$AA22*$AC22*$AI22)*$Y22 | AK22: =$O22-$AJ22 | AL22: =$N22-$AJ22 | AM22: =$M22-(MAX($Z22,$AB22)*$AF22+MAX($AA22,$AC22)*$AG22)*$Y22 | AN22: =IF($G22="j",Настройки!$D$27,IF($G22="n",Настройки!$D$28,IF(Настройки!$D$29="mit FZA",Настройки!$D$27,Настройки!$D$28))) | AO22: =IF($O22=0,Настройки!$D$34,($AB22*$AH22*$AD22+$AC22*$AI22*$AE22)*$Y22/$O22)
A23: =IF(19>Настройки!$D$6,"",DATE(Настройки!$D$4,Настройки!$D$5,19)) | B23: =IF($A23="","",CHOOSE(WEEKDAY($A23,2),"Пн","Вт","Ср","Чт","Пт","Сб","Вс")) | C23: =IF($A23="","",IFERROR(INDEX(Feiertage!$B$4:$B$43,MATCH($A23,Feiertage!$A$4:$A$43,0)),"")) | D23: FREI | H23: =IF($D23="ND",Настройки!$D$42,IF($D23="TD",Настройки!$D$39,"")) | I23: =IF($D23="ND",Настройки!$D$43,IF($D23="TD",Настройки!$D$40,"")) | J23: =IF($D23="ND",Настройки!$D$44,IF($D23="TD",Настройки!$D$41,"")) | K23: =IF($H23="","",$I23-$H23+IF($I23<=$H23,24,0)) | L23: =IF($K23="","",MAX(0,$K23-$J23)) | M23: =($AF23+$AG23)*$Y23 | N23: =($Z23*$AH23+$AA23*$AI23)*$Y23 | O23: =($AB23*$AH23+$AC23*$AI23)*$Y23 | P23: =IF($L23="","",MAX(0,$L23-$O23-$AL23-$AM23)) | Q23: =ROUND(Настройки!$D$10*($AK23*$AN23+$AJ23*MAX($AN23,Настройки!$D$26)+$AL23*Настройки!$D$26+$AM23*Настройки!$D$23),2) | R23: =IF($E23<>"Arbeit",0,ROUND(MIN(Настройки!$D$10,Настройки!$D$35)*($AK23*MIN($AN23,$AO23)+$AJ23*MIN(MAX($AN23,Настройки!$D$26),$AO23)+$AL23*MIN(Настройки!$D$26,Настройки!$D$33)+$AM23*MIN(Настройки!$D$23,Настройки!$D$32)),2)) | S23: =IF($E23<>"Arbeit",0,ROUND(MIN(Настройки!$D$10,Настройки!$D$36)*($AK23*MIN($AN23,$AO23)+$AJ23*MIN(MAX($AN23,Настройки!$D$26),$AO23)+$AL23*MIN(Настройки!$D$26,Настройки!$D$33)+$AM23*MIN(Настройки!$D$23,Настройки!$D$32)),2)) | T23: =IF(OR($W23="",$W22=""),"",24+$W23-$X22) | U23: =IF($L23="","",TRIM(IF($L23>10,"смена >10 ч (§ 3 / § 6 ArbZG) ","")&IF(AND($T23<>"",$T23<11),"отдых <11 ч (§ 5 ArbZG) ","")&IF(AND($L23>9,$J23<0.75),"перерыв <45 мин (§ 4 ArbZG) ","")&IF(AND($L23>6,$L23<=9,$J23<0.5),"перерыв <30 мин (§ 4 ArbZG)",""))) | W23: =IF($H23="","",$H23) | X23: =IF($H23="","",$I23+IF($I23<=$H23,24,0)) | Y23: =IF(OR($K23="",$K23=0),0,$L23/$K23) | Z23: =IF($A23="",0,IF(WEEKDAY($A23,2)=7,1,0)) | AA23: =IF($A23="",0,IF(WEEKDAY($A23+1,2)=7,1,0)) | AB23: =IF($A23="",0,MIN(1,COUNTIF(Feiertage!$A$4:$A$43,$A23))) | AC23: =IF($A23="",0,MIN(1,COUNTIF(Feiertage!$A$4:$A$43,$A23+1))) | AD23: =IFERROR(INDEX(Feiertage!$D$4:$D$43,MATCH($A23,Feiertage!$A$4:$A$43,0)),Настройки!$D$34) | AE23: =IFERROR(INDEX(Feiertage!$D$4:$D$43,MATCH($A23+1,Feiertage!$A$4:$A$43,0)),Настройки!$D$34) | AF23: =IF($W23="",0,MAX(0,MIN($X23,Настройки!$D$25)-MAX($W23,0))+MAX(0,MIN($X23,24)-MAX($W23,Настройки!$D$24))) | AG23: =IF($W23="",0,MAX(0,MIN($X23,24+Настройки!$D$25)-MAX($W23,24))) | AH23: =IF($W23="",0,MAX(0,MIN($X23,24)-MAX($W23,0))) | AI23: =IF($W23="",0,MAX(0,MIN($X23,48)-MAX($W23,24))) | AJ23: =($Z23*$AB23*$AH23+$AA23*$AC23*$AI23)*$Y23 | AK23: =$O23-$AJ23 | AL23: =$N23-$AJ23 | AM23: =$M23-(MAX($Z23,$AB23)*$AF23+MAX($AA23,$AC23)*$AG23)*$Y23 | AN23: =IF($G23="j",Настройки!$D$27,IF($G23="n",Настройки!$D$28,IF(Настройки!$D$29="mit FZA",Настройки!$D$27,Настройки!$D$28))) | AO23: =IF($O23=0,Настройки!$D$34,($AB23*$AH23*$AD23+$AC23*$AI23*$AE23)*$Y23/$O23)
A24: =IF(20>Настройки!$D$6,"",DATE(Настройки!$D$4,Настройки!$D$5,20)) | B24: =IF($A24="","",CHOOSE(WEEKDAY($A24,2),"Пн","Вт","Ср","Чт","Пт","Сб","Вс")) | C24: =IF($A24="","",IFERROR(INDEX(Feiertage!$B$4:$B$43,MATCH($A24,Feiertage!$A$4:$A$43,0)),"")) | D24: FREI | H24: =IF($D24="ND",Настройки!$D$42,IF($D24="TD",Настройки!$D$39,"")) | I24: =IF($D24="ND",Настройки!$D$43,IF($D24="TD",Настройки!$D$40,"")) | J24: =IF($D24="ND",Настройки!$D$44,IF($D24="TD",Настройки!$D$41,"")) | K24: =IF($H24="","",$I24-$H24+IF($I24<=$H24,24,0)) | L24: =IF($K24="","",MAX(0,$K24-$J24)) | M24: =($AF24+$AG24)*$Y24 | N24: =($Z24*$AH24+$AA24*$AI24)*$Y24 | O24: =($AB24*$AH24+$AC24*$AI24)*$Y24 | P24: =IF($L24="","",MAX(0,$L24-$O24-$AL24-$AM24)) | Q24: =ROUND(Настройки!$D$10*($AK24*$AN24+$AJ24*MAX($AN24,Настройки!$D$26)+$AL24*Настройки!$D$26+$AM24*Настройки!$D$23),2) | R24: =IF($E24<>"Arbeit",0,ROUND(MIN(Настройки!$D$10,Настройки!$D$35)*($AK24*MIN($AN24,$AO24)+$AJ24*MIN(MAX($AN24,Настройки!$D$26),$AO24)+$AL24*MIN(Настройки!$D$26,Настройки!$D$33)+$AM24*MIN(Настройки!$D$23,Настройки!$D$32)),2)) | S24: =IF($E24<>"Arbeit",0,ROUND(MIN(Настройки!$D$10,Настройки!$D$36)*($AK24*MIN($AN24,$AO24)+$AJ24*MIN(MAX($AN24,Настройки!$D$26),$AO24)+$AL24*MIN(Настройки!$D$26,Настройки!$D$33)+$AM24*MIN(Настройки!$D$23,Настройки!$D$32)),2)) | T24: =IF(OR($W24="",$W23=""),"",24+$W24-$X23) | U24: =IF($L24="","",TRIM(IF($L24>10,"смена >10 ч (§ 3 / § 6 ArbZG) ","")&IF(AND($T24<>"",$T24<11),"отдых <11 ч (§ 5 ArbZG) ","")&IF(AND($L24>9,$J24<0.75),"перерыв <45 мин (§ 4 ArbZG) ","")&IF(AND($L24>6,$L24<=9,$J24<0.5),"перерыв <30 мин (§ 4 ArbZG)",""))) | W24: =IF($H24="","",$H24) | X24: =IF($H24="","",$I24+IF($I24<=$H24,24,0)) | Y24: =IF(OR($K24="",$K24=0),0,$L24/$K24) | Z24: =IF($A24="",0,IF(WEEKDAY($A24,2)=7,1,0)) | AA24: =IF($A24="",0,IF(WEEKDAY($A24+1,2)=7,1,0)) | AB24: =IF($A24="",0,MIN(1,COUNTIF(Feiertage!$A$4:$A$43,$A24))) | AC24: =IF($A24="",0,MIN(1,COUNTIF(Feiertage!$A$4:$A$43,$A24+1))) | AD24: =IFERROR(INDEX(Feiertage!$D$4:$D$43,MATCH($A24,Feiertage!$A$4:$A$43,0)),Настройки!$D$34) | AE24: =IFERROR(INDEX(Feiertage!$D$4:$D$43,MATCH($A24+1,Feiertage!$A$4:$A$43,0)),Настройки!$D$34) | AF24: =IF($W24="",0,MAX(0,MIN($X24,Настройки!$D$25)-MAX($W24,0))+MAX(0,MIN($X24,24)-MAX($W24,Настройки!$D$24))) | AG24: =IF($W24="",0,MAX(0,MIN($X24,24+Настройки!$D$25)-MAX($W24,24))) | AH24: =IF($W24="",0,MAX(0,MIN($X24,24)-MAX($W24,0))) | AI24: =IF($W24="",0,MAX(0,MIN($X24,48)-MAX($W24,24))) | AJ24: =($Z24*$AB24*$AH24+$AA24*$AC24*$AI24)*$Y24 | AK24: =$O24-$AJ24 | AL24: =$N24-$AJ24 | AM24: =$M24-(MAX($Z24,$AB24)*$AF24+MAX($AA24,$AC24)*$AG24)*$Y24 | AN24: =IF($G24="j",Настройки!$D$27,IF($G24="n",Настройки!$D$28,IF(Настройки!$D$29="mit FZA",Настройки!$D$27,Настройки!$D$28))) | AO24: =IF($O24=0,Настройки!$D$34,($AB24*$AH24*$AD24+$AC24*$AI24*$AE24)*$Y24/$O24)
A25: =IF(21>Настройки!$D$6,"",DATE(Настройки!$D$4,Настройки!$D$5,21)) | B25: =IF($A25="","",CHOOSE(WEEKDAY($A25,2),"Пн","Вт","Ср","Чт","Пт","Сб","Вс")) | C25: =IF($A25="","",IFERROR(INDEX(Feiertage!$B$4:$B$43,MATCH($A25,Feiertage!$A$4:$A$43,0)),"")) | D25: FREI | H25: =IF($D25="ND",Настройки!$D$42,IF($D25="TD",Настройки!$D$39,"")) | I25: =IF($D25="ND",Настройки!$D$43,IF($D25="TD",Настройки!$D$40,"")) | J25: =IF($D25="ND",Настройки!$D$44,IF($D25="TD",Настройки!$D$41,"")) | K25: =IF($H25="","",$I25-$H25+IF($I25<=$H25,24,0)) | L25: =IF($K25="","",MAX(0,$K25-$J25)) | M25: =($AF25+$AG25)*$Y25 | N25: =($Z25*$AH25+$AA25*$AI25)*$Y25 | O25: =($AB25*$AH25+$AC25*$AI25)*$Y25 | P25: =IF($L25="","",MAX(0,$L25-$O25-$AL25-$AM25)) | Q25: =ROUND(Настройки!$D$10*($AK25*$AN25+$AJ25*MAX($AN25,Настройки!$D$26)+$AL25*Настройки!$D$26+$AM25*Настройки!$D$23),2) | R25: =IF($E25<>"Arbeit",0,ROUND(MIN(Настройки!$D$10,Настройки!$D$35)*($AK25*MIN($AN25,$AO25)+$AJ25*MIN(MAX($AN25,Настройки!$D$26),$AO25)+$AL25*MIN(Настройки!$D$26,Настройки!$D$33)+$AM25*MIN(Настройки!$D$23,Настройки!$D$32)),2)) | S25: =IF($E25<>"Arbeit",0,ROUND(MIN(Настройки!$D$10,Настройки!$D$36)*($AK25*MIN($AN25,$AO25)+$AJ25*MIN(MAX($AN25,Настройки!$D$26),$AO25)+$AL25*MIN(Настройки!$D$26,Настройки!$D$33)+$AM25*MIN(Настройки!$D$23,Настройки!$D$32)),2)) | T25: =IF(OR($W25="",$W24=""),"",24+$W25-$X24) | U25: =IF($L25="","",TRIM(IF($L25>10,"смена >10 ч (§ 3 / § 6 ArbZG) ","")&IF(AND($T25<>"",$T25<11),"отдых <11 ч (§ 5 ArbZG) ","")&IF(AND($L25>9,$J25<0.75),"перерыв <45 мин (§ 4 ArbZG) ","")&IF(AND($L25>6,$L25<=9,$J25<0.5),"перерыв <30 мин (§ 4 ArbZG)",""))) | W25: =IF($H25="","",$H25) | X25: =IF($H25="","",$I25+IF($I25<=$H25,24,0)) | Y25: =IF(OR($K25="",$K25=0),0,$L25/$K25) | Z25: =IF($A25="",0,IF(WEEKDAY($A25,2)=7,1,0)) | AA25: =IF($A25="",0,IF(WEEKDAY($A25+1,2)=7,1,0)) | AB25: =IF($A25="",0,MIN(1,COUNTIF(Feiertage!$A$4:$A$43,$A25))) | AC25: =IF($A25="",0,MIN(1,COUNTIF(Feiertage!$A$4:$A$43,$A25+1))) | AD25: =IFERROR(INDEX(Feiertage!$D$4:$D$43,MATCH($A25,Feiertage!$A$4:$A$43,0)),Настройки!$D$34) | AE25: =IFERROR(INDEX(Feiertage!$D$4:$D$43,MATCH($A25+1,Feiertage!$A$4:$A$43,0)),Настройки!$D$34) | AF25: =IF($W25="",0,MAX(0,MIN($X25,Настройки!$D$25)-MAX($W25,0))+MAX(0,MIN($X25,24)-MAX($W25,Настройки!$D$24))) | AG25: =IF($W25="",0,MAX(0,MIN($X25,24+Настройки!$D$25)-MAX($W25,24))) | AH25: =IF($W25="",0,MAX(0,MIN($X25,24)-MAX($W25,0))) | AI25: =IF($W25="",0,MAX(0,MIN($X25,48)-MAX($W25,24))) | AJ25: =($Z25*$AB25*$AH25+$AA25*$AC25*$AI25)*$Y25 | AK25: =$O25-$AJ25 | AL25: =$N25-$AJ25 | AM25: =$M25-(MAX($Z25,$AB25)*$AF25+MAX($AA25,$AC25)*$AG25)*$Y25 | AN25: =IF($G25="j",Настройки!$D$27,IF($G25="n",Настройки!$D$28,IF(Настройки!$D$29="mit FZA",Настройки!$D$27,Настройки!$D$28))) | AO25: =IF($O25=0,Настройки!$D$34,($AB25*$AH25*$AD25+$AC25*$AI25*$AE25)*$Y25/$O25)
A26: =IF(22>Настройки!$D$6,"",DATE(Настройки!$D$4,Настройки!$D$5,22)) | B26: =IF($A26="","",CHOOSE(WEEKDAY($A26,2),"Пн","Вт","Ср","Чт","Пт","Сб","Вс")) | C26: =IF($A26="","",IFERROR(INDEX(Feiertage!$B$4:$B$43,MATCH($A26,Feiertage!$A$4:$A$43,0)),"")) | D26: FREI | H26: =IF($D26="ND",Настройки!$D$42,IF($D26="TD",Настройки!$D$39,"")) | I26: =IF($D26="ND",Настройки!$D$43,IF($D26="TD",Настройки!$D$40,"")) | J26: =IF($D26="ND",Настройки!$D$44,IF($D26="TD",Настройки!$D$41,"")) | K26: =IF($H26="","",$I26-$H26+IF($I26<=$H26,24,0)) | L26: =IF($K26="","",MAX(0,$K26-$J26)) | M26: =($AF26+$AG26)*$Y26 | N26: =($Z26*$AH26+$AA26*$AI26)*$Y26 | O26: =($AB26*$AH26+$AC26*$AI26)*$Y26 | P26: =IF($L26="","",MAX(0,$L26-$O26-$AL26-$AM26)) | Q26: =ROUND(Настройки!$D$10*($AK26*$AN26+$AJ26*MAX($AN26,Настройки!$D$26)+$AL26*Настройки!$D$26+$AM26*Настройки!$D$23),2) | R26: =IF($E26<>"Arbeit",0,ROUND(MIN(Настройки!$D$10,Настройки!$D$35)*($AK26*MIN($AN26,$AO26)+$AJ26*MIN(MAX($AN26,Настройки!$D$26),$AO26)+$AL26*MIN(Настройки!$D$26,Настройки!$D$33)+$AM26*MIN(Настройки!$D$23,Настройки!$D$32)),2)) | S26: =IF($E26<>"Arbeit",0,ROUND(MIN(Настройки!$D$10,Настройки!$D$36)*($AK26*MIN($AN26,$AO26)+$AJ26*MIN(MAX($AN26,Настройки!$D$26),$AO26)+$AL26*MIN(Настройки!$D$26,Настройки!$D$33)+$AM26*MIN(Настройки!$D$23,Настройки!$D$32)),2)) | T26: =IF(OR($W26="",$W25=""),"",24+$W26-$X25) | U26: =IF($L26="","",TRIM(IF($L26>10,"смена >10 ч (§ 3 / § 6 ArbZG) ","")&IF(AND($T26<>"",$T26<11),"отдых <11 ч (§ 5 ArbZG) ","")&IF(AND($L26>9,$J26<0.75),"перерыв <45 мин (§ 4 ArbZG) ","")&IF(AND($L26>6,$L26<=9,$J26<0.5),"перерыв <30 мин (§ 4 ArbZG)",""))) | W26: =IF($H26="","",$H26) | X26: =IF($H26="","",$I26+IF($I26<=$H26,24,0)) | Y26: =IF(OR($K26="",$K26=0),0,$L26/$K26) | Z26: =IF($A26="",0,IF(WEEKDAY($A26,2)=7,1,0)) | AA26: =IF($A26="",0,IF(WEEKDAY($A26+1,2)=7,1,0)) | AB26: =IF($A26="",0,MIN(1,COUNTIF(Feiertage!$A$4:$A$43,$A26))) | AC26: =IF($A26="",0,MIN(1,COUNTIF(Feiertage!$A$4:$A$43,$A26+1))) | AD26: =IFERROR(INDEX(Feiertage!$D$4:$D$43,MATCH($A26,Feiertage!$A$4:$A$43,0)),Настройки!$D$34) | AE26: =IFERROR(INDEX(Feiertage!$D$4:$D$43,MATCH($A26+1,Feiertage!$A$4:$A$43,0)),Настройки!$D$34) | AF26: =IF($W26="",0,MAX(0,MIN($X26,Настройки!$D$25)-MAX($W26,0))+MAX(0,MIN($X26,24)-MAX($W26,Настройки!$D$24))) | AG26: =IF($W26="",0,MAX(0,MIN($X26,24+Настройки!$D$25)-MAX($W26,24))) | AH26: =IF($W26="",0,MAX(0,MIN($X26,24)-MAX($W26,0))) | AI26: =IF($W26="",0,MAX(0,MIN($X26,48)-MAX($W26,24))) | AJ26: =($Z26*$AB26*$AH26+$AA26*$AC26*$AI26)*$Y26 | AK26: =$O26-$AJ26 | AL26: =$N26-$AJ26 | AM26: =$M26-(MAX($Z26,$AB26)*$AF26+MAX($AA26,$AC26)*$AG26)*$Y26 | AN26: =IF($G26="j",Настройки!$D$27,IF($G26="n",Настройки!$D$28,IF(Настройки!$D$29="mit FZA",Настройки!$D$27,Настройки!$D$28))) | AO26: =IF($O26=0,Настройки!$D$34,($AB26*$AH26*$AD26+$AC26*$AI26*$AE26)*$Y26/$O26)
A27: =IF(23>Настройки!$D$6,"",DATE(Настройки!$D$4,Настройки!$D$5,23)) | B27: =IF($A27="","",CHOOSE(WEEKDAY($A27,2),"Пн","Вт","Ср","Чт","Пт","Сб","Вс")) | C27: =IF($A27="","",IFERROR(INDEX(Feiertage!$B$4:$B$43,MATCH($A27,Feiertage!$A$4:$A$43,0)),"")) | D27: TD | E27: Arbeit | H27: =IF($D27="ND",Настройки!$D$42,IF($D27="TD",Настройки!$D$39,"")) | I27: =IF($D27="ND",Настройки!$D$43,IF($D27="TD",Настройки!$D$40,"")) | J27: =IF($D27="ND",Настройки!$D$44,IF($D27="TD",Настройки!$D$41,"")) | K27: =IF($H27="","",$I27-$H27+IF($I27<=$H27,24,0)) | L27: =IF($K27="","",MAX(0,$K27-$J27)) | M27: =($AF27+$AG27)*$Y27 | N27: =($Z27*$AH27+$AA27*$AI27)*$Y27 | O27: =($AB27*$AH27+$AC27*$AI27)*$Y27 | P27: =IF($L27="","",MAX(0,$L27-$O27-$AL27-$AM27)) | Q27: =ROUND(Настройки!$D$10*($AK27*$AN27+$AJ27*MAX($AN27,Настройки!$D$26)+$AL27*Настройки!$D$26+$AM27*Настройки!$D$23),2) | R27: =IF($E27<>"Arbeit",0,ROUND(MIN(Настройки!$D$10,Настройки!$D$35)*($AK27*MIN($AN27,$AO27)+$AJ27*MIN(MAX($AN27,Настройки!$D$26),$AO27)+$AL27*MIN(Настройки!$D$26,Настройки!$D$33)+$AM27*MIN(Настройки!$D$23,Настройки!$D$32)),2)) | S27: =IF($E27<>"Arbeit",0,ROUND(MIN(Настройки!$D$10,Настройки!$D$36)*($AK27*MIN($AN27,$AO27)+$AJ27*MIN(MAX($AN27,Настройки!$D$26),$AO27)+$AL27*MIN(Настройки!$D$26,Настройки!$D$33)+$AM27*MIN(Настройки!$D$23,Настройки!$D$32)),2)) | T27: =IF(OR($W27="",$W26=""),"",24+$W27-$X26) | U27: =IF($L27="","",TRIM(IF($L27>10,"смена >10 ч (§ 3 / § 6 ArbZG) ","")&IF(AND($T27<>"",$T27<11),"отдых <11 ч (§ 5 ArbZG) ","")&IF(AND($L27>9,$J27<0.75),"перерыв <45 мин (§ 4 ArbZG) ","")&IF(AND($L27>6,$L27<=9,$J27<0.5),"перерыв <30 мин (§ 4 ArbZG)",""))) | W27: =IF($H27="","",$H27) | X27: =IF($H27="","",$I27+IF($I27<=$H27,24,0)) | Y27: =IF(OR($K27="",$K27=0),0,$L27/$K27) | Z27: =IF($A27="",0,IF(WEEKDAY($A27,2)=7,1,0)) | AA27: =IF($A27="",0,IF(WEEKDAY($A27+1,2)=7,1,0)) | AB27: =IF($A27="",0,MIN(1,COUNTIF(Feiertage!$A$4:$A$43,$A27))) | AC27: =IF($A27="",0,MIN(1,COUNTIF(Feiertage!$A$4:$A$43,$A27+1))) | AD27: =IFERROR(INDEX(Feiertage!$D$4:$D$43,MATCH($A27,Feiertage!$A$4:$A$43,0)),Настройки!$D$34) | AE27: =IFERROR(INDEX(Feiertage!$D$4:$D$43,MATCH($A27+1,Feiertage!$A$4:$A$43,0)),Настройки!$D$34) | AF27: =IF($W27="",0,MAX(0,MIN($X27,Настройки!$D$25)-MAX($W27,0))+MAX(0,MIN($X27,24)-MAX($W27,Настройки!$D$24))) | AG27: =IF($W27="",0,MAX(0,MIN($X27,24+Настройки!$D$25)-MAX($W27,24))) | AH27: =IF($W27="",0,MAX(0,MIN($X27,24)-MAX($W27,0))) | AI27: =IF($W27="",0,MAX(0,MIN($X27,48)-MAX($W27,24))) | AJ27: =($Z27*$AB27*$AH27+$AA27*$AC27*$AI27)*$Y27 | AK27: =$O27-$AJ27 | AL27: =$N27-$AJ27 | AM27: =$M27-(MAX($Z27,$AB27)*$AF27+MAX($AA27,$AC27)*$AG27)*$Y27 | AN27: =IF($G27="j",Настройки!$D$27,IF($G27="n",Настройки!$D$28,IF(Настройки!$D$29="mit FZA",Настройки!$D$27,Настройки!$D$28))) | AO27: =IF($O27=0,Настройки!$D$34,($AB27*$AH27*$AD27+$AC27*$AI27*$AE27)*$Y27/$O27)
A28: =IF(24>Настройки!$D$6,"",DATE(Настройки!$D$4,Настройки!$D$5,24)) | B28: =IF($A28="","",CHOOSE(WEEKDAY($A28,2),"Пн","Вт","Ср","Чт","Пт","Сб","Вс")) | C28: =IF($A28="","",IFERROR(INDEX(Feiertage!$B$4:$B$43,MATCH($A28,Feiertage!$A$4:$A$43,0)),"")) | D28: TD | E28: Arbeit | H28: =IF($D28="ND",Настройки!$D$42,IF($D28="TD",Настройки!$D$39,"")) | I28: =IF($D28="ND",Настройки!$D$43,IF($D28="TD",Настройки!$D$40,"")) | J28: =IF($D28="ND",Настройки!$D$44,IF($D28="TD",Настройки!$D$41,"")) | K28: =IF($H28="","",$I28-$H28+IF($I28<=$H28,24,0)) | L28: =IF($K28="","",MAX(0,$K28-$J28)) | M28: =($AF28+$AG28)*$Y28 | N28: =($Z28*$AH28+$AA28*$AI28)*$Y28 | O28: =($AB28*$AH28+$AC28*$AI28)*$Y28 | P28: =IF($L28="","",MAX(0,$L28-$O28-$AL28-$AM28)) | Q28: =ROUND(Настройки!$D$10*($AK28*$AN28+$AJ28*MAX($AN28,Настройки!$D$26)+$AL28*Настройки!$D$26+$AM28*Настройки!$D$23),2) | R28: =IF($E28<>"Arbeit",0,ROUND(MIN(Настройки!$D$10,Настройки!$D$35)*($AK28*MIN($AN28,$AO28)+$AJ28*MIN(MAX($AN28,Настройки!$D$26),$AO28)+$AL28*MIN(Настройки!$D$26,Настройки!$D$33)+$AM28*MIN(Настройки!$D$23,Настройки!$D$32)),2)) | S28: =IF($E28<>"Arbeit",0,ROUND(MIN(Настройки!$D$10,Настройки!$D$36)*($AK28*MIN($AN28,$AO28)+$AJ28*MIN(MAX($AN28,Настройки!$D$26),$AO28)+$AL28*MIN(Настройки!$D$26,Настройки!$D$33)+$AM28*MIN(Настройки!$D$23,Настройки!$D$32)),2)) | T28: =IF(OR($W28="",$W27=""),"",24+$W28-$X27) | U28: =IF($L28="","",TRIM(IF($L28>10,"смена >10 ч (§ 3 / § 6 ArbZG) ","")&IF(AND($T28<>"",$T28<11),"отдых <11 ч (§ 5 ArbZG) ","")&IF(AND($L28>9,$J28<0.75),"перерыв <45 мин (§ 4 ArbZG) ","")&IF(AND($L28>6,$L28<=9,$J28<0.5),"перерыв <30 мин (§ 4 ArbZG)",""))) | W28: =IF($H28="","",$H28) | X28: =IF($H28="","",$I28+IF($I28<=$H28,24,0)) | Y28: =IF(OR($K28="",$K28=0),0,$L28/$K28) | Z28: =IF($A28="",0,IF(WEEKDAY($A28,2)=7,1,0)) | AA28: =IF($A28="",0,IF(WEEKDAY($A28+1,2)=7,1,0)) | AB28: =IF($A28="",0,MIN(1,COUNTIF(Feiertage!$A$4:$A$43,$A28))) | AC28: =IF($A28="",0,MIN(1,COUNTIF(Feiertage!$A$4:$A$43,$A28+1))) | AD28: =IFERROR(INDEX(Feiertage!$D$4:$D$43,MATCH($A28,Feiertage!$A$4:$A$43,0)),Настройки!$D$34) | AE28: =IFERROR(INDEX(Feiertage!$D$4:$D$43,MATCH($A28+1,Feiertage!$A$4:$A$43,0)),Настройки!$D$34) | AF28: =IF($W28="",0,MAX(0,MIN($X28,Настройки!$D$25)-MAX($W28,0))+MAX(0,MIN($X28,24)-MAX($W28,Настройки!$D$24))) | AG28: =IF($W28="",0,MAX(0,MIN($X28,24+Настройки!$D$25)-MAX($W28,24))) | AH28: =IF($W28="",0,MAX(0,MIN($X28,24)-MAX($W28,0))) | AI28: =IF($W28="",0,MAX(0,MIN($X28,48)-MAX($W28,24))) | AJ28: =($Z28*$AB28*$AH28+$AA28*$AC28*$AI28)*$Y28 | AK28: =$O28-$AJ28 | AL28: =$N28-$AJ28 | AM28: =$M28-(MAX($Z28,$AB28)*$AF28+MAX($AA28,$AC28)*$AG28)*$Y28 | AN28: =IF($G28="j",Настройки!$D$27,IF($G28="n",Настройки!$D$28,IF(Настройки!$D$29="mit FZA",Настройки!$D$27,Настройки!$D$28))) | AO28: =IF($O28=0,Настройки!$D$34,($AB28*$AH28*$AD28+$AC28*$AI28*$AE28)*$Y28/$O28)
A29: =IF(25>Настройки!$D$6,"",DATE(Настройки!$D$4,Настройки!$D$5,25)) | B29: =IF($A29="","",CHOOSE(WEEKDAY($A29,2),"Пн","Вт","Ср","Чт","Пт","Сб","Вс")) | C29: =IF($A29="","",IFERROR(INDEX(Feiertage!$B$4:$B$43,MATCH($A29,Feiertage!$A$4:$A$43,0)),"")) | D29: TD | E29: Arbeit | F29: x | H29: =IF($D29="ND",Настройки!$D$42,IF($D29="TD",Настройки!$D$39,"")) | I29: =IF($D29="ND",Настройки!$D$43,IF($D29="TD",Настройки!$D$40,"")) | J29: =IF($D29="ND",Настройки!$D$44,IF($D29="TD",Настройки!$D$41,"")) | K29: =IF($H29="","",$I29-$H29+IF($I29<=$H29,24,0)) | L29: =IF($K29="","",MAX(0,$K29-$J29)) | M29: =($AF29+$AG29)*$Y29 | N29: =($Z29*$AH29+$AA29*$AI29)*$Y29 | O29: =($AB29*$AH29+$AC29*$AI29)*$Y29 | P29: =IF($L29="","",MAX(0,$L29-$O29-$AL29-$AM29)) | Q29: =ROUND(Настройки!$D$10*($AK29*$AN29+$AJ29*MAX($AN29,Настройки!$D$26)+$AL29*Настройки!$D$26+$AM29*Настройки!$D$23),2) | R29: =IF($E29<>"Arbeit",0,ROUND(MIN(Настройки!$D$10,Настройки!$D$35)*($AK29*MIN($AN29,$AO29)+$AJ29*MIN(MAX($AN29,Настройки!$D$26),$AO29)+$AL29*MIN(Настройки!$D$26,Настройки!$D$33)+$AM29*MIN(Настройки!$D$23,Настройки!$D$32)),2)) | S29: =IF($E29<>"Arbeit",0,ROUND(MIN(Настройки!$D$10,Настройки!$D$36)*($AK29*MIN($AN29,$AO29)+$AJ29*MIN(MAX($AN29,Настройки!$D$26),$AO29)+$AL29*MIN(Настройки!$D$26,Настройки!$D$33)+$AM29*MIN(Настройки!$D$23,Настройки!$D$32)),2)) | T29: =IF(OR($W29="",$W28=""),"",24+$W29-$X28) | U29: =IF($L29="","",TRIM(IF($L29>10,"смена >10 ч (§ 3 / § 6 ArbZG) ","")&IF(AND($T29<>"",$T29<11),"отдых <11 ч (§ 5 ArbZG) ","")&IF(AND($L29>9,$J29<0.75),"перерыв <45 мин (§ 4 ArbZG) ","")&IF(AND($L29>6,$L29<=9,$J29<0.5),"перерыв <30 мин (§ 4 ArbZG)",""))) | W29: =IF($H29="","",$H29) | X29: =IF($H29="","",$I29+IF($I29<=$H29,24,0)) | Y29: =IF(OR($K29="",$K29=0),0,$L29/$K29) | Z29: =IF($A29="",0,IF(WEEKDAY($A29,2)=7,1,0)) | AA29: =IF($A29="",0,IF(WEEKDAY($A29+1,2)=7,1,0)) | AB29: =IF($A29="",0,MIN(1,COUNTIF(Feiertage!$A$4:$A$43,$A29))) | AC29: =IF($A29="",0,MIN(1,COUNTIF(Feiertage!$A$4:$A$43,$A29+1))) | AD29: =IFERROR(INDEX(Feiertage!$D$4:$D$43,MATCH($A29,Feiertage!$A$4:$A$43,0)),Настройки!$D$34) | AE29: =IFERROR(INDEX(Feiertage!$D$4:$D$43,MATCH($A29+1,Feiertage!$A$4:$A$43,0)),Настройки!$D$34) | AF29: =IF($W29="",0,MAX(0,MIN($X29,Настройки!$D$25)-MAX($W29,0))+MAX(0,MIN($X29,24)-MAX($W29,Настройки!$D$24))) | AG29: =IF($W29="",0,MAX(0,MIN($X29,24+Настройки!$D$25)-MAX($W29,24))) | AH29: =IF($W29="",0,MAX(0,MIN($X29,24)-MAX($W29,0))) | AI29: =IF($W29="",0,MAX(0,MIN($X29,48)-MAX($W29,24))) | AJ29: =($Z29*$AB29*$AH29+$AA29*$AC29*$AI29)*$Y29 | AK29: =$O29-$AJ29 | AL29: =$N29-$AJ29 | AM29: =$M29-(MAX($Z29,$AB29)*$AF29+MAX($AA29,$AC29)*$AG29)*$Y29 | AN29: =IF($G29="j",Настройки!$D$27,IF($G29="n",Настройки!$D$28,IF(Настройки!$D$29="mit FZA",Настройки!$D$27,Настройки!$D$28))) | AO29: =IF($O29=0,Настройки!$D$34,($AB29*$AH29*$AD29+$AC29*$AI29*$AE29)*$Y29/$O29)
A30: =IF(26>Настройки!$D$6,"",DATE(Настройки!$D$4,Настройки!$D$5,26)) | B30: =IF($A30="","",CHOOSE(WEEKDAY($A30,2),"Пн","Вт","Ср","Чт","Пт","Сб","Вс")) | C30: =IF($A30="","",IFERROR(INDEX(Feiertage!$B$4:$B$43,MATCH($A30,Feiertage!$A$4:$A$43,0)),"")) | D30: FREI | H30: =IF($D30="ND",Настройки!$D$42,IF($D30="TD",Настройки!$D$39,"")) | I30: =IF($D30="ND",Настройки!$D$43,IF($D30="TD",Настройки!$D$40,"")) | J30: =IF($D30="ND",Настройки!$D$44,IF($D30="TD",Настройки!$D$41,"")) | K30: =IF($H30="","",$I30-$H30+IF($I30<=$H30,24,0)) | L30: =IF($K30="","",MAX(0,$K30-$J30)) | M30: =($AF30+$AG30)*$Y30 | N30: =($Z30*$AH30+$AA30*$AI30)*$Y30 | O30: =($AB30*$AH30+$AC30*$AI30)*$Y30 | P30: =IF($L30="","",MAX(0,$L30-$O30-$AL30-$AM30)) | Q30: =ROUND(Настройки!$D$10*($AK30*$AN30+$AJ30*MAX($AN30,Настройки!$D$26)+$AL30*Настройки!$D$26+$AM30*Настройки!$D$23),2) | R30: =IF($E30<>"Arbeit",0,ROUND(MIN(Настройки!$D$10,Настройки!$D$35)*($AK30*MIN($AN30,$AO30)+$AJ30*MIN(MAX($AN30,Настройки!$D$26),$AO30)+$AL30*MIN(Настройки!$D$26,Настройки!$D$33)+$AM30*MIN(Настройки!$D$23,Настройки!$D$32)),2)) | S30: =IF($E30<>"Arbeit",0,ROUND(MIN(Настройки!$D$10,Настройки!$D$36)*($AK30*MIN($AN30,$AO30)+$AJ30*MIN(MAX($AN30,Настройки!$D$26),$AO30)+$AL30*MIN(Настройки!$D$26,Настройки!$D$33)+$AM30*MIN(Настройки!$D$23,Настройки!$D$32)),2)) | T30: =IF(OR($W30="",$W29=""),"",24+$W30-$X29) | U30: =IF($L30="","",TRIM(IF($L30>10,"смена >10 ч (§ 3 / § 6 ArbZG) ","")&IF(AND($T30<>"",$T30<11),"отдых <11 ч (§ 5 ArbZG) ","")&IF(AND($L30>9,$J30<0.75),"перерыв <45 мин (§ 4 ArbZG) ","")&IF(AND($L30>6,$L30<=9,$J30<0.5),"перерыв <30 мин (§ 4 ArbZG)",""))) | W30: =IF($H30="","",$H30) | X30: =IF($H30="","",$I30+IF($I30<=$H30,24,0)) | Y30: =IF(OR($K30="",$K30=0),0,$L30/$K30) | Z30: =IF($A30="",0,IF(WEEKDAY($A30,2)=7,1,0)) | AA30: =IF($A30="",0,IF(WEEKDAY($A30+1,2)=7,1,0)) | AB30: =IF($A30="",0,MIN(1,COUNTIF(Feiertage!$A$4:$A$43,$A30))) | AC30: =IF($A30="",0,MIN(1,COUNTIF(Feiertage!$A$4:$A$43,$A30+1))) | AD30: =IFERROR(INDEX(Feiertage!$D$4:$D$43,MATCH($A30,Feiertage!$A$4:$A$43,0)),Настройки!$D$34) | AE30: =IFERROR(INDEX(Feiertage!$D$4:$D$43,MATCH($A30+1,Feiertage!$A$4:$A$43,0)),Настройки!$D$34) | AF30: =IF($W30="",0,MAX(0,MIN($X30,Настройки!$D$25)-MAX($W30,0))+MAX(0,MIN($X30,24)-MAX($W30,Настройки!$D$24))) | AG30: =IF($W30="",0,MAX(0,MIN($X30,24+Настройки!$D$25)-MAX($W30,24))) | AH30: =IF($W30="",0,MAX(0,MIN($X30,24)-MAX($W30,0))) | AI30: =IF($W30="",0,MAX(0,MIN($X30,48)-MAX($W30,24))) | AJ30: =($Z30*$AB30*$AH30+$AA30*$AC30*$AI30)*$Y30 | AK30: =$O30-$AJ30 | AL30: =$N30-$AJ30 | AM30: =$M30-(MAX($Z30,$AB30)*$AF30+MAX($AA30,$AC30)*$AG30)*$Y30 | AN30: =IF($G30="j",Настройки!$D$27,IF($G30="n",Настройки!$D$28,IF(Настройки!$D$29="mit FZA",Настройки!$D$27,Настройки!$D$28))) | AO30: =IF($O30=0,Настройки!$D$34,($AB30*$AH30*$AD30+$AC30*$AI30*$AE30)*$Y30/$O30)
A31: =IF(27>Настройки!$D$6,"",DATE(Настройки!$D$4,Настройки!$D$5,27)) | B31: =IF($A31="","",CHOOSE(WEEKDAY($A31,2),"Пн","Вт","Ср","Чт","Пт","Сб","Вс")) | C31: =IF($A31="","",IFERROR(INDEX(Feiertage!$B$4:$B$43,MATCH($A31,Feiertage!$A$4:$A$43,0)),"")) | D31: TD | E31: Arbeit | H31: =IF($D31="ND",Настройки!$D$42,IF($D31="TD",Настройки!$D$39,"")) | I31: =IF($D31="ND",Настройки!$D$43,IF($D31="TD",Настройки!$D$40,"")) | J31: =IF($D31="ND",Настройки!$D$44,IF($D31="TD",Настройки!$D$41,"")) | K31: =IF($H31="","",$I31-$H31+IF($I31<=$H31,24,0)) | L31: =IF($K31="","",MAX(0,$K31-$J31)) | M31: =($AF31+$AG31)*$Y31 | N31: =($Z31*$AH31+$AA31*$AI31)*$Y31 | O31: =($AB31*$AH31+$AC31*$AI31)*$Y31 | P31: =IF($L31="","",MAX(0,$L31-$O31-$AL31-$AM31)) | Q31: =ROUND(Настройки!$D$10*($AK31*$AN31+$AJ31*MAX($AN31,Настройки!$D$26)+$AL31*Настройки!$D$26+$AM31*Настройки!$D$23),2) | R31: =IF($E31<>"Arbeit",0,ROUND(MIN(Настройки!$D$10,Настройки!$D$35)*($AK31*MIN($AN31,$AO31)+$AJ31*MIN(MAX($AN31,Настройки!$D$26),$AO31)+$AL31*MIN(Настройки!$D$26,Настройки!$D$33)+$AM31*MIN(Настройки!$D$23,Настройки!$D$32)),2)) | S31: =IF($E31<>"Arbeit",0,ROUND(MIN(Настройки!$D$10,Настройки!$D$36)*($AK31*MIN($AN31,$AO31)+$AJ31*MIN(MAX($AN31,Настройки!$D$26),$AO31)+$AL31*MIN(Настройки!$D$26,Настройки!$D$33)+$AM31*MIN(Настройки!$D$23,Настройки!$D$32)),2)) | T31: =IF(OR($W31="",$W30=""),"",24+$W31-$X30) | U31: =IF($L31="","",TRIM(IF($L31>10,"смена >10 ч (§ 3 / § 6 ArbZG) ","")&IF(AND($T31<>"",$T31<11),"отдых <11 ч (§ 5 ArbZG) ","")&IF(AND($L31>9,$J31<0.75),"перерыв <45 мин (§ 4 ArbZG) ","")&IF(AND($L31>6,$L31<=9,$J31<0.5),"перерыв <30 мин (§ 4 ArbZG)",""))) | W31: =IF($H31="","",$H31) | X31: =IF($H31="","",$I31+IF($I31<=$H31,24,0)) | Y31: =IF(OR($K31="",$K31=0),0,$L31/$K31) | Z31: =IF($A31="",0,IF(WEEKDAY($A31,2)=7,1,0)) | AA31: =IF($A31="",0,IF(WEEKDAY($A31+1,2)=7,1,0)) | AB31: =IF($A31="",0,MIN(1,COUNTIF(Feiertage!$A$4:$A$43,$A31))) | AC31: =IF($A31="",0,MIN(1,COUNTIF(Feiertage!$A$4:$A$43,$A31+1))) | AD31: =IFERROR(INDEX(Feiertage!$D$4:$D$43,MATCH($A31,Feiertage!$A$4:$A$43,0)),Настройки!$D$34) | AE31: =IFERROR(INDEX(Feiertage!$D$4:$D$43,MATCH($A31+1,Feiertage!$A$4:$A$43,0)),Настройки!$D$34) | AF31: =IF($W31="",0,MAX(0,MIN($X31,Настройки!$D$25)-MAX($W31,0))+MAX(0,MIN($X31,24)-MAX($W31,Настройки!$D$24))) | AG31: =IF($W31="",0,MAX(0,MIN($X31,24+Настройки!$D$25)-MAX($W31,24))) | AH31: =IF($W31="",0,MAX(0,MIN($X31,24)-MAX($W31,0))) | AI31: =IF($W31="",0,MAX(0,MIN($X31,48)-MAX($W31,24))) | AJ31: =($Z31*$AB31*$AH31+$AA31*$AC31*$AI31)*$Y31 | AK31: =$O31-$AJ31 | AL31: =$N31-$AJ31 | AM31: =$M31-(MAX($Z31,$AB31)*$AF31+MAX($AA31,$AC31)*$AG31)*$Y31 | AN31: =IF($G31="j",Настройки!$D$27,IF($G31="n",Настройки!$D$28,IF(Настройки!$D$29="mit FZA",Настройки!$D$27,Настройки!$D$28))) | AO31: =IF($O31=0,Настройки!$D$34,($AB31*$AH31*$AD31+$AC31*$AI31*$AE31)*$Y31/$O31)
A32: =IF(28>Настройки!$D$6,"",DATE(Настройки!$D$4,Настройки!$D$5,28)) | B32: =IF($A32="","",CHOOSE(WEEKDAY($A32,2),"Пн","Вт","Ср","Чт","Пт","Сб","Вс")) | C32: =IF($A32="","",IFERROR(INDEX(Feiertage!$B$4:$B$43,MATCH($A32,Feiertage!$A$4:$A$43,0)),"")) | D32: TD | E32: Arbeit | H32: =IF($D32="ND",Настройки!$D$42,IF($D32="TD",Настройки!$D$39,"")) | I32: =IF($D32="ND",Настройки!$D$43,IF($D32="TD",Настройки!$D$40,"")) | J32: =IF($D32="ND",Настройки!$D$44,IF($D32="TD",Настройки!$D$41,"")) | K32: =IF($H32="","",$I32-$H32+IF($I32<=$H32,24,0)) | L32: =IF($K32="","",MAX(0,$K32-$J32)) | M32: =($AF32+$AG32)*$Y32 | N32: =($Z32*$AH32+$AA32*$AI32)*$Y32 | O32: =($AB32*$AH32+$AC32*$AI32)*$Y32 | P32: =IF($L32="","",MAX(0,$L32-$O32-$AL32-$AM32)) | Q32: =ROUND(Настройки!$D$10*($AK32*$AN32+$AJ32*MAX($AN32,Настройки!$D$26)+$AL32*Настройки!$D$26+$AM32*Настройки!$D$23),2) | R32: =IF($E32<>"Arbeit",0,ROUND(MIN(Настройки!$D$10,Настройки!$D$35)*($AK32*MIN($AN32,$AO32)+$AJ32*MIN(MAX($AN32,Настройки!$D$26),$AO32)+$AL32*MIN(Настройки!$D$26,Настройки!$D$33)+$AM32*MIN(Настройки!$D$23,Настройки!$D$32)),2)) | S32: =IF($E32<>"Arbeit",0,ROUND(MIN(Настройки!$D$10,Настройки!$D$36)*($AK32*MIN($AN32,$AO32)+$AJ32*MIN(MAX($AN32,Настройки!$D$26),$AO32)+$AL32*MIN(Настройки!$D$26,Настройки!$D$33)+$AM32*MIN(Настройки!$D$23,Настройки!$D$32)),2)) | T32: =IF(OR($W32="",$W31=""),"",24+$W32-$X31) | U32: =IF($L32="","",TRIM(IF($L32>10,"смена >10 ч (§ 3 / § 6 ArbZG) ","")&IF(AND($T32<>"",$T32<11),"отдых <11 ч (§ 5 ArbZG) ","")&IF(AND($L32>9,$J32<0.75),"перерыв <45 мин (§ 4 ArbZG) ","")&IF(AND($L32>6,$L32<=9,$J32<0.5),"перерыв <30 мин (§ 4 ArbZG)",""))) | W32: =IF($H32="","",$H32) | X32: =IF($H32="","",$I32+IF($I32<=$H32,24,0)) | Y32: =IF(OR($K32="",$K32=0),0,$L32/$K32) | Z32: =IF($A32="",0,IF(WEEKDAY($A32,2)=7,1,0)) | AA32: =IF($A32="",0,IF(WEEKDAY($A32+1,2)=7,1,0)) | AB32: =IF($A32="",0,MIN(1,COUNTIF(Feiertage!$A$4:$A$43,$A32))) | AC32: =IF($A32="",0,MIN(1,COUNTIF(Feiertage!$A$4:$A$43,$A32+1))) | AD32: =IFERROR(INDEX(Feiertage!$D$4:$D$43,MATCH($A32,Feiertage!$A$4:$A$43,0)),Настройки!$D$34) | AE32: =IFERROR(INDEX(Feiertage!$D$4:$D$43,MATCH($A32+1,Feiertage!$A$4:$A$43,0)),Настройки!$D$34) | AF32: =IF($W32="",0,MAX(0,MIN($X32,Настройки!$D$25)-MAX($W32,0))+MAX(0,MIN($X32,24)-MAX($W32,Настройки!$D$24))) | AG32: =IF($W32="",0,MAX(0,MIN($X32,24+Настройки!$D$25)-MAX($W32,24))) | AH32: =IF($W32="",0,MAX(0,MIN($X32,24)-MAX($W32,0))) | AI32: =IF($W32="",0,MAX(0,MIN($X32,48)-MAX($W32,24))) | AJ32: =($Z32*$AB32*$AH32+$AA32*$AC32*$AI32)*$Y32 | AK32: =$O32-$AJ32 | AL32: =$N32-$AJ32 | AM32: =$M32-(MAX($Z32,$AB32)*$AF32+MAX($AA32,$AC32)*$AG32)*$Y32 | AN32: =IF($G32="j",Настройки!$D$27,IF($G32="n",Настройки!$D$28,IF(Настройки!$D$29="mit FZA",Настройки!$D$27,Настройки!$D$28))) | AO32: =IF($O32=0,Настройки!$D$34,($AB32*$AH32*$AD32+$AC32*$AI32*$AE32)*$Y32/$O32)
A33: =IF(29>Настройки!$D$6,"",DATE(Настройки!$D$4,Настройки!$D$5,29)) | B33: =IF($A33="","",CHOOSE(WEEKDAY($A33,2),"Пн","Вт","Ср","Чт","Пт","Сб","Вс")) | C33: =IF($A33="","",IFERROR(INDEX(Feiertage!$B$4:$B$43,MATCH($A33,Feiertage!$A$4:$A$43,0)),"")) | D33: TD | E33: Arbeit | H33: =IF($D33="ND",Настройки!$D$42,IF($D33="TD",Настройки!$D$39,"")) | I33: =IF($D33="ND",Настройки!$D$43,IF($D33="TD",Настройки!$D$40,"")) | J33: =IF($D33="ND",Настройки!$D$44,IF($D33="TD",Настройки!$D$41,"")) | K33: =IF($H33="","",$I33-$H33+IF($I33<=$H33,24,0)) | L33: =IF($K33="","",MAX(0,$K33-$J33)) | M33: =($AF33+$AG33)*$Y33 | N33: =($Z33*$AH33+$AA33*$AI33)*$Y33 | O33: =($AB33*$AH33+$AC33*$AI33)*$Y33 | P33: =IF($L33="","",MAX(0,$L33-$O33-$AL33-$AM33)) | Q33: =ROUND(Настройки!$D$10*($AK33*$AN33+$AJ33*MAX($AN33,Настройки!$D$26)+$AL33*Настройки!$D$26+$AM33*Настройки!$D$23),2) | R33: =IF($E33<>"Arbeit",0,ROUND(MIN(Настройки!$D$10,Настройки!$D$35)*($AK33*MIN($AN33,$AO33)+$AJ33*MIN(MAX($AN33,Настройки!$D$26),$AO33)+$AL33*MIN(Настройки!$D$26,Настройки!$D$33)+$AM33*MIN(Настройки!$D$23,Настройки!$D$32)),2)) | S33: =IF($E33<>"Arbeit",0,ROUND(MIN(Настройки!$D$10,Настройки!$D$36)*($AK33*MIN($AN33,$AO33)+$AJ33*MIN(MAX($AN33,Настройки!$D$26),$AO33)+$AL33*MIN(Настройки!$D$26,Настройки!$D$33)+$AM33*MIN(Настройки!$D$23,Настройки!$D$32)),2)) | T33: =IF(OR($W33="",$W32=""),"",24+$W33-$X32) | U33: =IF($L33="","",TRIM(IF($L33>10,"смена >10 ч (§ 3 / § 6 ArbZG) ","")&IF(AND($T33<>"",$T33<11),"отдых <11 ч (§ 5 ArbZG) ","")&IF(AND($L33>9,$J33<0.75),"перерыв <45 мин (§ 4 ArbZG) ","")&IF(AND($L33>6,$L33<=9,$J33<0.5),"перерыв <30 мин (§ 4 ArbZG)",""))) | W33: =IF($H33="","",$H33) | X33: =IF($H33="","",$I33+IF($I33<=$H33,24,0)) | Y33: =IF(OR($K33="",$K33=0),0,$L33/$K33) | Z33: =IF($A33="",0,IF(WEEKDAY($A33,2)=7,1,0)) | AA33: =IF($A33="",0,IF(WEEKDAY($A33+1,2)=7,1,0)) | AB33: =IF($A33="",0,MIN(1,COUNTIF(Feiertage!$A$4:$A$43,$A33))) | AC33: =IF($A33="",0,MIN(1,COUNTIF(Feiertage!$A$4:$A$43,$A33+1))) | AD33: =IFERROR(INDEX(Feiertage!$D$4:$D$43,MATCH($A33,Feiertage!$A$4:$A$43,0)),Настройки!$D$34) | AE33: =IFERROR(INDEX(Feiertage!$D$4:$D$43,MATCH($A33+1,Feiertage!$A$4:$A$43,0)),Настройки!$D$34) | AF33: =IF($W33="",0,MAX(0,MIN($X33,Настройки!$D$25)-MAX($W33,0))+MAX(0,MIN($X33,24)-MAX($W33,Настройки!$D$24))) | AG33: =IF($W33="",0,MAX(0,MIN($X33,24+Настройки!$D$25)-MAX($W33,24))) | AH33: =IF($W33="",0,MAX(0,MIN($X33,24)-MAX($W33,0))) | AI33: =IF($W33="",0,MAX(0,MIN($X33,48)-MAX($W33,24))) | AJ33: =($Z33*$AB33*$AH33+$AA33*$AC33*$AI33)*$Y33 | AK33: =$O33-$AJ33 | AL33: =$N33-$AJ33 | AM33: =$M33-(MAX($Z33,$AB33)*$AF33+MAX($AA33,$AC33)*$AG33)*$Y33 | AN33: =IF($G33="j",Настройки!$D$27,IF($G33="n",Настройки!$D$28,IF(Настройки!$D$29="mit FZA",Настройки!$D$27,Настройки!$D$28))) | AO33: =IF($O33=0,Настройки!$D$34,($AB33*$AH33*$AD33+$AC33*$AI33*$AE33)*$Y33/$O33)
A34: =IF(30>Настройки!$D$6,"",DATE(Настройки!$D$4,Настройки!$D$5,30)) | B34: =IF($A34="","",CHOOSE(WEEKDAY($A34,2),"Пн","Вт","Ср","Чт","Пт","Сб","Вс")) | C34: =IF($A34="","",IFERROR(INDEX(Feiertage!$B$4:$B$43,MATCH($A34,Feiertage!$A$4:$A$43,0)),"")) | D34: TD | E34: Arbeit | H34: =IF($D34="ND",Настройки!$D$42,IF($D34="TD",Настройки!$D$39,"")) | I34: =IF($D34="ND",Настройки!$D$43,IF($D34="TD",Настройки!$D$40,"")) | J34: =IF($D34="ND",Настройки!$D$44,IF($D34="TD",Настройки!$D$41,"")) | K34: =IF($H34="","",$I34-$H34+IF($I34<=$H34,24,0)) | L34: =IF($K34="","",MAX(0,$K34-$J34)) | M34: =($AF34+$AG34)*$Y34 | N34: =($Z34*$AH34+$AA34*$AI34)*$Y34 | O34: =($AB34*$AH34+$AC34*$AI34)*$Y34 | P34: =IF($L34="","",MAX(0,$L34-$O34-$AL34-$AM34)) | Q34: =ROUND(Настройки!$D$10*($AK34*$AN34+$AJ34*MAX($AN34,Настройки!$D$26)+$AL34*Настройки!$D$26+$AM34*Настройки!$D$23),2) | R34: =IF($E34<>"Arbeit",0,ROUND(MIN(Настройки!$D$10,Настройки!$D$35)*($AK34*MIN($AN34,$AO34)+$AJ34*MIN(MAX($AN34,Настройки!$D$26),$AO34)+$AL34*MIN(Настройки!$D$26,Настройки!$D$33)+$AM34*MIN(Настройки!$D$23,Настройки!$D$32)),2)) | S34: =IF($E34<>"Arbeit",0,ROUND(MIN(Настройки!$D$10,Настройки!$D$36)*($AK34*MIN($AN34,$AO34)+$AJ34*MIN(MAX($AN34,Настройки!$D$26),$AO34)+$AL34*MIN(Настройки!$D$26,Настройки!$D$33)+$AM34*MIN(Настройки!$D$23,Настройки!$D$32)),2)) | T34: =IF(OR($W34="",$W33=""),"",24+$W34-$X33) | U34: =IF($L34="","",TRIM(IF($L34>10,"смена >10 ч (§ 3 / § 6 ArbZG) ","")&IF(AND($T34<>"",$T34<11),"отдых <11 ч (§ 5 ArbZG) ","")&IF(AND($L34>9,$J34<0.75),"перерыв <45 мин (§ 4 ArbZG) ","")&IF(AND($L34>6,$L34<=9,$J34<0.5),"перерыв <30 мин (§ 4 ArbZG)",""))) | W34: =IF($H34="","",$H34) | X34: =IF($H34="","",$I34+IF($I34<=$H34,24,0)) | Y34: =IF(OR($K34="",$K34=0),0,$L34/$K34) | Z34: =IF($A34="",0,IF(WEEKDAY($A34,2)=7,1,0)) | AA34: =IF($A34="",0,IF(WEEKDAY($A34+1,2)=7,1,0)) | AB34: =IF($A34="",0,MIN(1,COUNTIF(Feiertage!$A$4:$A$43,$A34))) | AC34: =IF($A34="",0,MIN(1,COUNTIF(Feiertage!$A$4:$A$43,$A34+1))) | AD34: =IFERROR(INDEX(Feiertage!$D$4:$D$43,MATCH($A34,Feiertage!$A$4:$A$43,0)),Настройки!$D$34) | AE34: =IFERROR(INDEX(Feiertage!$D$4:$D$43,MATCH($A34+1,Feiertage!$A$4:$A$43,0)),Настройки!$D$34) | AF34: =IF($W34="",0,MAX(0,MIN($X34,Настройки!$D$25)-MAX($W34,0))+MAX(0,MIN($X34,24)-MAX($W34,Настройки!$D$24))) | AG34: =IF($W34="",0,MAX(0,MIN($X34,24+Настройки!$D$25)-MAX($W34,24))) | AH34: =IF($W34="",0,MAX(0,MIN($X34,24)-MAX($W34,0))) | AI34: =IF($W34="",0,MAX(0,MIN($X34,48)-MAX($W34,24))) | AJ34: =($Z34*$AB34*$AH34+$AA34*$AC34*$AI34)*$Y34 | AK34: =$O34-$AJ34 | AL34: =$N34-$AJ34 | AM34: =$M34-(MAX($Z34,$AB34)*$AF34+MAX($AA34,$AC34)*$AG34)*$Y34 | AN34: =IF($G34="j",Настройки!$D$27,IF($G34="n",Настройки!$D$28,IF(Настройки!$D$29="mit FZA",Настройки!$D$27,Настройки!$D$28))) | AO34: =IF($O34=0,Настройки!$D$34,($AB34*$AH34*$AD34+$AC34*$AI34*$AE34)*$Y34/$O34)
A35: =IF(31>Настройки!$D$6,"",DATE(Настройки!$D$4,Настройки!$D$5,31)) | B35: =IF($A35="","",CHOOSE(WEEKDAY($A35,2),"Пн","Вт","Ср","Чт","Пт","Сб","Вс")) | C35: =IF($A35="","",IFERROR(INDEX(Feiertage!$B$4:$B$43,MATCH($A35,Feiertage!$A$4:$A$43,0)),"")) | D35: FREI | H35: =IF($D35="ND",Настройки!$D$42,IF($D35="TD",Настройки!$D$39,"")) | I35: =IF($D35="ND",Настройки!$D$43,IF($D35="TD",Настройки!$D$40,"")) | J35: =IF($D35="ND",Настройки!$D$44,IF($D35="TD",Настройки!$D$41,"")) | K35: =IF($H35="","",$I35-$H35+IF($I35<=$H35,24,0)) | L35: =IF($K35="","",MAX(0,$K35-$J35)) | M35: =($AF35+$AG35)*$Y35 | N35: =($Z35*$AH35+$AA35*$AI35)*$Y35 | O35: =($AB35*$AH35+$AC35*$AI35)*$Y35 | P35: =IF($L35="","",MAX(0,$L35-$O35-$AL35-$AM35)) | Q35: =ROUND(Настройки!$D$10*($AK35*$AN35+$AJ35*MAX($AN35,Настройки!$D$26)+$AL35*Настройки!$D$26+$AM35*Настройки!$D$23),2) | R35: =IF($E35<>"Arbeit",0,ROUND(MIN(Настройки!$D$10,Настройки!$D$35)*($AK35*MIN($AN35,$AO35)+$AJ35*MIN(MAX($AN35,Настройки!$D$26),$AO35)+$AL35*MIN(Настройки!$D$26,Настройки!$D$33)+$AM35*MIN(Настройки!$D$23,Настройки!$D$32)),2)) | S35: =IF($E35<>"Arbeit",0,ROUND(MIN(Настройки!$D$10,Настройки!$D$36)*($AK35*MIN($AN35,$AO35)+$AJ35*MIN(MAX($AN35,Настройки!$D$26),$AO35)+$AL35*MIN(Настройки!$D$26,Настройки!$D$33)+$AM35*MIN(Настройки!$D$23,Настройки!$D$32)),2)) | T35: =IF(OR($W35="",$W34=""),"",24+$W35-$X34) | U35: =IF($L35="","",TRIM(IF($L35>10,"смена >10 ч (§ 3 / § 6 ArbZG) ","")&IF(AND($T35<>"",$T35<11),"отдых <11 ч (§ 5 ArbZG) ","")&IF(AND($L35>9,$J35<0.75),"перерыв <45 мин (§ 4 ArbZG) ","")&IF(AND($L35>6,$L35<=9,$J35<0.5),"перерыв <30 мин (§ 4 ArbZG)",""))) | W35: =IF($H35="","",$H35) | X35: =IF($H35="","",$I35+IF($I35<=$H35,24,0)) | Y35: =IF(OR($K35="",$K35=0),0,$L35/$K35) | Z35: =IF($A35="",0,IF(WEEKDAY($A35,2)=7,1,0)) | AA35: =IF($A35="",0,IF(WEEKDAY($A35+1,2)=7,1,0)) | AB35: =IF($A35="",0,MIN(1,COUNTIF(Feiertage!$A$4:$A$43,$A35))) | AC35: =IF($A35="",0,MIN(1,COUNTIF(Feiertage!$A$4:$A$43,$A35+1))) | AD35: =IFERROR(INDEX(Feiertage!$D$4:$D$43,MATCH($A35,Feiertage!$A$4:$A$43,0)),Настройки!$D$34) | AE35: =IFERROR(INDEX(Feiertage!$D$4:$D$43,MATCH($A35+1,Feiertage!$A$4:$A$43,0)),Настройки!$D$34) | AF35: =IF($W35="",0,MAX(0,MIN($X35,Настройки!$D$25)-MAX($W35,0))+MAX(0,MIN($X35,24)-MAX($W35,Настройки!$D$24))) | AG35: =IF($W35="",0,MAX(0,MIN($X35,24+Настройки!$D$25)-MAX($W35,24))) | AH35: =IF($W35="",0,MAX(0,MIN($X35,24)-MAX($W35,0))) | AI35: =IF($W35="",0,MAX(0,MIN($X35,48)-MAX($W35,24))) | AJ35: =($Z35*$AB35*$AH35+$AA35*$AC35*$AI35)*$Y35 | AK35: =$O35-$AJ35 | AL35: =$N35-$AJ35 | AM35: =$M35-(MAX($Z35,$AB35)*$AF35+MAX($AA35,$AC35)*$AG35)*$Y35 | AN35: =IF($G35="j",Настройки!$D$27,IF($G35="n",Настройки!$D$28,IF(Настройки!$D$29="mit FZA",Настройки!$D$27,Настройки!$D$28))) | AO35: =IF($O35=0,Настройки!$D$34,($AB35*$AH35*$AD35+$AC35*$AI35*$AE35)*$Y35/$O35)
A36: ИТОГО ЗА МЕСЯЦ | F36: =COUNTIF(F5:F35,"x") | K36: =SUM(K5:K35) | L36: =SUM(L5:L35) | M36: =SUM(M5:M35) | N36: =SUM(N5:N35) | O36: =SUM(O5:O35) | P36: =SUM(P5:P35) | Q36: =SUM(Q5:Q35) | R36: =SUM(R5:R35) | S36: =SUM(S5:S35) | AJ36: =SUM(AJ5:AJ35) | AK36: =SUM(AK5:AK35) | AL36: =SUM(AL5:AL35) | AM36: =SUM(AM5:AM35)

Sheet Расчёт
A1: РАСЧЁТ ЗАРПЛАТЫ ЗА МЕСЯЦ / GEHALTSABRECHNUNG
B2: =CONCATENATE("Месяц: ",CHOOSE(Настройки!$D$5,"Январь","Февраль","Март","Апрель","Май","Июнь","Июль","Август","Сентябрь","Октябрь","Ноябрь","Декабрь")," ",Настройки!$D$4," · Alisher Karimov · Constantia Intensivpflege GmbH")
B4: A. ЧАСЫ / ARBEITSZEIT
B5: Отработано часов (факт) | C5: Ist-Stunden | D5: =Dienstplan!L36 | E5: Сумма с листа Dienstplan, включая дни отпуска и болезни
B6: Плановая норма месяца | C6: Sollstunden | D6: =ROUND(Настройки!$D$12*Настройки!$D$20,2) | E6: оклад / ставка = 173,20 ч
B7: Разница за месяц | C7: Differenz | D7: =D5-D6 | E7: «+» переработка, «−» недоработка (оклад платится полностью)
B8: Ночных часов | C8: Nachtstunden | D8: =Dienstplan!M36 | E8: 20:00–06:00
B9: Воскресных часов | C9: Sonntagsstunden | D9: =Dienstplan!N36
B10: Праздничных часов | C10: Feiertagsstunden | D10: =Dienstplan!O36
B11: Смен «Eingesprungen» | C11: Einspringdienste | D11: =Dienstplan!F36
B13: B. СЧЁТ ЧАСОВ / ARBEITSZEITKONTO
B14: Перенос из прошлого месяца | C14: Übertrag aus Vormonat | D14: =Настройки!$D$18 | E14: Впиши на листе «Настройки»
B15: Счёт часов до выплаты | C15: Stundenkonto vor Auszahlung | D15: =D14+D7
B16: Пропадает: включено в оклад | C16: pauschal abgegolten (§ 2 Abs. 3) | D16: =MIN(MAX(0,D7),Настройки!$D$14) | E16: 8 ч/мес — единственное, что договор разрешает не оплачивать
B17: Доступно к оплате | C17: auszahlbar | D17: =MAX(0,D15-D16) | E17: Отрицательный счёт к оплате не даёт — оклад всё равно выплачивается полностью
B18: Оплачено в этом месяце | C18: ausgezahlte Überstunden | D18: =IF(Настройки!$D$16="ja",MAX(0,MIN(D17,Настройки!$D$15)),0) | E18: ограничение 60 ч/мес — практика работодателя
B19: ПЕРЕНОС НА СЛЕДУЮЩИЙ МЕСЯЦ | C19: Übertrag in den Folgemonat | D19: =D15-D16-D18 | E19: Эту цифру впиши в «Настройки» следующего месяца. Минус = отработано меньше нормы, часы уходят в долг. И требуй письменного подтверждения остатка!
B20: Стоимость непогашенных часов | C20: Wert des Stundenkontos | D20: =ROUND(D19*Настройки!$D$10,2) | E20: Деньги, которые работодатель пока не выплатил. Не потеряй их из-за § 14 Ausschlussfrist
B21: Оплачено бы БЕЗ лимита 60 ч | C21: ohne 60-Stunden-Deckel | D21: =ROUND(D17*Настройки!$D$10,2) | E21: Столько работодатель должен был бы выплатить в этом месяце по § 3 Abs. 1, если бы лимита не было
B23: C. БРУТТО / BRUTTOENTGELT
B24: Оклад | C24: Grundvergütung § 3 Abs. 1 | D24: =ROUND(Настройки!$D$11*Настройки!$D$20,2) | E24: 4.676,40 € при полном месяце
B25: Оплата переработки | C25: Überstundenvergütung | D25: =ROUND(D18*Настройки!$D$10*(1+Настройки!$D$17),2) | E25: часы × 27,00 €
B26: Надбавки всего | C26: Zeitzuschläge gesamt | D26: =Dienstplan!Q36 | E26: начисляются на ВСЕ отработанные часы, включая переработку
B27: из них без подоходного налога | C27: steuerfrei § 3b EStG | D27: =Dienstplan!R36
B28: из них без соцвзносов | C28: SV-frei § 1 SvEV | D28: =Dienstplan!S36 | E28: меньше, т.к. база ограничена 25,00 €/ч
B29: облагается налогом | C29: steuerpflichtiger Anteil | D29: =D26-D27
B30: облагается взносами | C30: SV-pflichtiger Anteil | D30: =D26-D28
B31: Премии за Eingesprungen | C31: Einspringprämien | D31: =ROUND(D11*Настройки!$D$19,2) | E31: облагается полностью; сумму задай в «Настройках»
B32: БРУТТО ВСЕГО | C32: GESAMTBRUTTO | D32: =D24+D25+D26+D31
B33: Налогооблагаемое брутто | C33: steuerpflichtiges Brutto | D33: =D24+D25+D31+D29 | E33: база подоходного налога
B34: База для соцвзносов | C34: SV-Brutto | D34: =D24+D25+D31+D30 | E34: база KV/PV/RV/AV
B36: D. СОЦВЗНОСЫ (доля работника)
B37: Медицинское страхование | C37: Krankenversicherung | D37: =ROUND(MIN(D34,Настройки!$D$58)*(Настройки!$D$52/2+Настройки!$D$53/2),2) | E37: 7,3 % + половина доп. взноса
B38: Страхование по уходу | C38: Pflegeversicherung | D38: =ROUND(MIN(D34,Настройки!$D$58)*(Настройки!$D$54/2+IF(Настройки!$D$51="ja",Настройки!$D$55,0)),2) | E38: 1,8 %; доплата бездетных не применяется — есть ребёнок
B39: Пенсионное страхование | C39: Rentenversicherung | D39: =ROUND(MIN(D34,Настройки!$D$59)*Настройки!$D$56/2,2) | E39: 9,3 %
B40: Страхование по безработице | C40: Arbeitslosenversicherung | D40: =ROUND(MIN(D34,Настройки!$D$59)*Настройки!$D$57/2,2) | E40: 1,3 %
B41: СОЦВЗНОСЫ ВСЕГО | C41: SV gesamt | D41: =D37+D38+D39+D40
B43: E. НАЛОГИ
B44: Подоходный налог | C44: Lohnsteuer | D44: =Lohnsteuer!D26 | E44: налоговый класс 3 → Splittingtarif
B45: Надбавка солидарности | C45: Solidaritätszuschlag | D45: =Lohnsteuer!D31 | E45: при твоём доходе = 0
B46: Церковный налог | C46: Kirchensteuer | D46: =Lohnsteuer!D32
B47: НАЛОГИ ВСЕГО | C47: Steuern gesamt | D47: =D44+D45+D46
B49: F. НА РУКИ
B50: НЕТТО (на счёт) | C50: NETTOVERDIENST | D50: =D32-D41-D47 | E50: Выплата до 15-го числа следующего месяца (§ 3 Abs. 3)
B51: Нетто за час фактической работы | C51: Nettostundenlohn | D51: =IF(D5=0,0,ROUND(D50/D5,2))
B52: Доля отчислений | C52: Abzugsquote | D52: =IF(D32=0,0,(D41+D47)/D32)
B54: G. СПРАВОЧНО: расходы работодателя
B55: KV работодатель | C55: AG-Anteil KV | D55: =ROUND(MIN(D34,Настройки!$D$58)*(Настройки!$D$52/2+Настройки!$D$53/2),2)
B56: PV работодатель | C56: AG-Anteil PV | D56: =ROUND(MIN(D34,Настройки!$D$58)*Настройки!$D$54/2,2)
B57: RV работодатель | C57: AG-Anteil RV | D57: =ROUND(MIN(D34,Настройки!$D$59)*Настройки!$D$56/2,2)
B58: AV работодатель | C58: AG-Anteil AV | D58: =ROUND(MIN(D34,Настройки!$D$59)*Настройки!$D$57/2,2)
B59: Всего расходы работодателя | C59: Gesamtkosten Arbeitgeber | D59: =D32+D55+D56+D57+D58 | E59: без U1/U2 и страхования от несчастных случаев
B61: H. ПРОВЕРКА ПО ЗАКОНУ
B62: Ср. часов в неделю | C62: Ø Wochenarbeitszeit | D62: =ROUND(D5/(Настройки!$D$6/7),2) | E62: § 3 ArbZG: в среднем не более 48 ч/нед за 6 месяцев
B63: Смен длиннее 10 ч | C63: Dienste > 10 h | D63: =COUNTIF(Dienstplan!L5:L35,">10") | E63: § 3 ArbZG: максимум 10 ч. Для ночных § 6 Abs. 2 строже — 8 ч, до 10 ч с компенсацией за месяц
B64: Ночных смен длиннее 8 ч | C64: Nachtdienste > 8 h | D64: =COUNTIFS(Dienstplan!D5:D35,"ND",Dienstplan!L5:L35,">8") | E64: § 6 Abs. 2 ArbZG — самое серьёзное нарушение в твоём графике
B65: Нарушений отдыха 11 ч | C65: Ruhezeit < 11 h | D65: =COUNTIFS(Dienstplan!T5:T35,"<11",Dienstplan!T5:T35,">0") | E65: § 5 ArbZG; в уходе допустимо 10 ч с компенсацией в течение месяца
B66: Смен, задевающих воскресенье | C66: Sonntagsarbeit | D66: =COUNTIF(Dienstplan!N5:N35,">0") | E66: § 11 ArbZG: минимум 15 воскресений в году свободны; Ersatzruhetag в течение 2 недель
B67: Ставка ≥ Pflegemindestlohn? | C67: Pflegemindestlohn 21,03 € | D67: =IF(Настройки!$D$10>=21.03,"да / ja","НЕТ — проверить!") | E67: 7. PflegeArbbV, Pflegefachkraft с 01.07.2026

Sheet Lohnsteuer
A1: ПОДОХОДНЫЙ НАЛОГ / LOHNSTEUER 2026 — налоговый класс 3 (оценка)
B2: Метод официального Programmablaufplan: годовой прогноз → вычеты → тариф § 32a EStG → делим на 12.
G3: Коэффициенты § 32a EStG 2026
B4: 1. ИСХОДНЫЕ ДАННЫЕ | G4: 914.51 | H4: зона 1 · a
B5: Налогооблагаемое брутто за месяц | C5: steuerpflichtiger Monatslohn | D5: =Расчёт!D33 | E5: оклад + переработка + премии + облагаемая часть надбавок | G5: 1400 | H5: зона 1 · b
B6: Прогноз на год | C6: hochgerechneter Jahresarbeitslohn | D6: =ROUND(D5*12,2) | E6: как в ELStAM: месяц × 12. В месяц с большой переработкой налог удерживают завышенно — часть вернётся по Steuererklärung | G6: 173.1 | H6: зона 2 · a
B7: Налоговый класс | C7: Steuerklasse | D7: =Настройки!$D$47 | G7: 2397 | H7: зона 2 · b
G8: 1034.87 | H8: зона 2 · c
B9: 2. ВЫЧЕТЫ (в год) | G9: 0.42 | H9: зона 3 · %
B10: Вычет на работника | C10: Arbeitnehmer-Pauschbetrag | D10: =IF(Настройки!$D$47<6,Настройки!$D$62,0) | E10: § 9a Nr. 1a EStG | G10: 11135.63 | H10: зона 3 · вычет
B11: Особые расходы | C11: Sonderausgaben-Pauschbetrag | D11: =IF(Настройки!$D$47<6,Настройки!$D$63,0) | E11: § 10c EStG | G11: 0.45 | H11: зона 4 · %
B12: Одинокому родителю | C12: Entlastungsbetrag Alleinerziehende | D12: =IF(Настройки!$D$47=2,Настройки!$D$64,0) | E12: только класс 2 | G12: 19470.38 | H12: зона 4 · вычет
B14: 3. VORSORGEPAUSCHALE (§ 39b Abs. 2 S. 5 Nr. 3 EStG)
B15: Пенсионное страхование | C15: Teilbetrag Rentenversicherung | D15: =ROUND(MIN(D6,Настройки!$D$59*12)*Настройки!$D$56/2,2) | E15: 100 % доли работника
B16: Медицинское страхование | C16: Teilbetrag Krankenversicherung | D16: =ROUND(MIN(D6,Настройки!$D$58*12)*(Настройки!$D$52/2+Настройки!$D$53/2),2)
B17: Страхование по уходу | C17: Teilbetrag Pflegeversicherung | D17: =ROUND(MIN(D6,Настройки!$D$58*12)*(Настройки!$D$54/2+IF(Настройки!$D$51="ja",Настройки!$D$55,0)),2)
B18: Страхование по безработице | C18: Teilbetrag Arbeitslosenversicherung | D18: =IF(Настройки!$D$65="ja",ROUND(MIN(MIN(D6,Настройки!$D$59*12)*Настройки!$D$57/2,MAX(0,1900-D16-D17)),2),0) | E18: новое с 2026, засчитывается лишь в пределах 1.900 € вместе с KV/PV
B19: Vorsorgepauschale всего | C19: Vorsorgepauschale gesamt | D19: =D15+D16+D17+D18
B21: 4. ТАРИФ
B22: Налогооблагаемый доход | C22: zu versteuerndes Einkommen (zvE) | D22: =MAX(0,ROUNDDOWN(D6-D10-D11-D12-D19,0)) | E22: округляется вниз до полного евро
B23: Основной тариф | C23: Grundtarif § 32a Abs. 1 | D23: =IF(D22<=Настройки!$D$67,0,IF(D22<=Настройки!$D$68,ROUNDDOWN(($G$4*((D22-Настройки!$D$67)/10000)+$G$5)*((D22-Настройки!$D$67)/10000),0),IF(D22<=Настройки!$D$69,ROUNDDOWN(($G$6*((D22-Настройки!$D$68)/10000)+$G$7)*((D22-Настройки!$D$68)/10000)+$G$8,0),IF(D22<=Настройки!$D$70,ROUNDDOWN($G$9*D22-$G$10,0),ROUNDDOWN($G$11*D22-$G$12,0))))) | E23: классы 1, 2, 4
B24: Тариф со сплиттингом | C24: Splittingtarif § 32a Abs. 5 | D24: =2*(IF(ROUNDDOWN(D22/2,0)<=Настройки!$D$67,0,IF(ROUNDDOWN(D22/2,0)<=Настройки!$D$68,ROUNDDOWN(($G$4*((ROUNDDOWN(D22/2,0)-Настройки!$D$67)/10000)+$G$5)*((ROUNDDOWN(D22/2,0)-Настройки!$D$67)/10000),0),IF(ROUNDDOWN(D22/2,0)<=Настройки!$D$69,ROUNDDOWN(($G$6*((ROUNDDOWN(D22/2,0)-Настройки!$D$68)/10000)+$G$7)*((ROUNDDOWN(D22/2,0)-Настройки!$D$68)/10000)+$G$8,0),IF(ROUNDDOWN(D22/2,0)<=Настройки!$D$70,ROUNDDOWN($G$9*ROUNDDOWN(D22/2,0)-$G$10,0),ROUNDDOWN($G$11*ROUNDDOWN(D22/2,0)-$G$12,0)))))) | E24: класс 3 — твой случай
B25: Подоходный налог за год | C25: Jahreslohnsteuer | D25: =IF(Настройки!$D$47=3,D24,D23)
B26: ПОДОХОДНЫЙ НАЛОГ ЗА МЕСЯЦ | C26: Lohnsteuer monatlich | D26: =ROUND(D25/12,2)
B28: 5. SOLI И ЦЕРКОВНЫЙ НАЛОГ
B29: Порог Soli для твоего класса | C29: Soli-Freigrenze | D29: =IF(Настройки!$D$47=3,Настройки!$D$66*2,Настройки!$D$66) | E29: для класса 3 порог удваивается
B30: Soli за год | C30: Solidaritätszuschlag Jahr | D30: =IF(D25<=D29,0,ROUND(MIN(0.055*D25,0.119*(D25-D29)),2)) | E30: зона смягчения 11,9 %
B31: Soli за месяц | C31: Solidaritätszuschlag monatlich | D31: =ROUND(D30/12,2)
B32: Церковный налог за месяц | C32: Kirchensteuer monatlich | D32: =IF(Настройки!$D$48="ja",ROUND(D26*Настройки!$D$49,2),0)
B34: =IF(OR(Настройки!$D$47=5,Настройки!$D$47=6),"ВНИМАНИЕ: для классов 5 и 6 действует другой алгоритм (§ 39b Abs. 2 S. 7 EStG) — расчёт НЕ подходит.","Оценка. Официальная сумма — в Lohnabrechnung. Сверить: bmf-steuerrechner.de (там выбери Steuerklasse 3, Kinderfreibetrag 1,0)")

Sheet Контроль ArbZG
A1: КОНТРОЛЬ РАБОЧЕГО ВРЕМЕНИ / ARBEITSZEITGESETZ
B2: Считаются смены, НАЧИНАЮЩИЕСЯ в этом месяце. Стыки месяцев проверь вручную.
B4: Неделя с | C4: по | D4: Часов | E4: Смен | F4: Ночных | G4: Статус
B5: =DATE(Настройки!$D$4,Настройки!$D$5,1)-WEEKDAY(DATE(Настройки!$D$4,Настройки!$D$5,1),2)+1+7*0 | C5: =B5+6 | D5: =SUMIFS(Dienstplan!$L$5:$L$35,Dienstplan!$A$5:$A$35,">="&B5,Dienstplan!$A$5:$A$35,"<="&C5) | E5: =COUNTIFS(Dienstplan!$A$5:$A$35,">="&B5,Dienstplan!$A$5:$A$35,"<="&C5,Dienstplan!$L$5:$L$35,">0") | F5: =COUNTIFS(Dienstplan!$A$5:$A$35,">="&B5,Dienstplan!$A$5:$A$35,"<="&C5,Dienstplan!$D$5:$D$35,"ND") | G5: =IF(D5>48,"ПРЕВЫШЕНИЕ: больше 48 ч (§ 3 ArbZG)",IF(D5>40,"выше нормы 40 ч","в норме"))
B6: =DATE(Настройки!$D$4,Настройки!$D$5,1)-WEEKDAY(DATE(Настройки!$D$4,Настройки!$D$5,1),2)+1+7*1 | C6: =B6+6 | D6: =SUMIFS(Dienstplan!$L$5:$L$35,Dienstplan!$A$5:$A$35,">="&B6,Dienstplan!$A$5:$A$35,"<="&C6) | E6: =COUNTIFS(Dienstplan!$A$5:$A$35,">="&B6,Dienstplan!$A$5:$A$35,"<="&C6,Dienstplan!$L$5:$L$35,">0") | F6: =COUNTIFS(Dienstplan!$A$5:$A$35,">="&B6,Dienstplan!$A$5:$A$35,"<="&C6,Dienstplan!$D$5:$D$35,"ND") | G6: =IF(D6>48,"ПРЕВЫШЕНИЕ: больше 48 ч (§ 3 ArbZG)",IF(D6>40,"выше нормы 40 ч","в норме"))
B7: =DATE(Настройки!$D$4,Настройки!$D$5,1)-WEEKDAY(DATE(Настройки!$D$4,Настройки!$D$5,1),2)+1+7*2 | C7: =B7+6 | D7: =SUMIFS(Dienstplan!$L$5:$L$35,Dienstplan!$A$5:$A$35,">="&B7,Dienstplan!$A$5:$A$35,"<="&C7) | E7: =COUNTIFS(Dienstplan!$A$5:$A$35,">="&B7,Dienstplan!$A$5:$A$35,"<="&C7,Dienstplan!$L$5:$L$35,">0") | F7: =COUNTIFS(Dienstplan!$A$5:$A$35,">="&B7,Dienstplan!$A$5:$A$35,"<="&C7,Dienstplan!$D$5:$D$35,"ND") | G7: =IF(D7>48,"ПРЕВЫШЕНИЕ: больше 48 ч (§ 3 ArbZG)",IF(D7>40,"выше нормы 40 ч","в норме"))
B8: =DATE(Настройки!$D$4,Настройки!$D$5,1)-WEEKDAY(DATE(Настройки!$D$4,Настройки!$D$5,1),2)+1+7*3 | C8: =B8+6 | D8: =SUMIFS(Dienstplan!$L$5:$L$35,Dienstplan!$A$5:$A$35,">="&B8,Dienstplan!$A$5:$A$35,"<="&C8) | E8: =COUNTIFS(Dienstplan!$A$5:$A$35,">="&B8,Dienstplan!$A$5:$A$35,"<="&C8,Dienstplan!$L$5:$L$35,">0") | F8: =COUNTIFS(Dienstplan!$A$5:$A$35,">="&B8,Dienstplan!$A$5:$A$35,"<="&C8,Dienstplan!$D$5:$D$35,"ND") | G8: =IF(D8>48,"ПРЕВЫШЕНИЕ: больше 48 ч (§ 3 ArbZG)",IF(D8>40,"выше нормы 40 ч","в норме"))
B9: =DATE(Настройки!$D$4,Настройки!$D$5,1)-WEEKDAY(DATE(Настройки!$D$4,Настройки!$D$5,1),2)+1+7*4 | C9: =B9+6 | D9: =SUMIFS(Dienstplan!$L$5:$L$35,Dienstplan!$A$5:$A$35,">="&B9,Dienstplan!$A$5:$A$35,"<="&C9) | E9: =COUNTIFS(Dienstplan!$A$5:$A$35,">="&B9,Dienstplan!$A$5:$A$35,"<="&C9,Dienstplan!$L$5:$L$35,">0") | F9: =COUNTIFS(Dienstplan!$A$5:$A$35,">="&B9,Dienstplan!$A$5:$A$35,"<="&C9,Dienstplan!$D$5:$D$35,"ND") | G9: =IF(D9>48,"ПРЕВЫШЕНИЕ: больше 48 ч (§ 3 ArbZG)",IF(D9>40,"выше нормы 40 ч","в норме"))
B10: =DATE(Настройки!$D$4,Настройки!$D$5,1)-WEEKDAY(DATE(Настройки!$D$4,Настройки!$D$5,1),2)+1+7*5 | C10: =B10+6 | D10: =SUMIFS(Dienstplan!$L$5:$L$35,Dienstplan!$A$5:$A$35,">="&B10,Dienstplan!$A$5:$A$35,"<="&C10) | E10: =COUNTIFS(Dienstplan!$A$5:$A$35,">="&B10,Dienstplan!$A$5:$A$35,"<="&C10,Dienstplan!$L$5:$L$35,">0") | F10: =COUNTIFS(Dienstplan!$A$5:$A$35,">="&B10,Dienstplan!$A$5:$A$35,"<="&C10,Dienstplan!$D$5:$D$35,"ND") | G10: =IF(D10>48,"ПРЕВЫШЕНИЕ: больше 48 ч (§ 3 ArbZG)",IF(D10>40,"выше нормы 40 ч","в норме"))
A12: ЧТО ГОВОРИТ ЗАКОН
B13: § 3 ArbZG | C13: Рабочий день — максимум 8 ч. До 10 ч можно, только если за 6 месяцев (или 24 недели) средняя не выше 8 ч в день, то есть около 48 ч в неделю.
B14: § 4 ArbZG | C14: Перерыв: при работе более 6 ч — 30 мин, более 9 ч — 45 мин. Можно дробить по 15 мин. Более 6 ч подряд без перерыва запрещено.
B15: § 5 ArbZG | C15: Отдых между сменами 11 ч. В уходе допускается 10 ч, если в течение месяца компенсируется другой сменой отдыха в 12 ч.
B16: § 6 Abs. 2 ArbZG | C16: ГЛАВНОЕ ДЛЯ ТЕБЯ: у ночного работника смена максимум 8 ч, до 10 ч — только если за календарный месяц (или 4 недели) средняя не выше 8 ч. Твои 12-часовые ND этому не соответствуют.
B17: § 7 ArbZG | C17: Смены длиннее возможны лишь при существенной доле Bereitschaftsdienst И на основании Tarifvertrag или Betriebsvereinbarung. В EzB (п. 42) прямо указано, что работодатель НЕ связан тарифом — значит такой основы нет.
B18: § 6 Abs. 3 ArbZG | C18: Право на бесплатное медобследование каждые 3 года (после 50 лет — ежегодно), за счёт работодателя.
B19: § 6 Abs. 5 ArbZG | C19: Право на соразмерную надбавку за ночную работу ИЛИ на оплачиваемые отгулы. Ориентир BAG — 25 %; при постоянной ночной работе суды присуждали до 30 %.
B20: § 11 ArbZG | C20: Минимум 15 воскресений в году свободны. За работу в воскресенье — Ersatzruhetag в течение 2 недель, за праздник — в течение 8 недель.
B21: § 16 ArbZG | C21: Работодатель обязан фиксировать всё время сверх 8 ч и хранить записи 2 года. Веди свой учёт — он решает исход спора.
B22: § 22 ArbZG | C22: Нарушения — штраф до 15.000 € для работодателя. Жалоба: Gewerbeaufsichtsamt Hannover (Staatliches Gewerbeaufsichtsamt), анонимно тоже принимают.
B23: § 3b EStG | C23: Надбавки за ночь/воскресенье/праздник не облагаются подоходным налогом: ночь 25 %, воскресенье 50 %, праздник 125/150 %, база до 50 €/ч.
B24: § 1 SvEV | C24: От соцвзносов надбавки свободны только с базы до 25 €/ч. При ставке 27 € часть надбавок облагается взносами.
... B26: § 4 EFZG | C26: На больничном платят по принципу Lohnausfall — то, что заработал бы, включая надбавки за смены по графику.

Sheet Права и риски
A1: ПРАВА И РИСКИ — что в договоре есть, чего нет
B2: Проверено по всем 19 параграфам договора от 01.08.2026 и по EzB от 13.07.2026.
B4: Тема | C4: Что в договоре | D4: Что по закону / на практике | E4: Что делать
B5: Einspringprämie | C5: НЕТ НИ СЛОВА. § 4 Abs. 1: любые Sonderleistungen сверх договора — добровольные, права на них нет. | D5: НО § 4 Abs. 1 Satz 3: оговорка о добровольности НЕ действует, если выплата основана на индивидуальной договорённости (individuelle Vertragsabrede). Устная договорённость тоже считается, но её надо доказать. | E5: Напиши руководителю e-mail: «Bitte bestätigen Sie mir die vereinbarte Einspringprämie von … € je kurzfristig übernommenem Dienst.» Ответ по e-mail = доказательство. Без этого премию могут прекратить в любой момент.
B6: Лимит 60 ч переработки | C6: НЕТ ТАКОГО ПРАВИЛА. § 2 Abs. 3 разрешает не оплачивать только 8 ч в месяц. Всё остальное — обычное рабочее время по § 3 Abs. 1 (27 €/ч). | D6: Замена оплаты на отгулы (Freizeitausgleich) требует соглашения сторон или Betriebsvereinbarung. Работодатель не может ввести это в одностороннем порядке. Часы не пропадают — они на счёте (Arbeitszeitkonto). | E6: Само по себе накопление часов не страшно. Опасен § 14: требуй КАЖДЫЙ месяц письменное подтверждение остатка счёта часов. Это и фиксирует требование, и не даёт сроку истечь.
B7: Ausschlussfrist 3 месяца | C7: § 14: любые требования пропадают, если не заявлены письменно в течение 3 месяцев с момента, когда они стали к оплате. | D7: Зарплата за август платится 15 сентября → срок по августу истекает 15 декабря. Для перенесённых часов момент возникновения требования спорный — не рискуй. | E7: Достаточно e-mail с формулировкой: «Hiermit mache ich die Vergütung der im Monat … geleisteten … Überstunden geltend.» Храни копию. Это занимает 2 минуты и сохраняет тысячи евро.
B8: 12-часовые ночные смены | C8: § 2 Abs. 2: обязан работать в ночь, в выходные и праздники по распоряжению — «soweit dies gesetzlich zulässig ist». | D8: § 6 Abs. 2 ArbZG: у ночного работника смена максимум 8 ч, до 10 ч только с компенсацией в течение месяца. 12 ч допустимы лишь при большой доле Bereitschaftsdienst и только на базе тарифа или Betriebsvereinbarung (§ 7 ArbZG). По EzB п. 42 работодатель НЕ tarifgebunden. | E8: Оговорка «soweit gesetzlich zulässig» работает в твою пользу: сверх законного предела ты не обязан. Если давят — Gewerbeaufsichtsamt Hannover. Обращение может быть анонимным.
B9: Ночная надбавка 25 % | C9: § 3 Abs. 2 a): 25 % за 20:00–06:00. | D9: § 6 Abs. 5 ArbZG даёт право на «angemessener Zuschlag». BAG: 25 % — норма при обычной ночной работе; при Dauernachtarbeit (как у тебя — почти только ночи) суды присуждали 30 %. | E9: Реальный аргумент на переговорах о повышении. 5 % от 170 ночных часов — это около 230 € в месяц.
B10: Надбавки на переработку | C10: § 3 Abs. 2: надбавки начисляются «je Stunde auf die (Grund-)Vergütung» — на каждый час, без исключений для переработки. | D10: Значит за переработанные ночные часы надбавка 25 % тоже положена. Частая ошибка расчётчиков — начислить надбавки только на часы в пределах нормы. | E10: Сверь в Lohnabrechnung: количество часов с надбавкой должно совпасть с колонками «Ночь/Воскр./Праздн.» этого файла, а не быть меньше.
B11: Надбавки в отпуске и на больничном | C11: § 5 и § 6 отсылают к закону. | D11: § 11 BUrlG: отпускные — среднее за 13 недель ВКЛЮЧАЯ надбавки. § 4 EFZG: больничный — по принципу Lohnausfall, тоже с надбавками за смены по графику. | E11: Проверь: если в месяц с отпуском надбавки резко упали — это ошибка расчёта. Такие надбавки, в отличие от обычных, облагаются налогом (§ 3b требует фактической работы) — файл это учитывает.
B12: Праздники 135 % | C12: § 3 Abs. 2 d): 135 % за праздник без отгула, 35 % — если дают отгул. | D12: Разница огромная: 12-часовая смена в праздник — 437,40 € надбавки без отгула против 113,40 € с отгулом. Свободны от налога только 125 %, остальные 10 % облагаются. | E12: Заранее уточняй по каждому празднику: с отгулом или без. В файле есть колонка FZA — ставь j (с отгулом) или n (без).
B13: Служебная машина | C13: § 12 Abs. 1: машина предоставляется, ЛЮБОЕ личное использование запрещено — включая дорогу из дома до места работы. | D13: Раз личного использования нет, нет и geldwerter Vorteil. Правило 1 % применяться НЕ должно. | E13: Проверь Lohnabrechnung: если там есть строка «geldwerter Vorteil Pkw» или «1 %-Regelung» — это ошибка, ты платишь лишний налог и взносы.
B14: Дорога до работы | C14: § 2 Abs. 5: дорога дом–работа рабочим временем не считается. | D14: Это законно. НО поездки МЕЖДУ пациентами в течение смены — рабочее время и должны оплачиваться. | E14: Если ездишь между объектами — фиксируй это время и требуй оплаты.
B15: Отпуск | C15: § 5 Abs. 1: «по закону». В EzB стояло 15 дней — но это было для 21 ч/нед. | D15: § 3 BUrlG при 5-дневной неделе — 20 рабочих дней. Плюс дополнительный оплачиваемый отпуск по PflegeArbbV. При работе по сменам отпуск пересчитывается по фактическим рабочим дням. | E15: Требуй письменного подтверждения количества дней на полной ставке. 15 дней для Vollzeit было бы нарушением закона.
... B18: Выплата и проверка | C18: § 3 Abs. 3: 15-го числа следующего месяца, безналично. | D18: Работодатель обязан выдать понятную расчётку (§ 108 GewO) с разбивкой по видам надбавок. | E18: Каждый месяц сверяй расчётку с этим файлом. Расхождение больше пары евро — пиши сразу, не жди.

Sheet Мои данные
A1: МОИ ДАННЫЕ / PERSÖNLICHE DATEN
B2: ПОЛЯ ОСТАВЛЕНЫ ПУСТЫМИ НАМЕРЕННО: этот файл лежит в публичном репозитории GitHub. Заполни их у себя на телефоне/компьютере и НЕ загружай файл с данными обратно в репозиторий. Steuer-ID и SV-Nummer — это идентификаторы, по которым возможно мошенничество.
B4: ЛИЧНОЕ
B5: Фамилия, имя | C5: Name, Vorname | D5: Karimov, Alisher
B6: Дата рождения | C6: Geburtsdatum | D6: 07.02.1998
B7: Адрес | C7: Anschrift
B8: Номер соцстрахования | C8: Sozialversicherungsnummer
B9: Налоговый номер | C9: Steuer-Identifikationsnummer
B10: Больничная касса | C10: Krankenkasse
B11: Доп. взнос кассы, % | C11: Zusatzbeitrag
B12: НАЛОГИ
B13: Налоговый класс | C13: Steuerklasse | D13: 3
B14: Детские вычеты | C14: Kinderfreibeträge | D14: 1,0
B15: Ребёнок, дата рождения | C15: Kind, geboren am
B16: Церковный налог | C16: Kirchensteuer | D16: nein
B17: РАБОТА
B18: Работодатель | C18: Arbeitgeber | D18: Constantia Intensivpflege GmbH
B19: Адрес работодателя | C19: Anschrift AG | D19: Theaterstraße 1, 30159 Hannover
B20: Betriebsnummer | C20: Betriebsnummer | D20: 70027532
B21: Должность | C21: Tätigkeit | D21: Examinierte Pflegefachkraft, außerklinische Intensivpflege 1:1
B22: Начало работы по договору | C22: Beginn | D22: 01.08.2026
B23: Испытательный срок | C23: Probezeit | D23: в договоре не предусмотрен
B24: Контактное лицо | C24: Kontaktperson | D24: Christopher Kruhl · 0511 43834924 · info@constantia-intensiv.de

Sheet Год
A1: СВОДКА ЗА ГОД / JAHRESÜBERSICHT
B2: Каждый месяц: копия файла → расчёт → перенеси итоги сюда. Колонка «Счёт часов» — остаток переносимых часов на конец месяца.
B4: Месяц | C4: Часы | D4: Брутто | E4: Надбавки | F4: Соцвзносы | G4: Налоги | H4: Нетто | I4: Счёт часов
B5: Январь
B6: Февраль
B7: Март
B8: Апрель
B9: Май
B10: Июнь
B11: Июль
B12: Август
B13: Сентябрь
B14: Октябрь
B15: Ноябрь
B16: Декабрь
B17: ИТОГО | C17: =SUM(C5:C16) | D17: =SUM(D5:D16) | E17: =SUM(E5:E16) | F17: =SUM(F5:F16) | G17: =SUM(G5:G16) | H17: =SUM(H5:H16)
B19: Зачем это нужно:
B20: · Не пропустить срок § 14 (3 месяца) ни по одному месяцу.
B21: · Видеть, как растёт счёт неоплаченных часов — при лимите 60 ч/мес он может копиться бесконечно.
B22: · Понять, выгодна ли Steuererklärung: при неровном доходе почти всегда возвращают деньги.
B23: · Контроль среднего рабочего времени за 6 месяцев (§ 3 ArbZG — не более 48 ч/нед).
B24: · База для отпускных (§ 11 BUrlG — среднее за 13 недель, включая надбавки).

Sheet Сверка с расчёткой
A1: СВЕРКА С РЕАЛЬНОЙ РАСЧЁТКОЙ / ABGLEICH MIT DER LOHNABRECHNUNG
B2: Данные взяты дословно из Verdienstnachweis 07/2026 и 08/2026 (Constantia Intensivpflege GmbH). Колонка «Проверка» пересчитывает сумму формулой — если совпало, строка верна.
B3: АВГУСТ 2026 — Abrechnung vom 09.09.2026, выплата 14.09.2026
B4: Строка расчётки | C4: Часы | D4: Ставка | E4: % | F4: В расчётке | G4: Проверка | H4: Комментарий
B5: 101 Stundenlohn | C5: 168 | D5: 27 | F5: 4536 | G5: =ROUND($C5*$D5*IF($E5="",1,$E5),2) | H5: Норма месяца (Zeitlohn Stunden)
B6: 103 Überstdgrundvergütung | C6: 48 | D6: 27 | F6: 1296 | G6: =ROUND($C6*$D6*IF($E6="",1,$E6),2) | H6: Переработка. Та же ставка, надбавки за переработку нет
B7: 114 Nacht 25% frei | C7: 132 | D7: 27 | E7: 0.25 | F7: 891 | G7: =ROUND($C7*$D7*IF($E7="",1,$E7),2) | H7: Ночная надбавка. F F = без налога и без взносов
B8: 115 Sonntag 50% frei | C8: 44 | D8: 27 | E8: 0.5 | F8: 594 | G8: =ROUND($C8*$D8*IF($E8="",1,$E8),2) | H8: Воскресная надбавка. F F = без налога и без взносов
B9: Gesamt-Brutto | F9: 7317 | G9: =SUM($F$5:$F$8) | H9: Сумма четырёх строк выше
B10: Steuer-Brutto | F10: 5832 | H10: 4.536 + 1.296. Надбавки 891 + 594 в базу не входят — § 3b EStG
B11: Lohnsteuer | F11: -587.66 | H11: Класс 3, 1 ребёнок
B12: KV-Beitrag | F12: -511.21 | H12: 5.812,50 € (потолок) × 8,795 % = (14,6 % + 2,99 %) / 2 → доп. взнос AOK BW = 2,99 %
B13: RV-Beitrag | F13: -542.38 | H13: 5.832,00 € × 9,3 %
B14: AV-Beitrag | F14: -75.82 | H14: 5.832,00 € × 1,3 %
B15: PV-Beitrag | F15: -104.63 | H15: 5.812,50 € × 1,8 %. Доплата бездетным 0,6 % НЕ удержана — верно, ребёнок учтён («1»)
B16: Netto-Verdienst | F16: 5495.3 | H16: Всё, что осталось после налога и взносов
B17: Abschlag / Vorschuss | F17: -2000 | H17: Аванс, полученный раньше
B18: aus NB 07/2026 | F18: 117 | H18: Доплата ночных за ИЮЛЬ — см. раздел ниже. К августу отношения не имеет
B19: Auszahlungsbetrag | F19: 3612.3 | H19: Переведено на Sparkasse Hannover
B21: АВГУСТ — СХОДЯТСЯ ЛИ ЧАСЫ (числа зафиксированы, лист Dienstplan уже за сентябрь)
B22: Строка расчётки | C22: Часы | D22: Ставка | E22: % | F22: В расчётке | G22: Проверка | H22: Комментарий
B23: Отработано по графику | F23: 216 | H23: 16 ND + 2 TD = 18 смен × 12 ч
B24: Оплачено по расчётке | F24: 216 | H24: 168 (норма) + 48 (переработка)
B25: Разница | F25: =$F$23-$F$24 | H25: 0 = всё оплачено
B26: Ночных часов по графику | F26: 132 | H26: 20:00–06:00 БЕЗ тех, что попали на воскресенье — их работодатель платит как воскресные (50 %), а не как ночные (25 %)
B27: из них пришлось на воскресенье | F27: 28 | H27: Всего ночных часов по графику 160. Совпадение надбавок: платится только самая высокая — § 3 Abs. 2 договора
B28: Ночных по расчётке | F28: 132
B29: Воскресных по графику | F29: 44
B30: Воскресных по расчётке | F30: 44
B32: Изначально в графике стояли смены 19.08 и 20.08 (TD) и 31.08 (ND) — получалось 240 ч и не хватало 24 ч. После проверки: 19.08, 20.08 и 31.08 были выходными. 18 смен × 12 ч = 216 ч — ровно столько и оплачено. Недоплаты за август НЕТ.
B33: Ночные 132 ч и воскресные 44 ч сошлись с графиком копейка в копейку — это подтверждает и время смен (ND 20:00–08:00, TD 08:00–20:00), и то, что перерыв из оплаты не вычитают.
B34: Работодатель заплатил ЩЕДРЕЕ, чем написано в договоре: § 2 Abs. 3 разрешает не платить первые 8 ч переработки в месяц, но в расчётке оплачены все 216 ч (168 + 48), а не 208. Это +216,00 € брутто в твою пользу. Поэтому в «Настройках» «Переработка включена в оклад» стоит 0 — так файл повторяет расчётку. Поставь 8, если захочешь увидеть, сколько работодатель обязан минимум по договору.
B35: Почему ночных 132, а не 160: 16 ночных смен × 10 ч = 160 ночных часов, но 28 из них выпали на воскресенье. За них платят воскресные 50 %, а не ночные 25 % — надбавки не складываются. 160 − 28 = 132.
B37: ИЮЛЬ 2026 — Abrechnung vom 12.08.2026 (Eintritt 15.07.2026, 17 дней)
B38: Строка расчётки | C38: Часы | D38: Ставка | E38: % | F38: В расчётке | G38: Проверка | H38: Комментарий
B39: 101 Stundenlohn | C39: 46 | D39: 26 | F39: 1196 | G39: =ROUND($C39*$D39*IF($E39="",1,$E39),2) | H39: Ставка в июле была ещё 26,00 € (Teilzeit-Vertrag)
B40: 103 Überstdgrundvergütung | C40: 74 | D40: 26 | F40: 1924 | G40: =ROUND($C40*$D40*IF($E40="",1,$E40),2)
B41: 114 Nacht 25% frei | C41: 42 | D41: 26 | E41: 0.25 | F41: 273 | G41: =ROUND($C41*$D41*IF($E41="",1,$E41),2)
B42: 115 Sonntag 50% frei | C42: 20 | D42: 26 | E42: 0.5 | F42: 260 | G42: =ROUND($C42*$D42*IF($E42="",1,$E42),2)
B43: Gesamt-Brutto | F43: 3653 | G43: =SUM($F$39:$F$42)
B44: Lohnsteuer | F44: -853.91 | H44: СТЕРИЛЬНО МНОГО: класс 6, потому что до 31.07 числился ещё и в KRH. Это законно, но переплату вернёт Steuererklärung за 2026 — примерно 800 €
B45: Соцвзносы всего | F45: -661.28 | H45: KV 274,40 + RV 290,16 + AV 40,56 + PV 56,16
B46: Netto-Verdienst | F46: 2137.81
B47: Abschlag / Vorschuss | F47: -2000
B48: Auszahlungsbetrag | F48: 137.81
B50: ИЮЛЬ — ПЕРЕСЧЁТ (1. NB), проведён вместе с августом
B51: Строка расчётки | C51: Часы | D51: Ставка | E51: % | F51: В расчётке | G51: Проверка | H51: Комментарий
B52: N 114 Nacht 25% frei | C52: 18 | D52: 26 | E52: 0.25 | F52: 117 | G52: =ROUND($C52*$D52*IF($E52="",1,$E52),2) | H52: «N» = Nachberechnung, пересчёт задним числом. Нашли 18 неучтённых ночных часов
B53: Новый Gesamt-Brutto июля | F53: 3770 | H53: 3.653,00 + 117,00
B54: Новый Netto июля | F54: 2254.81 | H54: 2.137,81 + 117,00
B55: Уже выплачено | F55: -2137.81 | H55: 2.000,00 аванс + 137,81 перевод
B56: Доплата, проведённая в августе | F56: 117 | H56: Та самая строка «aus NB 07/2026» в августовской расчётке
B58: ВАЖНО ПО ИЮЛЮ: пересчитали только НАДБАВКУ за ночь (18 ч × 26 € × 25 %). Сами 18 часов при этом в строку 101/103 не добавили — оплаченных часов как было 120, так и осталось. Если в июльском графике смен было больше, чем на 120 ч, — это надо предъявить. Срок по июлю: 3 месяца с 15.08.2026, то есть до 15.11.2026 (§ 14 Ausschlussfrist).
B60: ЧТО ВЫЯСНИЛОСЬ ПО ХОДУ
B61: · Einspringzuschlag / Einspringprämie у работодателя НЕТ вообще — подтверждено письменно (Chris, 09/2026). В договоре её тоже нет. Поэтому в «Настройках» премия за Eingesprungen стоит 0,00 €.
B62: · Verpflegungszuschuss в расчётке отсутствует. Единственная добавка к нетто — 117,00 €, и это ночные за июль.
B63: · Строки Zeitkonto / Arbeitszeitkonto / Übertrag / Saldo в расчётке НЕТ ни одной. Счёт часов, если он ведётся, виден только в Zeitnachweis — его надо запрашивать отдельно.
B64: · Arbeitszeitkonto был прописан в СТАРОМ Teilzeit-договоре (§ 4 Abs. 1). В новом Vollzeit-договоре с 01.08.2026 такого пункта НЕТ — значит формального основания складывать часы на счёт больше не существует.
B65: · Времена надбавок подтверждены работодателем письменно (Chris, WhatsApp, сентябрь 2026): ночь 20:00–06:00, воскресенье с 00:00, и при совпадении воскресенья с ночью считается ВОСКРЕСЕНЬЕ. Именно так файл и считает. Отсюда те 28 часов в августе, что ушли из ночных (25 %) в воскресные (50 %).
B66: · ОТКРЫТО: как оплачивается ПРАЗДНИК. Договор § 3 Abs. 2 даёт +35 % с отгулом (c) или +135 % без отгула (d). Ни одной расчётки с праздником ещё не было. Первый случай — 03.10.2026, Tag der Deutschen Einheit: 12 праздничных часов, разница между вариантами ≈ 324 € брутто. Спросить заранее и проверить строку Feiertagszuschlag в расчётке за октябрь.
B67: · Доп. взнос кассы AOK Baden-Württemberg = 2,99 % (не средние 2,9 %). В «Настройках» исправлено.
B68: · Доплата бездетным в Pflegeversicherung (0,6 %) не удерживается — ребёнок учтён правильно.
B69: · Надбавки провели полностью свободными от взносов, хотя § 1 SvEV освобождает только с базы 25 €/ч. Сейчас это в твою пользу (~110 € в месяц), но уменьшает будущую пенсию на эту же базу.
B71: Сроки, которые нельзя пропустить: по июлю — до 15.11.2026, по августу — до 14.12.2026. Разговор в WhatsApp сроки НЕ прерывает, нужна письменная претензия (e-mail достаточно).
